Workbook

Sheet README
A1: NexusAI Strategic Pricing Dataset v2.0
A4: Purpose | B4: Robust synthetic B2B SaaS pricing dataset with internally consistent customer, contract, and deal lifecycles.
A5: Observation window | B5: January 2024 through December 2025.
A6: Unit of analysis | B6: One row in Deals_Raw equals one commercial opportunity.
A7: Hierarchy | B7: Customer → Contract → Opportunity.
A8: Lifecycle logic | B8: New Business starts a contract; Renewal continues it; Expansion grows an active contract; Win-back follows churn/lost renewal.
A9: Multiple same-product purchases | B9: Allowed only when Contract_ID or Business_Unit differs.
A10: Customer tenure | B10: Time from Customer_Since to each Deal_Date; not the same as contract length.
A11: Contract length | B11: Length of the specific commercial agreement, recorded per opportunity.
A12: Pricing power | B12: Not pre-scored. It should be inferred from win rate, discount, margin, renewal, and expansion outcomes.
A13: Data status | B13: Synthetic source data, deliberately robust rather than pre-analyzed.

Sheet Customer_Master
A1: Customer Master
A4: Customer_ID | B4: Customer | C4: Industry | D4: Region | E4: Sales_Territory | F4: Company_Size | G4: Strategic_Account | H4: Customer_Since | I4: Health_Score | J4: Current_Relationship_Stage
A5: C0001 | B5: LEG-0001 | C5: Legal | D5: South | E5: South Commercial | F5: SMB | G5: No | H5: 43891 | I5: 63 | J5: Mature
A6: C0002 | B6: LEG-0002 | C6: Legal | D6: South | E6: South Enterprise | F6: Enterprise | G6: Yes | H6: 44958 | I6: 74 | J6: Mature
A7: C0003 | B7: TEC-0003 | C7: Technology | D7: Northeast | E7: Northeast Commercial | F7: SMB | G7: No | H7: 44256 | I7: 87 | J7: Growing
A8: C0004 | B8: FIN-0004 | C8: Financial Services | D8: West | E8: West Commercial | F8: Mid-Market | G8: No | H8: 45383 | I8: 50 | J8: At Risk
A9: C0005 | B9: HEA-0005 | C9: Healthcare | D9: South | E9: South Commercial | F9: Mid-Market | G9: No | H9: 43952 | I9: 66 | J9: Mature
A10: C0006 | B10: LEG-0006 | C10: Legal | D10: West | E10: West Commercial | F10: Mid-Market | G10: No | H10: 45323 | I10: 73 | J10: Mature
A11: C0007 | B11: FIN-0007 | C11: Financial Services | D11: Northeast | E11: Northeast Commercial | F11: Mid-Market | G11: No | H11: 43160 | I11: 47 | J11: At Risk
A12: C0008 | B12: TEC-0008 | C12: Technology | D12: South | E12: South Enterprise | F12: Enterprise | G12: Yes | H12: 45536 | I12: 71 | J12: Mature
A13: C0009 | B13: MAN-0009 | C13: Manufacturing | D13: Midwest | E13: Midwest Commercial | F13: SMB | G13: No | H13: 44682 | I13: 38 | J13: At Risk
A14: C0010 | B14: LEG-0010 | C14: Legal | D14: West | E14: West Commercial | F14: Mid-Market | G14: No | H14: 44348 | I14: 59 | J14: Mature
A15: C0011 | B15: TEC-0011 | C15: Technology | D15: Midwest | E15: Midwest Enterprise | F15: Enterprise | G15: Yes | H15: 44197 | I15: 45 | J15: At Risk
A16: C0012 | B16: TEC-0012 | C16: Technology | D16: Midwest | E16: Midwest Commercial | F16: Mid-Market | G16: No | H16: 44531 | I16: 69 | J16: Mature
... A184: C0180 | B184: TEC-0180 | C184: Technology | D184: West | E184: West Commercial | F184: SMB | G184: No | H184: 43344 | I184: 71 | J184: Mature

Sheet Product_Catalog
A1: Product Catalog
A4: Product | B4: Reference_List_Price | C4: Typical_Cost_Rate | D4: Primary_Value_Driver | E4: Notes
A5: Nexus Insights | B5: 30000 | C5: 0.28 | D5: Research productivity | E5: Pricing power must be derived from actual outcomes
A6: Nexus Analytics | B6: 60000 | C6: 0.31 | D6: Decision analytics | E6: Pricing power must be derived from actual outcomes
A7: Nexus Compliance | B7: 85000 | C7: 0.34 | D7: Risk reduction | E7: Pricing power must be derived from actual outcomes
A8: Nexus AI Assistant | B8: 50000 | C8: 0.38 | D8: Labor automation | E8: Pricing power must be derived from actual outcomes
A9: Nexus Enterprise Suite | B9: 180000 | C9: 0.36 | D9: Integrated platform coverage | E9: Pricing power must be derived from actual outcomes

Sheet Contract_Master
A1: Contract Master
A4: Contract_ID | B4: Customer_ID | C4: Customer | D4: Business_Unit | E4: Product | F4: Contract_Start | G4: Original_Term_Years | H4: Initial_Seats | I4: Original_List_ACV | J4: Current_Status | K4: Lifecycle_Validity
A5: CT00001 | B5: C0001 | C5: LEG-0001 | D5: Sales | E5: Nexus Enterprise Suite | F5: 44551 | G5: 1 | H5: 54 | I5: 140300.39 | J5: Active | K5: Valid by generation rule
A6: CT00002 | B6: C0002 | C6: LEG-0002 | D6: Finance | E6: Nexus Enterprise Suite | F6: 45578 | G6: 1 | H6: 1133 | I6: 448091.47 | J6: Active | K6: Valid by generation rule
A7: CT00003 | B7: C0002 | C7: LEG-0002 | D7: Legal | E7: Nexus Insights | F7: 45175 | G7: 3 | H7: 1509 | I7: 79079.559 | J7: Active | K7: Valid by generation rule
A8: CT00004 | B8: C0003 | C8: TEC-0003 | D8: Legal | E8: Nexus Insights | F8: 44917 | G8: 3 | H8: 20 | I8: 24565.523 | J8: Active | K8: Valid by generation rule
A9: CT00005 | B9: C0004 | C9: FIN-0004 | D9: Finance | E9: Nexus AI Assistant | F9: 45567 | G9: 3 | H9: 176 | I9: 64148.04 | J9: Active | K9: Valid by generation rule
A10: CT00006 | B10: C0004 | C10: FIN-0004 | D10: Legal | E10: Nexus Enterprise Suite | F10: 45821 | G10: 1 | H10: 141 | I10: 223858.23 | J10: Active | K10: Valid by generation rule
A11: CT00007 | B11: C0005 | C11: HEA-0005 | D11: Technology | E11: Nexus Enterprise Suite | F11: 44568 | G11: 3 | H11: 276 | I11: 320385.64 | J11: Churned | K11: Valid by generation rule
A12: CT00008 | B12: C0005 | C12: HEA-0005 | D12: Legal | E12: Nexus Enterprise Suite | F12: 45804 | G12: 1 | H12: 110 | I12: 320597.41 | J12: Lost | K12: Valid by generation rule
A13: CT00009 | B13: C0005 | C13: HEA-0005 | D13: Finance | E13: Nexus AI Assistant | F13: 44975 | G13: 1 | H13: 99 | I13: 103727.12 | J13: Churned | K13: Valid by generation rule
A14: CT00010 | B14: C0005 | C14: HEA-0005 | D14: Legal | E14: Nexus Compliance | F14: 44702 | G14: 1 | H14: 209 | I14: 98450.21 | J14: Active | K14: Valid by generation rule
A15: CT00011 | B15: C0006 | C15: LEG-0006 | D15: Legal | E15: Nexus Compliance | F15: 45344 | G15: 1 | H15: 131 | I15: 184726.34 | J15: Lost | K15: Valid by generation rule
A16: CT00012 | B16: C0006 | C16: LEG-0006 | D16: Finance | E16: Nexus Enterprise Suite | F16: 45685 | G16: 1 | H16: 210 | I16: 259121.64 | J16: Lost | K16: Valid by generation rule
... A402: CT00398 | B402: C0180 | C402: TEC-0180 | D402: Legal | E402: Nexus Analytics | F402: 45831 | G402: 1 | H402: 65 | I402: 56101.806 | J402: Lost | K402: Valid by generation rule

Sheet Deals_Raw
A1: Deals_Raw — Salesforce-Style Opportunity Export
A4: Deal_ID | B4: Deal_Date | C4: Customer_ID | D4: Customer | E4: Contract_ID | F4: Business_Unit | G4: Industry | H4: Region | I4: Sales_Territory | J4: Company_Size | K4: Strategic_Account | L4: Customer_Since | M4: Health_Score | N4: Product | O4: Deal_Type | P4: Expansion_Type | Q4: Contract_Years | R4: Seats | S4: Sales_Rep | T4: List_ACV | U4: List_TCV | V4: Discount_Requested | W4: Discount_Approved | X4: Competitor_Gap_vs_Us | Y4: Discount_Reason | Z4: Approval_Level | AA4: Final_Price_ACV | AB4: Final_Price_TCV | AC4: Cost_to_Serve | AD4: Proposed_Gross_Profit | AE4: Proposed_Gross_Margin | AF4: Deal_Status | AG4: Renewed | AH4: Expanded | AI4: Winback_Flag | AJ4: Realized_Revenue | AK4: Realized_Gross_Profit | AL4: Lifecycle_Notes | AM4: Validated_Annual_Final_Price | AN4: Validated_Total_Final_Price2 | AO4: Validated_Grossprofit | AP4: Validated_GrossMargin | AQ4: updated Validated_Annual_Final_Price | AR4: updated Validated_Total_Final_Price2 | AS4: updated Validated_Grossprofit | AT4: Updated Validated GrossMargin | AU4: Approved discount band | AV4: Won Deals | AW4: Column1
A5: D00003 | B5: 45646 | C5: C0001 | D5: LEG-0001 | E5: CT00001 | F5: Sales | G5: Legal | H5: South | I5: South Commercial | J5: SMB | K5: No | L5: 43891 | M5: 63 | N5: Nexus Enterprise Suite | O5: Renewal | Q5: 1 | R5: 54 | S5: M. Johnson | T5: 157663.13 | U5: =T5*DealsRawTable[[#This Row],[Contract_Years]] -> 157663.13 | V5: 0.066 | W5: 0.06 | X5: -0.119 | Y5: Renewal retention risk | Z5: Sales Manager | AA5: 148139.39 | AB5: =DealsRawTable[[#This Row],[Final_Price_ACV]]*DealsRawTable[[#This Row],[Contract_Years]] -> 148139.39 | AC5: 61223.551 | AD5: 86915.841 | AE5: 0.5867166 | AF5: Won | AG5: Yes | AI5: No | AJ5: 148139.39 | AK5: 86915.841 | AL5: Renewal of existing active contract | AM5: =ROUND(T5*(1-W5),2) -> 148203.34 | AN5: =DealsRawTable[[#This Row],[Validated_Annual_Final_Price]]*DealsRawTable[[#This Row],[Contract_Years]] -> 148203.34 | AO5: =DealsRawTable[[#This Row],[Validated_Annual_Final_Price]]-DealsRawTable[[#This Row],[Cost_to_Serve]] -> 86979.789 | AP5: =DealsRawTable[[#This Row],[Validated_Grossprofit]]/DealsRawTable[[#This Row],[Validated_Annual_Final_Price]] -> 0.58689493 | AQ5: 148203.34 | AR5: 148203.34 | AS5: 86979.789 | AT5: 0.58689493 | AU5: =IF(W5<=0.05,"0–5%", IF(W5<=0.1,"5–10%", IF(W5<=0.15,"10–15%", IF(W5<=0.2,"15–20%", IF(W5<=0.25,"20–25%", IF(W5<=0.3,"25–30%","Above 30%")))))) -> 5–10% | AV5: 116 | AW5: AVERAGEIFS($AT:$AT, $AU:$AU, AU5, $AV:$AV, "Won")
A6: D00004 | B6: 45863 | C6: C0001 | D6: LEG-0001 | E6: CT00001 | F6: Sales | G6: Legal | H6: South | I6: South Commercial | J6: SMB | K6: No | L6: 43891 | M6: 63 | N6: Nexus Enterprise Suite | O6: Expansion | P6: Module Add-on | Q6: 1 | R6: 66 | S6: M. Johnson | T6: 171556.91 | U6: =T6*DealsRawTable[[#This Row],[Contract_Years]] -> 171556.91 | V6: 0.012 | W6: 0.012 | X6: 0.079 | Y6: Expansion opportunity | Z6: Sales Manager | AA6: 169511.06 | AB6: =DealsRawTable[[#This Row],[Final_Price_ACV]]*DealsRawTable[[#This Row],[Contract_Years]] -> 169511.06 | AC6: 59147.753 | AD6: 110363.3 | AE6: 0.65106847 | AF6: Won | AH6: Yes | AI6: No | AJ6: 169511.06 | AK6: 110363.3 | AL6: Expansion allowed because contract was active | AM6: =ROUND(T6*(1-W6),2) -> 169498.23 | AN6: =DealsRawTable[[#This Row],[Validated_Annual_Final_Price]]*DealsRawTable[[#This Row],[Contract_Years]] -> 169498.23 | AO6: =DealsRawTable[[#This Row],[Validated_Annual_Final_Price]]-DealsRawTable[[#This Row],[Cost_to_Serve]] -> 110350.48 | AP6: =DealsRawTable[[#This Row],[Validated_Grossprofit]]/DealsRawTable[[#This Row],[Validated_Annual_Final_Price]] -> 0.65104206 | AQ6: 169498.23 | AR6: 169498.23 | AS6: 110350.48 | AT6: 0.65104206 | AU6: =IF(W6<=0.05,"0–5%", IF(W6<=0.1,"5–10%", IF(W6<=0.15,"10–15%", IF(W6<=0.2,"15–20%", IF(W6<=0.25,"20–25%", IF(W6<=0.3,"25–30%","Above 30%")))))) -> 0–5% | AV6: 55
A7: D00005 | B7: 46011 | C7: C0001 | D7: LEG-0001 | E7: CT00001 | F7: Sales | G7: Legal | H7: South | I7: South Commercial | J7: SMB | K7: No | L7: 43891 | M7: 63 | N7: Nexus Enterprise Suite | O7: Renewal | Q7: 1 | R7: 66 | S7: T. Brooks | T7: 183149.11 | U7: =T7*DealsRawTable[[#This Row],[Contract_Years]] -> 183149.11 | V7: 0.167 | W7: 0.148 | X7: -0.02 | Y7: Renewal retention risk | Z7: Pricing Analyst | AA7: 155982.63 | AB7: =DealsRawTable[[#This Row],[Final_Price_ACV]]*DealsRawTable[[#This Row],[Contract_Years]] -> 155982.63 | AC7: 64410.549 | AD7: 91572.082 | AE7: 0.58706589 | AF7: Won | AG7: Yes | AI7: No | AJ7: 155982.63 | AK7: 91572.082 | AL7: Renewal of existing active contract | AM7: =ROUND(T7*(1-W7),2) -> 156043.04 | AN7: =DealsRawTable[[#This Row],[Validated_Annual_Final_Price]]*DealsRawTable[[#This Row],[Contract_Years]] -> 156043.04 | AO7: =DealsRawTable[[#This Row],[Validated_Annual_Final_Price]]-DealsRawTable[[#This Row],[Cost_to_Serve]] -> 91632.491 | AP7: =DealsRawTable[[#This Row],[Validated_Grossprofit]]/DealsRawTable[[#This Row],[Validated_Annual_Final_Price]] -> 0.58722575 | AQ7: 156043.04 | AR7: 156043.04 | AS7: 91632.491 | AT7: 0.58722575 | AU7: =IF(W7<=0.05,"0–5%", IF(W7<=0.1,"5–10%", IF(W7<=0.15,"10–15%", IF(W7<=0.2,"15–20%", IF(W7<=0.25,"20–25%", IF(W7<=0.3,"25–30%","Above 30%")))))) -> 10–15% | AV7: 113
A8: D00006 | B8: 45578 | C8: C0002 | D8: LEG-0002 | E8: CT00002 | F8: Finance | G8: Legal | H8: South | I8: South Enterprise | J8: Enterprise | K8: Yes | L8: 44958 | M8: 74 | N8: Nexus Enterprise Suite | O8: New Business | Q8: 1 | R8: 1133 | S8: R. Singh | T8: 448091.47 | U8: =T8*DealsRawTable[[#This Row],[Contract_Years]] -> 448091.47 | V8: 0.211 | W8: 0.2 | X8: 0.104 | Y8: Renewal retention risk | Z8: Business Manager | AA8: 358284.32 | AB8: =DealsRawTable[[#This Row],[Final_Price_ACV]]*DealsRawTable[[#This Row],[Contract_Years]] -> 358284.32 | AC8: 180745.64 | AD8: 177538.68 | AE8: 0.49552456 | AF8: Won | AI8: No | AJ8: 358284.32 | AK8: 177538.68 | AL8: First purchase under this contract | AM8: =ROUND(T8*(1-W8),2) -> 358473.18 | AN8: =DealsRawTable[[#This Row],[Validated_Annual_Final_Price]]*DealsRawTable[[#This Row],[Contract_Years]] -> 358473.18 | AO8: =DealsRawTable[[#This Row],[Validated_Annual_Final_Price]]-DealsRawTable[[#This Row],[Cost_to_Serve]] -> 177727.54 | AP8: =DealsRawTable[[#This Row],[Validated_Grossprofit]]/DealsRawTable[[#This Row],[Validated_Annual_Final_Price]] -> 0.49579034 | AQ8: 358473.18 | AR8: 358473.18 | AS8: 177727.54 | AT8: 0.49579034 | AU8: =IF(W8<=0.05,"0–5%", IF(W8<=0.1,"5–10%", IF(W8<=0.15,"10–15%", IF(W8<=0.2,"15–20%", IF(W8<=0.25,"20–25%", IF(W8<=0.3,"25–30%","Above 30%")))))) -> 15–20% | AV8: 108
A9: D00007 | B9: 45943 | C9: C0002 | D9: LEG-0002 | E9: CT00002 | F9: Finance | G9: Legal | H9: South | I9: South Enterprise | J9: Enterprise | K9: Yes | L9: 44958 | M9: 74 | N9: Nexus Enterprise Suite | O9: Renewal | Q9: 1 | R9: 1133 | S9: L. Williams | T9: 470220.96 | U9: =T9*DealsRawTable[[#This Row],[Contract_Years]] -> 470220.96 | V9: 0.147 | W9: 0.089 | X9: -0.086 | Y9: Multi-year commitment | Z9: Sales Manager | AA9: 428472.21 | AB9: =DealsRawTable[[#This Row],[Final_Price_ACV]]*DealsRawTable[[#This Row],[Contract_Years]] -> 428472.21 | AC9: 163165.18 | AD9: 265307.03 | AE9: 0.61919309 | AF9: Won | AG9: Yes | AI9: No | AJ9: 428472.21 | AK9: 265307.03 | AL9: Renewal of existing active contract | AM9: =ROUND(T9*(1-W9),2) -> 428371.3 | AN9: =DealsRawTable[[#This Row],[Validated_Annual_Final_Price]]*DealsRawTable[[#This Row],[Contract_Years]] -> 428371.3 | AO9: =DealsRawTable[[#This Row],[Validated_Annual_Final_Price]]-DealsRawTable[[#This Row],[Cost_to_Serve]] -> 265206.12 | AP9: =DealsRawTable[[#This Row],[Validated_Grossprofit]]/DealsRawTable[[#This Row],[Validated_Annual_Final_Price]] -> 0.61910338 | AQ9: 428371.3 | AR9: 428371.3 | AS9: 265206.12 | AT9: 0.61910338 | AU9: =IF(W9<=0.05,"0–5%", IF(W9<=0.1,"5–10%", IF(W9<=0.15,"10–15%", IF(W9<=0.2,"15–20%", IF(W9<=0.25,"20–25%", IF(W9<=0.3,"25–30%","Above 30%")))))) -> 5–10% | AV9: 116
A10: D00008 | B10: 45872 | C10: C0003 | D10: TEC-0003 | E10: CT00004 | F10: Legal | G10: Technology | H10: Northeast | I10: Northeast Commercial | J10: SMB | K10: No | L10: 44256 | M10: 87 | N10: Nexus Insights | O10: Expansion | P10: Storage / Usage Expansion | Q10: 3 | R10: 30 | S10: A. Patel | T10: 30632.964 | U10: =T10*DealsRawTable[[#This Row],[Contract_Years]] -> 91898.893 | V10: 0.148 | W10: 0.137 | X10: 0.054 | Y10: Expansion opportunity | Z10: Pricing Analyst | AA10: 26446.113 | AB10: =DealsRawTable[[#This Row],[Final_Price_ACV]]*DealsRawTable[[#This Row],[Contract_Years]] -> 79338.34 | AC10: 8043.5155 | AD10: 18402.598 | AE10: 0.69585264 | AF10: Won | AH10: Yes | AI10: No | AJ10: 26446.113 | AK10: 18402.598 | AL10: Expansion allowed because contract was active | AM10: =ROUND(T10*(1-W10),2) -> 26436.25 | AN10: =DealsRawTable[[#This Row],[Validated_Annual_Final_Price]]*DealsRawTable[[#This Row],[Contract_Years]] -> 79308.75 | AO10: =DealsRawTable[[#This Row],[Validated_Annual_Final_Price]]-DealsRawTable[[#This Row],[Cost_to_Serve]] -> 18392.734 | AP10: =DealsRawTable[[#This Row],[Validated_Grossprofit]]/DealsRawTable[[#This Row],[Validated_Annual_Final_Price]] -> 0.69573916 | AQ10: 26436.25 | AR10: 79308.75 | AS10: 18392.734 | AT10: 0.69573916 | AU10: =IF(W10<=0.05,"0–5%", IF(W10<=0.1,"5–10%", IF(W10<=0.15,"10–15%", IF(W10<=0.2,"15–20%", IF(W10<=0.25,"20–25%", IF(W10<=0.3,"25–30%","Above 30%")))))) -> 10–15% | AV10: 113
A11: D00009 | B11: 46012 | C11: C0003 | D11: TEC-0003 | E11: CT00004 | F11: Legal | G11: Technology | H11: Northeast | I11: Northeast Commercial | J11: SMB | K11: No | L11: 44256 | M11: 87 | N11: Nexus Insights | O11: Renewal | Q11: 3 | R11: 30 | S11: M. Johnson | T11: 33055.576 | U11: =T11*DealsRawTable[[#This Row],[Contract_Years]] -> 99166.728 | V11: 0.154 | W11: 0.12 | X11: -0.081 | Y11: Verified competitor pressure | Z11: Pricing Analyst | AA11: 29083.19 | AB11: =DealsRawTable[[#This Row],[Final_Price_ACV]]*DealsRawTable[[#This Row],[Contract_Years]] -> 87249.57 | AC11: 8527.9708 | AD11: 20555.219 | AE11: 0.7067732 | AF11: Won | AG11: Yes | AI11: No | AJ11: 29083.19 | AK11: 20555.219 | AL11: Renewal of existing active contract | AM11: =ROUND(T11*(1-W11),2) -> 29088.91 | AN11: =DealsRawTable[[#This Row],[Validated_Annual_Final_Price]]*DealsRawTable[[#This Row],[Contract_Years]] -> 87266.73 | AO11: =DealsRawTable[[#This Row],[Validated_Annual_Final_Price]]-DealsRawTable[[#This Row],[Cost_to_Serve]] -> 20560.939 | AP11: =DealsRawTable[[#This Row],[Validated_Grossprofit]]/DealsRawTable[[#This Row],[Validated_Annual_Final_Price]] -> 0.70683086 | AQ11: 29088.91 | AR11: 87266.73 | AS11: 20560.939 | AT11: 0.70683086 | AU11: =IF(W11<=0.05,"0–5%", IF(W11<=0.1,"5–10%", IF(W11<=0.15,"10–15%", IF(W11<=0.2,"15–20%", IF(W11<=0.25,"20–25%", IF(W11<=0.3,"25–30%","Above 30%")))))) -> 10–15% | AV11: 113
A12: D00010 | B12: 45567 | C12: C0004 | D12: FIN-0004 | E12: CT00005 | F12: Finance | G12: Financial Services | H12: West | I12: West Commercial | J12: Mid-Market | K12: No | L12: 45383 | M12: 50 | N12: Nexus AI Assistant | O12: New Business | Q12: 3 | R12: 176 | S12: R. Singh | T12: 64148.04 | U12: =T12*DealsRawTable[[#This Row],[Contract_Years]] -> 192444.12 | V12: 0.189 | W12: 0.188 | X12: -0.013 | Y12: Verified competitor pressure | Z12: Pricing Analyst | AA12: 52095.758 | AB12: =DealsRawTable[[#This Row],[Final_Price_ACV]]*DealsRawTable[[#This Row],[Contract_Years]] -> 156287.27 | AC12: 27124.236 | AD12: 24971.522 | AE12: 0.47933887 | AF12: Won | AI12: No | AJ12: 52095.758 | AK12: 24971.522 | AL12: First purchase under this contract | AM12: =ROUND(T12*(1-W12),2) -> 52088.21 | AN12: =DealsRawTable[[#This Row],[Validated_Annual_Final_Price]]*DealsRawTable[[#This Row],[Contract_Years]] -> 156264.63 | AO12: =DealsRawTable[[#This Row],[Validated_Annual_Final_Price]]-DealsRawTable[[#This Row],[Cost_to_Serve]] -> 24963.974 | AP12: =DealsRawTable[[#This Row],[Validated_Grossprofit]]/DealsRawTable[[#This Row],[Validated_Annual_Final_Price]] -> 0.47926342 | AQ12: 52088.21 | AR12: 156264.63 | AS12: 24963.974 | AT12: 0.47926342 | AU12: =IF(W12<=0.05,"0–5%", IF(W12<=0.1,"5–10%", IF(W12<=0.15,"10–15%", IF(W12<=0.2,"15–20%", IF(W12<=0.25,"20–25%", IF(W12<=0.3,"25–30%","Above 30%")))))) -> 15–20% | AV12: 108
A13: D00011 | B13: 45821 | C13: C0004 | D13: FIN-0004 | E13: CT00006 | F13: Legal | G13: Financial Services | H13: West | I13: West Commercial | J13: Mid-Market | K13: No | L13: 45383 | M13: 50 | N13: Nexus Enterprise Suite | O13: New Business | Q13: 1 | R13: 141 | S13: L. Williams | T13: 223858.23 | U13: =T13*DealsRawTable[[#This Row],[Contract_Years]] -> 223858.23 | V13: 0.167 | W13: 0.119 | X13: -0.049 | Y13: Strategic logo opportunity | Z13: Pricing Analyst | AA13: 197151.93 | AB13: =DealsRawTable[[#This Row],[Final_Price_ACV]]*DealsRawTable[[#This Row],[Contract_Years]] -> 197151.93 | AC13: 94186.983 | AD13: 102964.94 | AE13: 0.52226192 | AF13: Won | AI13: No | AJ13: 197151.93 | AK13: 102964.94 | AL13: First purchase under this contract | AM13: =ROUND(T13*(1-W13),2) -> 197219.1 | AN13: =DealsRawTable[[#This Row],[Validated_Annual_Final_Price]]*DealsRawTable[[#This Row],[Contract_Years]] -> 197219.1 | AO13: =DealsRawTable[[#This Row],[Validated_Annual_Final_Price]]-DealsRawTable[[#This Row],[Cost_to_Serve]] -> 103032.12 | AP13: =DealsRawTable[[#This Row],[Validated_Grossprofit]]/DealsRawTable[[#This Row],[Validated_Annual_Final_Price]] -> 0.52242464 | AQ13: 197219.1 | AR13: 197219.1 | AS13: 103032.12 | AT13: 0.52242464 | AU13: =IF(W13<=0.05,"0–5%", IF(W13<=0.1,"5–10%", IF(W13<=0.15,"10–15%", IF(W13<=0.2,"15–20%", IF(W13<=0.25,"20–25%", IF(W13<=0.3,"25–30%","Above 30%")))))) -> 10–15% | AV13: 113
A14: D00012 | B14: 45663 | C14: C0005 | D14: HEA-0005 | E14: CT00007 | F14: Technology | G14: Healthcare | H14: South | I14: South Commercial | J14: Mid-Market | K14: No | L14: 43952 | M14: 66 | N14: Nexus Enterprise Suite | O14: Renewal | Q14: 3 | R14: 276 | S14: D. Chen | T14: 340477.39 | U14: =T14*DealsRawTable[[#This Row],[Contract_Years]] -> 1021432.2 | V14: 0.159 | W14: 0.13 | X14: -0.081 | Y14: Verified competitor pressure | Z14: Pricing Analyst | AA14: 296123.33 | AB14: =DealsRawTable[[#This Row],[Final_Price_ACV]]*DealsRawTable[[#This Row],[Contract_Years]] -> 888369.98 | AC14: 134110.72 | AD14: 162012.61 | AE14: 0.54711193 | AF14: Lost | AG14: No | AI14: No | AJ14: 0 | AK14: 0 | AL14: Renewal of existing active contract | AM14: =ROUND(T14*(1-W14),2) -> 296215.33 | AN14: =DealsRawTable[[#This Row],[Validated_Annual_Final_Price]]*DealsRawTable[[#This Row],[Contract_Years]] -> 888645.99 | AO14: =DealsRawTable[[#This Row],[Validated_Annual_Final_Price]]-DealsRawTable[[#This Row],[Cost_to_Serve]] -> 162104.61 | AP14: =DealsRawTable[[#This Row],[Validated_Grossprofit]]/DealsRawTable[[#This Row],[Validated_Annual_Final_Price]] -> 0.5472526 | AQ14: 0 | AR14: 0 | AS14: 0 | AT14: 0 | AU14: =IF(W14<=0.05,"0–5%", IF(W14<=0.1,"5–10%", IF(W14<=0.15,"10–15%", IF(W14<=0.2,"15–20%", IF(W14<=0.25,"20–25%", IF(W14<=0.3,"25–30%","Above 30%")))))) -> 10–15% | AV14: 113
A15: D00013 | B15: 45804 | C15: C0005 | D15: HEA-0005 | E15: CT00008 | F15: Legal | G15: Healthcare | H15: South | I15: South Commercial | J15: Mid-Market | K15: No | L15: 43952 | M15: 66 | N15: Nexus Enterprise Suite | O15: New Business | Q15: 1 | R15: 110 | S15: R. Singh | T15: 320597.41 | U15: =T15*DealsRawTable[[#This Row],[Contract_Years]] -> 320597.41 | V15: 0.191 | W15: 0.188 | X15: -0.007 | Y15: Procurement requirement | Z15: Pricing Analyst | AA15: 260342.6 | AB15: =DealsRawTable[[#This Row],[Final_Price_ACV]]*DealsRawTable[[#This Row],[Contract_Years]] -> 260342.6 | AC15: 126422.67 | AD15: 133919.93 | AE15: 0.51439882 | AF15: Lost | AI15: No | AJ15: 0 | AK15: 0 | AL15: First purchase under this contract | AM15: =ROUND(T15*(1-W15),2) -> 260325.1 | AN15: =DealsRawTable[[#This Row],[Validated_Annual_Final_Price]]*DealsRawTable[[#This Row],[Contract_Years]] -> 260325.1 | AO15: =DealsRawTable[[#This Row],[Validated_Annual_Final_Price]]-DealsRawTable[[#This Row],[Cost_to_Serve]] -> 133902.43 | AP15: =DealsRawTable[[#This Row],[Validated_Grossprofit]]/DealsRawTable[[#This Row],[Validated_Annual_Final_Price]] -> 0.51436618 | AQ15: 0 | AR15: 0 | AS15: 0 | AT15: 0 | AU15: =IF(W15<=0.05,"0–5%", IF(W15<=0.1,"5–10%", IF(W15<=0.15,"10–15%", IF(W15<=0.2,"15–20%", IF(W15<=0.25,"20–25%", IF(W15<=0.3,"25–30%","Above 30%")))))) -> 15–20% | AV15: 108
A16: D00014 | B16: 45340 | C16: C0005 | D16: HEA-0005 | E16: CT00009 | F16: Finance | G16: Healthcare | H16: South | I16: South Commercial | J16: Mid-Market | K16: No | L16: 43952 | M16: 66 | N16: Nexus AI Assistant | O16: Renewal | Q16: 1 | R16: 99 | S16: A. Patel | T16: 110842.81 | U16: =T16*DealsRawTable[[#This Row],[Contract_Years]] -> 110842.81 | V16: 0.185 | W16: 0.168 | X16: -0.131 | Y16: Budget constraint | Z16: Pricing Analyst | AA16: 92186.507 | AB16: =DealsRawTable[[#This Row],[Final_Price_ACV]]*DealsRawTable[[#This Row],[Contract_Years]] -> 92186.507 | AC16: 40259.459 | AD16: 51927.049 | AE16: 0.56328253 | AF16: Lost | AG16: No | AI16: No | AJ16: 0 | AK16: 0 | AL16: Renewal of existing active contract | AM16: =ROUND(T16*(1-W16),2) -> 92221.22 | AN16: =DealsRawTable[[#This Row],[Validated_Annual_Final_Price]]*DealsRawTable[[#This Row],[Contract_Years]] -> 92221.22 | AO16: =DealsRawTable[[#This Row],[Validated_Annual_Final_Price]]-DealsRawTable[[#This Row],[Cost_to_Serve]] -> 51961.761 | AP16: =DealsRawTable[[#This Row],[Validated_Grossprofit]]/DealsRawTable[[#This Row],[Validated_Annual_Final_Price]] -> 0.56344691 | AQ16: 0 | AR16: 0 | AS16: 0 | AT16: 0 | AU16: =IF(W16<=0.05,"0–5%", IF(W16<=0.1,"5–10%", IF(W16<=0.15,"10–15%", IF(W16<=0.2,"15–20%", IF(W16<=0.25,"20–25%", IF(W16<=0.3,"25–30%","Above 30%")))))) -> 15–20% | AV16: 108
A17: D00017 | B17: 45432 | C17: C0005 | D17: HEA-0005 | E17: CT00010 | F17: Legal | G17: Healthcare | H17: South | I17: South Commercial | J17: Mid-Market | K17: No | L17: 43952 | M17: 66 | N17: Nexus Compliance | O17: Renewal | Q17: 1 | R17: 209 | S17: T. Brooks | T17: 110315.32 | U17: =T17*DealsRawTable[[#This Row],[Contract_Years]] -> 110315.32 | V17: 0.137 | W17: 0.115 | X17: -0.041 | Y17: Expansion opportunity | Z17: Pricing Analyst | AA17: 97591.585 | AB17: =DealsRawTable[[#This Row],[Final_Price_ACV]]*DealsRawTable[[#This Row],[Contract_Years]] -> 97591.585 | AC17: 37804.254 | AD17: 59787.331 | AE17: 0.61262793 | AF17: Won | AG17: Yes | AI17: No | AJ17: 97591.585 | AK17: 59787.331 | AL17: Renewal of existing active contract | AM17: =ROUND(T17*(1-W17),2) -> 97629.05 | AN17: =DealsRawTable[[#This Row],[Validated_Annual_Final_Price]]*DealsRawTable[[#This Row],[Contract_Years]] -> 97629.05 | AO17: =DealsRawTable[[#This Row],[Validated_Annual_Final_Price]]-DealsRawTable[[#This Row],[Cost_to_Serve]] -> 59824.796 | AP17: =DealsRawTable[[#This Row],[Validated_Grossprofit]]/DealsRawTable[[#This Row],[Validated_Annual_Final_Price]] -> 0.61277659 | AQ17: 97629.05 | AR17: 97629.05 | AS17: 59824.796 | AT17: 0.61277659 | AU17: =IF(W17<=0.05,"0–5%", IF(W17<=0.1,"5–10%", IF(W17<=0.15,"10–15%", IF(W17<=0.2,"15–20%", IF(W17<=0.25,"20–25%", IF(W17<=0.3,"25–30%","Above 30%")))))) -> 10–15% | AV17: 113
A18: D00018 | B18: 45797 | C18: C0005 | D18: HEA-0005 | E18: CT00010 | F18: Legal | G18: Healthcare | H18: South | I18: South Commercial | J18: Mid-Market | K18: No | L18: 43952 | M18: 66 | N18: Nexus Compliance | O18: Renewal | Q18: 1 | R18: 209 | S18: M. Johnson | T18: 117035.83 | U18: =T18*DealsRawTable[[#This Row],[Contract_Years]] -> 117035.83 | V18: 0.213 | W18: 0.212 | X18: -0.001 | Y18: Budget constraint | Z18: Business Manager | AA18: 92239.591 | AB18: =DealsRawTable[[#This Row],[Final_Price_ACV]]*DealsRawTable[[#This Row],[Contract_Years]] -> 92239.591 | AC18: 45049.823 | AD18: 47189.768 | AE18: 0.51159992 | AF18: Lost | AG18: No | AI18: No | AJ18: 0 | AK18: 0 | AL18: Renewal of existing active contract | AM18: =ROUND(T18*(1-W18),2) -> 92224.24 | AN18: =DealsRawTable[[#This Row],[Validated_Annual_Final_Price]]*DealsRawTable[[#This Row],[Contract_Years]] -> 92224.24 | AO18: =DealsRawTable[[#This Row],[Validated_Annual_Final_Price]]-DealsRawTable[[#This Row],[Cost_to_Serve]] -> 47174.417 | AP18: =DealsRawTable[[#This Row],[Validated_Grossprofit]]/DealsRawTable[[#This Row],[Validated_Annual_Final_Price]] -> 0.51151863 | AQ18: 0 | AR18: 0 | AS18: 0 | AT18: 0 | AU18: =IF(W18<=0.05,"0–5%", IF(W18<=0.1,"5–10%", IF(W18<=0.15,"10–15%", IF(W18<=0.2,"15–20%", IF(W18<=0.25,"20–25%", IF(W18<=0.3,"25–30%","Above 30%")))))) -> 20–25% | AV18: 29
A19: D00019 | B19: 45925 | C19: C0005 | D19: HEA-0005 | E19: CT00010 | F19: Legal | G19: Healthcare | H19: South | I19: South Commercial | J19: Mid-Market | K19: No | L19: 43952 | M19: 66 | N19: Nexus Compliance | O19: Win-back | Q19: 1 | R19: 209 | S19: D. Chen | T19: 117035.83 | U19: =T19*DealsRawTable[[#This Row],[Contract_Years]] -> 117035.83 | V19: 0.274 | W19: 0.264 | X19: -0.041 | Y19: Renewal retention risk | Z19: Business Manager | AA19: 86133.571 | AB19: =DealsRawTable[[#This Row],[Final_Price_ACV]]*DealsRawTable[[#This Row],[Contract_Years]] -> 86133.571 | AC19: 38249.246 | AD19: 47884.325 | AE19: 0.55593103 | AF19: Won | AI19: Yes | AJ19: 86133.571 | AK19: 47884.325 | AL19: Customer returned after lost renewal | AM19: =ROUND(T19*(1-W19),2) -> 86138.37 | AN19: =DealsRawTable[[#This Row],[Validated_Annual_Final_Price]]*DealsRawTable[[#This Row],[Contract_Years]] -> 86138.37 | AO19: =DealsRawTable[[#This Row],[Validated_Annual_Final_Price]]-DealsRawTable[[#This Row],[Cost_to_Serve]] -> 47889.124 | AP19: =DealsRawTable[[#This Row],[Validated_Grossprofit]]/DealsRawTable[[#This Row],[Validated_Annual_Final_Price]] -> 0.55595577 | AQ19: 86138.37 | AR19: 86138.37 | AS19: 47889.124 | AT19: 0.55595577 | AU19: =IF(W19<=0.05,"0–5%", IF(W19<=0.1,"5–10%", IF(W19<=0.15,"10–15%", IF(W19<=0.2,"15–20%", IF(W19<=0.25,"20–25%", IF(W19<=0.3,"25–30%","Above 30%")))))) -> 25–30% | AV19: 3
A20: D00020 | B20: 45344 | C20: C0006 | D20: LEG-0006 | E20: CT00011 | F20: Legal | G20: Legal | H20: West | I20: West Commercial | J20: Mid-Market | K20: No | L20: 45323 | M20: 73 | N20: Nexus Compliance | O20: New Business | Q20: 1 | R20: 131 | S20: R. Singh | T20: 184726.34 | U20: =T20*DealsRawTable[[#This Row],[Contract_Years]] -> 184726.34 | V20: 0.127 | W20: 0.099 | X20: 0.036 | Y20: Expansion opportunity | Z20: Sales Manager | AA20: 166516.73 | AB20: =DealsRawTable[[#This Row],[Final_Price_ACV]]*DealsRawTable[[#This Row],[Contract_Years]] -> 166516.73 | AC20: 58415.092 | AD20: 108101.64 | AE20: 0.64919386 | AF20: Lost | AI20: No | AJ20: 0 | AK20: 0 | AL20: First purchase under this contract | AM20: =ROUND(T20*(1-W20),2) -> 166438.43 | AN20: =DealsRawTable[[#This Row],[Validated_Annual_Final_Price]]*DealsRawTable[[#This Row],[Contract_Years]] -> 166438.43 | AO20: =DealsRawTable[[#This Row],[Validated_Annual_Final_Price]]-DealsRawTable[[#This Row],[Cost_to_Serve]] -> 108023.34 | AP20: =DealsRawTable[[#This Row],[Validated_Grossprofit]]/DealsRawTable[[#This Row],[Validated_Annual_Final_Price]] -> 0.64902882 | AQ20: 0 | AR20: 0 | AS20: 0 | AT20: 0 | AU20: =IF(W20<=0.05,"0–5%", IF(W20<=0.1,"5–10%", IF(W20<=0.15,"10–15%", IF(W20<=0.2,"15–20%", IF(W20<=0.25,"20–25%", IF(W20<=0.3,"25–30%","Above 30%")))))) -> 5–10% | AV20: 116
A21: D00021 | B21: 45685 | C21: C0006 | D21: LEG-0006 | E21: CT00012 | F21: Finance | G21: Legal | H21: West | I21: West Commercial | J21: Mid-Market | K21: No | L21: 45323 | M21: 73 | N21: Nexus Enterprise Suite | O21: New Business | Q21: 1 | R21: 210 | S21: M. Johnson | T21: 259121.64 | U21: =T21*DealsRawTable[[#This Row],[Contract_Years]] -> 259121.64 | V21: 0.138 | W21: 0.103 | X21: 0.112 | Y21: Expansion opportunity | Z21: Pricing Analyst | AA21: 232470.33 | AB21: =DealsRawTable[[#This Row],[Final_Price_ACV]]*DealsRawTable[[#This Row],[Contract_Years]] -> 232470.33 | AC21: 92801.566 | AD21: 139668.77 | AE21: 0.60080254 | AF21: Lost | AI21: No | AJ21: 0 | AK21: 0 | AL21: First purchase under this contract | AM21: =ROUND(T21*(1-W21),2) -> 232432.11 | AN21: =DealsRawTable[[#This Row],[Validated_Annual_Final_Price]]*DealsRawTable[[#This Row],[Contract_Years]] -> 232432.11 | AO21: =DealsRawTable[[#This Row],[Validated_Annual_Final_Price]]-DealsRawTable[[#This Row],[Cost_to_Serve]] -> 139630.54 | AP21: =DealsRawTable[[#This Row],[Validated_Grossprofit]]/DealsRawTable[[#This Row],[Validated_Annual_Final_Price]] -> 0.6007369 | AQ21: 0 | AR21: 0 | AS21: 0 | AT21: 0 | AU21: =IF(W21<=0.05,"0–5%", IF(W21<=0.1,"5–10%", IF(W21<=0.15,"10–15%", IF(W21<=0.2,"15–20%", IF(W21<=0.25,"20–25%", IF(W21<=0.3,"25–30%","Above 30%")))))) -> 10–15% | AV21: 113
A22: D00022 | B22: 45341 | C22: C0006 | D22: LEG-0006 | E22: CT00013 | F22: Sales | G22: Legal | H22: West | I22: West Commercial | J22: Mid-Market | K22: No | L22: 45323 | M22: 73 | N22: Nexus Enterprise Suite | O22: New Business | Q22: 3 | R22: 213 | S22: T. Brooks | T22: 196873.51 | U22: =T22*DealsRawTable[[#This Row],[Contract_Years]] -> 590620.52 | V22: 0.069 | W22: 0.033 | X22: 0.15 | Y22: Verified competitor pressure | Z22: Sales Manager | AA22: 190467.75 | AB22: =DealsRawTable[[#This Row],[Final_Price_ACV]]*DealsRawTable[[#This Row],[Contract_Years]] -> 571403.24 | AC22: 70817.896 | AD22: 119649.85 | AE22: 0.62818956 | AF22: Won | AI22: No | AJ22: 190467.75 | AK22: 119649.85 | AL22: First purchase under this contract | AM22: =ROUND(T22*(1-W22),2) -> 190376.68 | AN22: =DealsRawTable[[#This Row],[Validated_Annual_Final_Price]]*DealsRawTable[[#This Row],[Contract_Years]] -> 571130.04 | AO22: =DealsRawTable[[#This Row],[Validated_Annual_Final_Price]]-DealsRawTable[[#This Row],[Cost_to_Serve]] -> 119558.78 | AP22: =DealsRawTable[[#This Row],[Validated_Grossprofit]]/DealsRawTable[[#This Row],[Validated_Annual_Final_Price]] -> 0.62801171 | AQ22: 190376.68 | AR22: 571130.04 | AS22: 119558.78 | AT22: 0.62801171 | AU22: =IF(W22<=0.05,"0–5%", IF(W22<=0.1,"5–10%", IF(W22<=0.15,"10–15%", IF(W22<=0.2,"15–20%", IF(W22<=0.25,"20–25%", IF(W22<=0.3,"25–30%","Above 30%")))))) -> 0–5% | AV22: 55
A23: D00023 | B23: 45310 | C23: C0007 | D23: FIN-0007 | E23: CT00014 | F23: Finance | G23: Financial Services | H23: Northeast | I23: Northeast Commercial | J23: Mid-Market | K23: No | L23: 43160 | M23: 47 | N23: Nexus Analytics | O23: New Business | Q23: 2 | R23: 204 | S23: D. Chen | T23: 112696.57 | U23: =T23*DealsRawTable[[#This Row],[Contract_Years]] -> 225393.13 | V23: 0.218 | W23: 0.195 | X23: -0.072 | Y23: Verified competitor pressure | Z23: Pricing Analyst | AA23: 90720.722 | AB23: =DealsRawTable[[#This Row],[Final_Price_ACV]]*DealsRawTable[[#This Row],[Contract_Years]] -> 181441.44 | AC23: 40187.432 | AD23: 50533.29 | AE23: 0.55702037 | AF23: Lost | AI23: No | AJ23: 0 | AK23: 0 | AL23: First purchase under this contract | AM23: =ROUND(T23*(1-W23),2) -> 90720.74 | AN23: =DealsRawTable[[#This Row],[Validated_Annual_Final_Price]]*DealsRawTable[[#This Row],[Contract_Years]] -> 181441.48 | AO23: =DealsRawTable[[#This Row],[Validated_Annual_Final_Price]]-DealsRawTable[[#This Row],[Cost_to_Serve]] -> 50533.308 | AP23: =DealsRawTable[[#This Row],[Validated_Grossprofit]]/DealsRawTable[[#This Row],[Validated_Annual_Final_Price]] -> 0.55702045 | AQ23: 0 | AR23: 0 | AS23: 0 | AT23: 0 | AU23: =IF(W23<=0.05,"0–5%", IF(W23<=0.1,"5–10%", IF(W23<=0.15,"10–15%", IF(W23<=0.2,"15–20%", IF(W23<=0.25,"20–25%", IF(W23<=0.3,"25–30%","Above 30%")))))) -> 15–20% | AV23: 108
A24: D00026 | B24: 45504 | C24: C0007 | D24: FIN-0007 | E24: CT00015 | F24: Finance | G24: Financial Services | H24: Northeast | I24: Northeast Commercial | J24: Mid-Market | K24: No | L24: 43160 | M24: 47 | N24: Nexus Insights | O24: Renewal | Q24: 1 | R24: 305 | S24: T. Brooks | T24: 65414.55 | U24: =T24*DealsRawTable[[#This Row],[Contract_Years]] -> 65414.55 | V24: 0.163 | W24: 0.149 | X24: -0.023 | Y24: Renewal retention risk | Z24: Pricing Analyst | AA24: 55639.64 | AB24: =DealsRawTable[[#This Row],[Final_Price_ACV]]*DealsRawTable[[#This Row],[Contract_Years]] -> 55639.64 | AC24: 19905.247 | AD24: 35734.393 | AE24: 0.64224702 | AF24: Lost | AG24: No | AI24: No | AJ24: 0 | AK24: 0 | AL24: Renewal of existing active contract | AM24: =ROUND(T24*(1-W24),2) -> 55667.78 | AN24: =DealsRawTable[[#This Row],[Validated_Annual_Final_Price]]*DealsRawTable[[#This Row],[Contract_Years]] -> 55667.78 | AO24: =DealsRawTable[[#This Row],[Validated_Annual_Final_Price]]-DealsRawTable[[#This Row],[Cost_to_Serve]] -> 35762.533 | AP24: =DealsRawTable[[#This Row],[Validated_Grossprofit]]/DealsRawTable[[#This Row],[Validated_Annual_Final_Price]] -> 0.64242786 | AQ24: 0 | AR24: 0 | AS24: 0 | AT24: 0 | AU24: =IF(W24<=0.05,"0–5%", IF(W24<=0.1,"5–10%", IF(W24<=0.15,"10–15%", IF(W24<=0.2,"15–20%", IF(W24<=0.25,"20–25%", IF(W24<=0.3,"25–30%","Above 30%")))))) -> 10–15% | AV24: 113
A25: D00027 | B25: 45391 | C25: C0007 | D25: FIN-0007 | E25: CT00016 | F25: Corporate | G25: Financial Services | H25: Northeast | I25: Northeast Commercial | J25: Mid-Market | K25: No | L25: 43160 | M25: 47 | N25: Nexus Compliance | O25: Renewal | Q25: 1 | R25: 227 | S25: M. Johnson | T25: 92718.099 | U25: =T25*DealsRawTable[[#This Row],[Contract_Years]] -> 92718.099 | V25: 0.197 | W25: 0.195 | X25: -0.114 | Y25: Renewal retention risk | Z25: Pricing Analyst | AA25: 74619.853 | AB25: =DealsRawTable[[#This Row],[Final_Price_ACV]]*DealsRawTable[[#This Row],[Contract_Years]] -> 74619.853 | AC25: 35433.595 | AD25: 39186.259 | AE25: 0.52514521 | AF25: Won | AG25: Yes | AI25: No | AJ25: 74619.853 | AK25: 39186.259 | AL25: Renewal of existing active contract | AM25: =ROUND(T25*(1-W25),2) -> 74638.07 | AN25: =DealsRawTable[[#This Row],[Validated_Annual_Final_Price]]*DealsRawTable[[#This Row],[Contract_Years]] -> 74638.07 | AO25: =DealsRawTable[[#This Row],[Validated_Annual_Final_Price]]-DealsRawTable[[#This Row],[Cost_to_Serve]] -> 39204.475 | AP25: =DealsRawTable[[#This Row],[Validated_Grossprofit]]/DealsRawTable[[#This Row],[Validated_Annual_Final_Price]] -> 0.5252611 | AQ25: 74638.07 | AR25: 74638.07 | AS25: 39204.475 | AT25: 0.5252611 | AU25: =IF(W25<=0.05,"0–5%", IF(W25<=0.1,"5–10%", IF(W25<=0.15,"10–15%", IF(W25<=0.2,"15–20%", IF(W25<=0.25,"20–25%", IF(W25<=0.3,"25–30%","Above 30%")))))) -> 15–20% | AV25: 108
A26: D00028 | B26: 45756 | C26: C0007 | D26: FIN-0007 | E26: CT00016 | F26: Corporate | G26: Financial Services | H26: Northeast | I26: Northeast Commercial | J26: Mid-Market | K26: No | L26: 43160 | M26: 47 | N26: Nexus Compliance | O26: Renewal | Q26: 1 | R26: 227 | S26: T. Brooks | T26: 99705.748 | U26: =T26*DealsRawTable[[#This Row],[Contract_Years]] -> 99705.748 | V26: 0.209 | W26: 0.177 | X26: 0.012 | Y26: Renewal retention risk | Z26: Pricing Analyst | AA26: 82087.561 | AB26: =DealsRawTable[[#This Row],[Final_Price_ACV]]*DealsRawTable[[#This Row],[Contract_Years]] -> 82087.561 | AC26: 37524.631 | AD26: 44562.93 | AE26: 0.54287068 | AF26: Won | AG26: Yes | AI26: No | AJ26: 82087.561 | AK26: 44562.93 | AL26: Renewal of existing active contract | AM26: =ROUND(T26*(1-W26),2) -> 82057.83 | AN26: =DealsRawTable[[#This Row],[Validated_Annual_Final_Price]]*DealsRawTable[[#This Row],[Contract_Years]] -> 82057.83 | AO26: =DealsRawTable[[#This Row],[Validated_Annual_Final_Price]]-DealsRawTable[[#This Row],[Cost_to_Serve]] -> 44533.199 | AP26: =DealsRawTable[[#This Row],[Validated_Grossprofit]]/DealsRawTable[[#This Row],[Validated_Annual_Final_Price]] -> 0.54270506 | AQ26: 82057.83 | AR26: 82057.83 | AS26: 44533.199 | AT26: 0.54270506 | AU26: =IF(W26<=0.05,"0–5%", IF(W26<=0.1,"5–10%", IF(W26<=0.15,"10–15%", IF(W26<=0.2,"15–20%", IF(W26<=0.25,"20–25%", IF(W26<=0.3,"25–30%","Above 30%")))))) -> 15–20% | AV26: 108
A27: D00029 | B27: 45796 | C27: C0007 | D27: FIN-0007 | E27: CT00017 | F27: Technology | G27: Financial Services | H27: Northeast | I27: Northeast Commercial | J27: Mid-Market | K27: No | L27: 43160 | M27: 47 | N27: Nexus Enterprise Suite | O27: New Business | Q27: 3 | R27: 133 | S27: M. Johnson | T27: 362900.54 | U27: =T27*DealsRawTable[[#This Row],[Contract_Years]] -> 1088701.6 | V27: 0.147 | W27: 0.112 | X27: -0.14 | Y27: Strategic logo opportunity | Z27: Pricing Analyst | AA27: 322206.16 | AB27: =DealsRawTable[[#This Row],[Final_Price_ACV]]*DealsRawTable[[#This Row],[Contract_Years]] -> 966618.47 | AC27: 137627.51 | AD27: 184578.65 | AE27: 0.57285884 | AF27: Lost | AI27: No | AJ27: 0 | AK27: 0 | AL27: First purchase under this contract | AM27: =ROUND(T27*(1-W27),2) -> 322255.68 | AN27: =DealsRawTable[[#This Row],[Validated_Annual_Final_Price]]*DealsRawTable[[#This Row],[Contract_Years]] -> 966767.04 | AO27: =DealsRawTable[[#This Row],[Validated_Annual_Final_Price]]-DealsRawTable[[#This Row],[Cost_to_Serve]] -> 184628.17 | AP27: =DealsRawTable[[#This Row],[Validated_Grossprofit]]/DealsRawTable[[#This Row],[Validated_Annual_Final_Price]] -> 0.57292448 | AQ27: 0 | AR27: 0 | AS27: 0 | AT27: 0 | AU27: =IF(W27<=0.05,"0–5%", IF(W27<=0.1,"5–10%", IF(W27<=0.15,"10–15%", IF(W27<=0.2,"15–20%", IF(W27<=0.25,"20–25%", IF(W27<=0.3,"25–30%","Above 30%")))))) -> 10–15% | AV27: 113
A28: D00030 | B28: 45719 | C28: C0008 | D28: TEC-0008 | E28: CT00018 | F28: Legal | G28: Technology | H28: South | I28: South Enterprise | J28: Enterprise | K28: Yes | L28: 45536 | M28: 71 | N28: Nexus Compliance | O28: New Business | Q28: 1 | R28: 796 | S28: T. Brooks | T28: 181007.6 | U28: =T28*DealsRawTable[[#This Row],[Contract_Years]] -> 181007.6 | V28: 0.25 | W28: 0.234 | X28: 0.134 | Y28: Procurement requirement | Z28: Business Manager | AA28: 138635.96 | AB28: =DealsRawTable[[#This Row],[Final_Price_ACV]]*DealsRawTable[[#This Row],[Contract_Years]] -> 138635.96 | AC28: 66961.706 | AD28: 71674.258 | AE28: 0.51699614 | AF28: Lost | AI28: No | AJ28: 0 | AK28: 0 | AL28: First purchase under this contract | AM28: =ROUND(T28*(1-W28),2) -> 138651.82 | AN28: =DealsRawTable[[#This Row],[Validated_Annual_Final_Price]]*DealsRawTable[[#This Row],[Contract_Years]] -> 138651.82 | AO28: =DealsRawTable[[#This Row],[Validated_Annual_Final_Price]]-DealsRawTable[[#This Row],[Cost_to_Serve]] -> 71690.114 | AP28: =DealsRawTable[[#This Row],[Validated_Grossprofit]]/DealsRawTable[[#This Row],[Validated_Annual_Final_Price]] -> 0.51705137 | AQ28: 0 | AR28: 0 | AS28: 0 | AT28: 0 | AU28: =IF(W28<=0.05,"0–5%", IF(W28<=0.1,"5–10%", IF(W28<=0.15,"10–15%", IF(W28<=0.2,"15–20%", IF(W28<=0.25,"20–25%", IF(W28<=0.3,"25–30%","Above 30%")))))) -> 20–25% | AV28: 29
A29: D00031 | B29: 45830 | C29: C0008 | D29: TEC-0008 | E29: CT00019 | F29: Finance | G29: Technology | H29: South | I29: South Enterprise | J29: Enterprise | K29: Yes | L29: 45536 | M29: 71 | N29: Nexus Analytics | O29: New Business | Q29: 1 | R29: 1345 | S29: M. Johnson | T29: 237976.42 | U29: =T29*DealsRawTable[[#This Row],[Contract_Years]] -> 237976.42 | V29: 0.105 | W29: 0.1 | X29: 0.07 | Y29: Expansion opportunity | Z29: Pricing Analyst | AA29: 214135.78 | AB29: =DealsRawTable[[#This Row],[Final_Price_ACV]]*DealsRawTable[[#This Row],[Contract_Years]] -> 214135.78 | AC29: 84085.734 | AD29: 130050.05 | AE29: 0.60732515 | AF29: Lost | AI29: No | AJ29: 0 | AK29: 0 | AL29: First purchase under this contract | AM29: =ROUND(T29*(1-W29),2) -> 214178.78 | AN29: =DealsRawTable[[#This Row],[Validated_Annual_Final_Price]]*DealsRawTable[[#This Row],[Contract_Years]] -> 214178.78 | AO29: =DealsRawTable[[#This Row],[Validated_Annual_Final_Price]]-DealsRawTable[[#This Row],[Cost_to_Serve]] -> 130093.05 | AP29: =DealsRawTable[[#This Row],[Validated_Grossprofit]]/DealsRawTable[[#This Row],[Validated_Annual_Final_Price]] -> 0.60740399 | AQ29: 0 | AR29: 0 | AS29: 0 | AT29: 0 | AU29: =IF(W29<=0.05,"0–5%", IF(W29<=0.1,"5–10%", IF(W29<=0.15,"10–15%", IF(W29<=0.2,"15–20%", IF(W29<=0.25,"20–25%", IF(W29<=0.3,"25–30%","Above 30%")))))) -> 5–10% | AV29: 116
A30: D00032 | B30: 45580 | C30: C0009 | D30: MAN-0009 | E30: CT00020 | F30: Sales | G30: Manufacturing | H30: Midwest | I30: Midwest Commercial | J30: SMB | K30: No | L30: 44682 | M30: 38 | N30: Nexus AI Assistant | O30: New Business | Q30: 1 | R30: 75 | S30: R. Singh | T30: 41655.051 | U30: =T30*DealsRawTable[[#This Row],[Contract_Years]] -> 41655.051 | V30: 0.226 | W30: 0.184 | X30: -0.117 | Y30: Procurement requirement | Z30: Pricing Analyst | AA30: 33993.638 | AB30: =DealsRawTable[[#This Row],[Final_Price_ACV]]*DealsRawTable[[#This Row],[Contract_Years]] -> 33993.638 | AC30: 17884.639 | AD30: 16109 | AE30: 0.47388278 | AF30: Lost | AI30: No | AJ30: 0 | AK30: 0 | AL30: First purchase under this contract | AM30: =ROUND(T30*(1-W30),2) -> 33990.52 | AN30: =DealsRawTable[[#This Row],[Validated_Annual_Final_Price]]*DealsRawTable[[#This Row],[Contract_Years]] -> 33990.52 | AO30: =DealsRawTable[[#This Row],[Validated_Annual_Final_Price]]-DealsRawTable[[#This Row],[Cost_to_Serve]] -> 16105.881 | AP30: =DealsRawTable[[#This Row],[Validated_Grossprofit]]/DealsRawTable[[#This Row],[Validated_Annual_Final_Price]] -> 0.47383451 | AQ30: 0 | AR30: 0 | AS30: 0 | AT30: 0 | AU30: =IF(W30<=0.05,"0–5%", IF(W30<=0.1,"5–10%", IF(W30<=0.15,"10–15%", IF(W30<=0.2,"15–20%", IF(W30<=0.25,"20–25%", IF(W30<=0.3,"25–30%","Above 30%")))))) -> 15–20% | AV30: 108
A31: D00033 | B31: 45882 | C31: C0010 | D31: LEG-0010 | E31: CT00021 | F31: Legal | G31: Legal | H31: West | I31: West Commercial | J31: Mid-Market | K31: No | L31: 44348 | M31: 59 | N31: Nexus Analytics | O31: Renewal | Q31: 2 | R31: 207 | S31: D. Chen | T31: 139960.13 | U31: =T31*DealsRawTable[[#This Row],[Contract_Years]] -> 279920.25 | V31: 0.204 | W31: 0.156 | X31: -0.001 | Y31: Renewal retention risk | Z31: Pricing Analyst | AA31: 118066.05 | AB31: =DealsRawTable[[#This Row],[Final_Price_ACV]]*DealsRawTable[[#This Row],[Contract_Years]] -> 236132.1 | AC31: 43010.71 | AD31: 75055.341 | AE31: 0.63570637 | AF31: Lost | AG31: No | AI31: No | AJ31: 0 | AK31: 0 | AL31: Renewal of existing active contract | AM31: =ROUND(T31*(1-W31),2) -> 118126.35 | AN31: =DealsRawTable[[#This Row],[Validated_Annual_Final_Price]]*DealsRawTable[[#This Row],[Contract_Years]] -> 236252.7 | AO31: =DealsRawTable[[#This Row],[Validated_Annual_Final_Price]]-DealsRawTable[[#This Row],[Cost_to_Serve]] -> 75115.64 | AP31: =DealsRawTable[[#This Row],[Validated_Grossprofit]]/DealsRawTable[[#This Row],[Validated_Annual_Final_Price]] -> 0.63589233 | AQ31: 0 | AR31: 0 | AS31: 0 | AT31: 0 | AU31: =IF(W31<=0.05,"0–5%", IF(W31<=0.1,"5–10%", IF(W31<=0.15,"10–15%", IF(W31<=0.2,"15–20%", IF(W31<=0.25,"20–25%", IF(W31<=0.3,"25–30%","Above 30%")))))) -> 15–20% | AV31: 108
A32: D00034 | B32: 45298 | C32: C0011 | D32: TEC-0011 | E32: CT00022 | F32: Sales | G32: Technology | H32: Midwest | I32: Midwest Enterprise | J32: Enterprise | K32: Yes | L32: 44197 | M32: 45 | N32: Nexus Compliance | O32: New Business | Q32: 1 | R32: 628 | S32: A. Patel | T32: 253577.77 | U32: =T32*DealsRawTable[[#This Row],[Contract_Years]] -> 253577.77 | V32: 0.171 | W32: 0.134 | X32: 0.044 | Y32: Volume purchase | Z32: Pricing Analyst | AA32: 219611.38 | AB32: =DealsRawTable[[#This Row],[Final_Price_ACV]]*DealsRawTable[[#This Row],[Contract_Years]] -> 219611.38 | AC32: 106942.15 | AD32: 112669.23 | AE32: 0.51303911 | AF32: Lost | AI32: No | AJ32: 0 | AK32: 0 | AL32: First purchase under this contract | AM32: =ROUND(T32*(1-W32),2) -> 219598.35 | AN32: =DealsRawTable[[#This Row],[Validated_Annual_Final_Price]]*DealsRawTable[[#This Row],[Contract_Years]] -> 219598.35 | AO32: =DealsRawTable[[#This Row],[Validated_Annual_Final_Price]]-DealsRawTable[[#This Row],[Cost_to_Serve]] -> 112656.2 | AP32: =DealsRawTable[[#This Row],[Validated_Grossprofit]]/DealsRawTable[[#This Row],[Validated_Annual_Final_Price]] -> 0.51301022 | AQ32: 0 | AR32: 0 | AS32: 0 | AT32: 0 | AU32: =IF(W32<=0.05,"0–5%", IF(W32<=0.1,"5–10%", IF(W32<=0.15,"10–15%", IF(W32<=0.2,"15–20%", IF(W32<=0.25,"20–25%", IF(W32<=0.3,"25–30%","Above 30%")))))) -> 10–15% | AV32: 113
A33: D00035 | B33: 45386 | C33: C0011 | D33: TEC-0011 | E33: CT00023 | F33: Corporate | G33: Technology | H33: Midwest | I33: Midwest Enterprise | J33: Enterprise | K33: Yes | L33: 44197 | M33: 45 | N33: Nexus Compliance | O33: New Business | Q33: 3 | R33: 1885 | S33: S. Rivera | T33: 468080.85 | U33: =T33*DealsRawTable[[#This Row],[Contract_Years]] -> 1404242.6 | V33: 0.184 | W33: 0.152 | X33: -0.18 | Y33: Strategic logo opportunity | Z33: Pricing Analyst | AA33: 396827.15 | AB33: =DealsRawTable[[#This Row],[Final_Price_ACV]]*DealsRawTable[[#This Row],[Contract_Years]] -> 1190481.4 | AC33: 177287.52 | AD33: 219539.63 | AE33: 0.55323742 | AF33: Lost | AI33: No | AJ33: 0 | AK33: 0 | AL33: First purchase under this contract | AM33: =ROUND(T33*(1-W33),2) -> 396932.56 | AN33: =DealsRawTable[[#This Row],[Validated_Annual_Final_Price]]*DealsRawTable[[#This Row],[Contract_Years]] -> 1190797.7 | AO33: =DealsRawTable[[#This Row],[Validated_Annual_Final_Price]]-DealsRawTable[[#This Row],[Cost_to_Serve]] -> 219645.04 | AP33: =DealsRawTable[[#This Row],[Validated_Grossprofit]]/DealsRawTable[[#This Row],[Validated_Annual_Final_Price]] -> 0.55335606 | AQ33: 0 | AR33: 0 | AS33: 0 | AT33: 0 | AU33: =IF(W33<=0.05,"0–5%", IF(W33<=0.1,"5–10%", IF(W33<=0.15,"10–15%", IF(W33<=0.2,"15–20%", IF(W33<=0.25,"20–25%", IF(W33<=0.3,"25–30%","Above 30%")))))) -> 15–20% | AV33: 108
A34: D00036 | B34: 45719 | C34: C0011 | D34: TEC-0011 | E34: CT00023 | F34: Corporate | G34: Technology | H34: Midwest | I34: Midwest Enterprise | J34: Enterprise | K34: Yes | L34: 44197 | M34: 45 | N34: Nexus Compliance | O34: Win-back | Q34: 3 | R34: 1885 | S34: A. Patel | T34: 468080.85 | U34: =T34*DealsRawTable[[#This Row],[Contract_Years]] -> 1404242.6 | V34: 0.182 | W34: 0.171 | X34: -0.135 | Y34: Renewal retention risk | Z34: Pricing Analyst | AA34: 387889.1 | AB34: =DealsRawTable[[#This Row],[Final_Price_ACV]]*DealsRawTable[[#This Row],[Contract_Years]] -> 1163667.3 | AC34: 167433.57 | AD34: 220455.53 | AE34: 0.5683468 | AF34: Won | AI34: Yes | AJ34: 387889.1 | AK34: 220455.53 | AL34: Customer returned after prior lost initial opportunity | AM34: =ROUND(T34*(1-W34),2) -> 388039.03 | AN34: =DealsRawTable[[#This Row],[Validated_Annual_Final_Price]]*DealsRawTable[[#This Row],[Contract_Years]] -> 1164117.1 | AO34: =DealsRawTable[[#This Row],[Validated_Annual_Final_Price]]-DealsRawTable[[#This Row],[Cost_to_Serve]] -> 220605.46 | AP34: =DealsRawTable[[#This Row],[Validated_Grossprofit]]/DealsRawTable[[#This Row],[Validated_Annual_Final_Price]] -> 0.56851357 | AQ34: 388039.03 | AR34: 1164117.1 | AS34: 220605.46 | AT34: 0.56851357 | AU34: =IF(W34<=0.05,"0–5%", IF(W34<=0.1,"5–10%", IF(W34<=0.15,"10–15%", IF(W34<=0.2,"15–20%", IF(W34<=0.25,"20–25%", IF(W34<=0.3,"25–30%","Above 30%")))))) -> 15–20% | AV34: 108
A35: D00037 | B35: 45776 | C35: C0012 | D35: TEC-0012 | E35: CT00024 | F35: Operations | G35: Technology | H35: Midwest | I35: Midwest Commercial | J35: Mid-Market | K35: No | L35: 44531 | M35: 69 | N35: Nexus Compliance | O35: New Business | Q35: 1 | R35: 338 | S35: M. Johnson | T35: 173097.35 | U35: =T35*DealsRawTable[[#This Row],[Contract_Years]] -> 173097.35 | V35: 0.124 | W35: 0.079 | X35: -0.048 | Y35: Expansion opportunity | Z35: Sales Manager | AA35: 159491.64 | AB35: =DealsRawTable[[#This Row],[Final_Price_ACV]]*DealsRawTable[[#This Row],[Contract_Years]] -> 159491.64 | AC35: 61793.253 | AD35: 97698.391 | AE35: 0.61256119 | AF35: Won | AI35: No | AJ35: 159491.64 | AK35: 97698.391 | AL35: First purchase under this contract | AM35: =ROUND(T35*(1-W35),2) -> 159422.66 | AN35: =DealsRawTable[[#This Row],[Validated_Annual_Final_Price]]*DealsRawTable[[#This Row],[Contract_Years]] -> 159422.66 | AO35: =DealsRawTable[[#This Row],[Validated_Annual_Final_Price]]-DealsRawTable[[#This Row],[Cost_to_Serve]] -> 97629.407 | AP35: =DealsRawTable[[#This Row],[Validated_Grossprofit]]/DealsRawTable[[#This Row],[Validated_Annual_Final_Price]] -> 0.61239354 | AQ35: 159422.66 | AR35: 159422.66 | AS35: 97629.407 | AT35: 0.61239354 | AU35: =IF(W35<=0.05,"0–5%", IF(W35<=0.1,"5–10%", IF(W35<=0.15,"10–15%", IF(W35<=0.2,"15–20%", IF(W35<=0.25,"20–25%", IF(W35<=0.3,"25–30%","Above 30%")))))) -> 5–10% | AV35: 116
A36: D00038 | B36: 45702 | C36: C0012 | D36: TEC-0012 | E36: CT00025 | F36: Legal | G36: Technology | H36: Midwest | I36: Midwest Commercial | J36: Mid-Market | K36: No | L36: 44531 | M36: 69 | N36: Nexus Analytics | O36: Renewal | Q36: 3 | R36: 213 | S36: A. Patel | T36: 120002.86 | U36: =T36*DealsRawTable[[#This Row],[Contract_Years]] -> 360008.57 | V36: 0.069 | W36: 0.056 | X36: -0.018 | Y36: Budget constraint | Z36: Sales Manager | AA36: 113266.12 | AB36: =DealsRawTable[[#This Row],[Final_Price_ACV]]*DealsRawTable[[#This Row],[Contract_Years]] -> 339798.36 | AC36: 38550.371 | AD36: 74715.749 | AE36: 0.65964782 | AF36: Won | AG36: Yes | AI36: No | AJ36: 113266.12 | AK36: 74715.749 | AL36: Renewal of existing active contract | AM36: =ROUND(T36*(1-W36),2) -> 113282.7 | AN36: =DealsRawTable[[#This Row],[Validated_Annual_Final_Price]]*DealsRawTable[[#This Row],[Contract_Years]] -> 339848.1 | AO36: =DealsRawTable[[#This Row],[Validated_Annual_Final_Price]]-DealsRawTable[[#This Row],[Cost_to_Serve]] -> 74732.329 | AP36: =DealsRawTable[[#This Row],[Validated_Grossprofit]]/DealsRawTable[[#This Row],[Validated_Annual_Final_Price]] -> 0.65969763 | AQ36: 113282.7 | AR36: 339848.1 | AS36: 74732.329 | AT36: 0.65969763 | AU36: =IF(W36<=0.05,"0–5%", IF(W36<=0.1,"5–10%", IF(W36<=0.15,"10–15%", IF(W36<=0.2,"15–20%", IF(W36<=0.25,"20–25%", IF(W36<=0.3,"25–30%","Above 30%")))))) -> 5–10% | AV36: 116
A37: D00039 | B37: 45551 | C37: C0013 | D37: FIN-0013 | E37: CT00027 | F37: Finance | G37: Financial Services | H37: West | I37: West Commercial | J37: Mid-Market | K37: No | L37: 44531 | M37: 67 | N37: Nexus AI Assistant | O37: Renewal | Q37: 1 | R37: 280 | S37: T. Brooks | T37: 55186.784 | U37: =T37*DealsRawTable[[#This Row],[Contract_Years]] -> 55186.784 | V37: 0.2 | W37: 0.178 | X37: -0.073 | Y37: Multi-year commitment | Z37: Pricing Analyst | AA37: 45368.135 | AB37: =DealsRawTable[[#This Row],[Final_Price_ACV]]*DealsRawTable[[#This Row],[Contract_Years]] -> 45368.135 | AC37: 21810.707 | AD37: 23557.427 | AE37: 0.51925052 | AF37: Won | AG37: Yes | AI37: No | AJ37: 45368.135 | AK37: 23557.427 | AL37: Renewal of existing active contract | AM37: =ROUND(T37*(1-W37),2) -> 45363.54 | AN37: =DealsRawTable[[#This Row],[Validated_Annual_Final_Price]]*DealsRawTable[[#This Row],[Contract_Years]] -> 45363.54 | AO37: =DealsRawTable[[#This Row],[Validated_Annual_Final_Price]]-DealsRawTable[[#This Row],[Cost_to_Serve]] -> 23552.833 | AP37: =DealsRawTable[[#This Row],[Validated_Grossprofit]]/DealsRawTable[[#This Row],[Validated_Annual_Final_Price]] -> 0.51920182 | AQ37: 45363.54 | AR37: 45363.54 | AS37: 23552.833 | AT37: 0.51920182 | AU37: =IF(W37<=0.05,"0–5%", IF(W37<=0.1,"5–10%", IF(W37<=0.15,"10–15%", IF(W37<=0.2,"15–20%", IF(W37<=0.25,"20–25%", IF(W37<=0.3,"25–30%","Above 30%")))))) -> 15–20% | AV37: 108
A38: D00040 | B38: 45750 | C38: C0013 | D38: FIN-0013 | E38: CT00027 | F38: Finance | G38: Financial Services | H38: West | I38: West Commercial | J38: Mid-Market | K38: No | L38: 44531 | M38: 67 | N38: Nexus AI Assistant | O38: Expansion | P38: Storage / Usage Expansion | Q38: 1 | R38: 397 | S38: T. Brooks | T38: 66130.911 | U38: =T38*DealsRawTable[[#This Row],[Contract_Years]] -> 66130.911 | V38: 0.187 | W38: 0.165 | X38: -0.017 | Y38: Expansion opportunity | Z38: Pricing Analyst | AA38: 55225.688 | AB38: =DealsRawTable[[#This Row],[Final_Price_ACV]]*DealsRawTable[[#This Row],[Contract_Years]] -> 55225.688 | AC38: 25358.411 | AD38: 29867.278 | AE38: 0.54082219 | AF38: Won | AH38: Yes | AI38: No | AJ38: 55225.688 | AK38: 29867.278 | AL38: Expansion allowed because contract was active | AM38: =ROUND(T38*(1-W38),2) -> 55219.31 | AN38: =DealsRawTable[[#This Row],[Validated_Annual_Final_Price]]*DealsRawTable[[#This Row],[Contract_Years]] -> 55219.31 | AO38: =DealsRawTable[[#This Row],[Validated_Annual_Final_Price]]-DealsRawTable[[#This Row],[Cost_to_Serve]] -> 29860.899 | AP38: =DealsRawTable[[#This Row],[Validated_Grossprofit]]/DealsRawTable[[#This Row],[Validated_Annual_Final_Price]] -> 0.54076915 | AQ38: 55219.31 | AR38: 55219.31 | AS38: 29860.899 | AT38: 0.54076915 | AU38: =IF(W38<=0.05,"0–5%", IF(W38<=0.1,"5–10%", IF(W38<=0.15,"10–15%", IF(W38<=0.2,"15–20%", IF(W38<=0.25,"20–25%", IF(W38<=0.3,"25–30%","Above 30%")))))) -> 15–20% | AV38: 108
A39: D00041 | B39: 45916 | C39: C0013 | D39: FIN-0013 | E39: CT00027 | F39: Finance | G39: Financial Services | H39: West | I39: West Commercial | J39: Mid-Market | K39: No | L39: 44531 | M39: 67 | N39: Nexus AI Assistant | O39: Renewal | Q39: 1 | R39: 397 | S39: A. Patel | T39: 67469.034 | U39: =T39*DealsRawTable[[#This Row],[Contract_Years]] -> 67469.034 | V39: 0.077 | W39: 0.034 | X39: -0.029 | Y39: Budget constraint | Z39: Sales Manager | AA39: 65189.491 | AB39: =DealsRawTable[[#This Row],[Final_Price_ACV]]*DealsRawTable[[#This Row],[Contract_Years]] -> 65189.491 | AC39: 25848.65 | AD39: 39340.84 | AE39: 0.6034844 | AF39: Won | AG39: Yes | AI39: No | AJ39: 65189.491 | AK39: 39340.84 | AL39: Renewal of existing active contract | AM39: =ROUND(T39*(1-W39),2) -> 65175.09 | AN39: =DealsRawTable[[#This Row],[Validated_Annual_Final_Price]]*DealsRawTable[[#This Row],[Contract_Years]] -> 65175.09 | AO39: =DealsRawTable[[#This Row],[Validated_Annual_Final_Price]]-DealsRawTable[[#This Row],[Cost_to_Serve]] -> 39326.44 | AP39: =DealsRawTable[[#This Row],[Validated_Grossprofit]]/DealsRawTable[[#This Row],[Validated_Annual_Final_Price]] -> 0.60339678 | AQ39: 65175.09 | AR39: 65175.09 | AS39: 39326.44 | AT39: 0.60339678 | AU39: =IF(W39<=0.05,"0–5%", IF(W39<=0.1,"5–10%", IF(W39<=0.15,"10–15%", IF(W39<=0.2,"15–20%", IF(W39<=0.25,"20–25%", IF(W39<=0.3,"25–30%","Above 30%")))))) -> 0–5% | AV39: 55
A40: D00042 | B40: 45719 | C40: C0013 | D40: FIN-0013 | E40: CT00028 | F40: Technology | G40: Financial Services | H40: West | I40: West Commercial | J40: Mid-Market | K40: No | L40: 44531 | M40: 67 | N40: Nexus Analytics | O40: New Business | Q40: 3 | R40: 115 | S40: S. Rivera | T40: 102198.77 | U40: =T40*DealsRawTable[[#This Row],[Contract_Years]] -> 306596.3 | V40: 0.069 | W40: 0.051 | X40: 0.031 | Y40: Verified competitor pressure | Z40: Sales Manager | AA40: 97031.658 | AB40: =DealsRawTable[[#This Row],[Final_Price_ACV]]*DealsRawTable[[#This Row],[Contract_Years]] -> 291094.97 | AC40: 35647.422 | AD40: 61384.236 | AE40: 0.6326207 | AF40: Won | AI40: No | AJ40: 97031.658 | AK40: 61384.236 | AL40: First purchase under this contract | AM40: =ROUND(T40*(1-W40),2) -> 96986.63 | AN40: =DealsRawTable[[#This Row],[Validated_Annual_Final_Price]]*DealsRawTable[[#This Row],[Contract_Years]] -> 290959.89 | AO40: =DealsRawTable[[#This Row],[Validated_Annual_Final_Price]]-DealsRawTable[[#This Row],[Cost_to_Serve]] -> 61339.208 | AP40: =DealsRawTable[[#This Row],[Validated_Grossprofit]]/DealsRawTable[[#This Row],[Validated_Annual_Final_Price]] -> 0.63245014 | AQ40: 96986.63 | AR40: 290959.89 | AS40: 61339.208 | AT40: 0.63245014 | AU40: =IF(W40<=0.05,"0–5%", IF(W40<=0.1,"5–10%", IF(W40<=0.15,"10–15%", IF(W40<=0.2,"15–20%", IF(W40<=0.25,"20–25%", IF(W40<=0.3,"25–30%","Above 30%")))))) -> 5–10% | AV40: 116
A41: D00043 | B41: 45343 | C41: C0013 | D41: FIN-0013 | E41: CT00029 | F41: Operations | G41: Financial Services | H41: West | I41: West Commercial | J41: Mid-Market | K41: No | L41: 44531 | M41: 67 | N41: Nexus Analytics | O41: Renewal | Q41: 1 | R41: 264 | S41: T. Brooks | T41: 109848.93 | U41: =T41*DealsRawTable[[#This Row],[Contract_Years]] -> 109848.93 | V41: 0.2 | W41: 0.197 | X41: -0.094 | Y41: Budget constraint | Z41: Pricing Analyst | AA41: 88180.622 | AB41: =DealsRawTable[[#This Row],[Final_Price_ACV]]*DealsRawTable[[#This Row],[Contract_Years]] -> 88180.622 | AC41: 30477.677 | AD41: 57702.944 | AE41: 0.65437217 | AF41: Won | AG41: Yes | AI41: No | AJ41: 88180.622 | AK41: 57702.944 | AL41: Renewal of existing active contract | AM41: =ROUND(T41*(1-W41),2) -> 88208.69 | AN41: =DealsRawTable[[#This Row],[Validated_Annual_Final_Price]]*DealsRawTable[[#This Row],[Contract_Years]] -> 88208.69 | AO41: =DealsRawTable[[#This Row],[Validated_Annual_Final_Price]]-DealsRawTable[[#This Row],[Cost_to_Serve]] -> 57731.013 | AP41: =DealsRawTable[[#This Row],[Validated_Grossprofit]]/DealsRawTable[[#This Row],[Validated_Annual_Final_Price]] -> 0.65448215 | AQ41: 88208.69 | AR41: 88208.69 | AS41: 57731.013 | AT41: 0.65448215 | AU41: =IF(W41<=0.05,"0–5%", IF(W41<=0.1,"5–10%", IF(W41<=0.15,"10–15%", IF(W41<=0.2,"15–20%", IF(W41<=0.25,"20–25%", IF(W41<=0.3,"25–30%","Above 30%")))))) -> 15–20% | AV41: 108
A42: D00044 | B42: 45708 | C42: C0013 | D42: FIN-0013 | E42: CT00029 | F42: Operations | G42: Financial Services | H42: West | I42: West Commercial | J42: Mid-Market | K42: No | L42: 44531 | M42: 67 | N42: Nexus Analytics | O42: Renewal | Q42: 1 | R42: 264 | S42: T. Brooks | T42: 112393.82 | U42: =T42*DealsRawTable[[#This Row],[Contract_Years]] -> 112393.82 | V42: 0.086 | W42: 0.067 | X42: -0.012 | Y42: Expansion opportunity | Z42: Sales Manager | AA42: 104820.09 | AB42: =DealsRawTable[[#This Row],[Final_Price_ACV]]*DealsRawTable[[#This Row],[Contract_Years]] -> 104820.09 | AC42: 36410.452 | AD42: 68409.639 | AE42: 0.65263861 | AF42: Lost | AG42: No | AI42: No | AJ42: 0 | AK42: 0 | AL42: Renewal of existing active contract | AM42: =ROUND(T42*(1-W42),2) -> 104863.44 | AN42: =DealsRawTable[[#This Row],[Validated_Annual_Final_Price]]*DealsRawTable[[#This Row],[Contract_Years]] -> 104863.44 | AO42: =DealsRawTable[[#This Row],[Validated_Annual_Final_Price]]-DealsRawTable[[#This Row],[Cost_to_Serve]] -> 68452.988 | AP42: =DealsRawTable[[#This Row],[Validated_Grossprofit]]/DealsRawTable[[#This Row],[Validated_Annual_Final_Price]] -> 0.65278221 | AQ42: 0 | AR42: 0 | AS42: 0 | AT42: 0 | AU42: =IF(W42<=0.05,"0–5%", IF(W42<=0.1,"5–10%", IF(W42<=0.15,"10–15%", IF(W42<=0.2,"15–20%", IF(W42<=0.25,"20–25%", IF(W42<=0.3,"25–30%","Above 30%")))))) -> 5–10% | AV42: 116
A43: D00045 | B43: 45516 | C43: C0014 | D43: PUB-0014 | E43: CT00030 | F43: Finance | G43: Public Sector | H43: West | I43: West Commercial | J43: SMB | K43: Yes | L43: 44743 | M43: 80 | N43: Nexus Enterprise Suite | O43: Expansion | P43: Module Add-on | Q43: 1 | R43: 85 | S43: S. Rivera | T43: 178886.39 | U43: =T43*DealsRawTable[[#This Row],[Contract_Years]] -> 178886.39 | V43: 0.043 | W43: 0.007 | X43: -0.024 | Y43: Expansion opportunity | Z43: Sales Manager | AA43: 177720.63 | AB43: =DealsRawTable[[#This Row],[Final_Price_ACV]]*DealsRawTable[[#This Row],[Contract_Years]] -> 177720.63 | AC43: 65664.053 | AD43: 112056.58 | AE43: 0.63052093 | AF43: Won | AH43: Yes | AI43: No | AJ43: 177720.63 | AK43: 112056.58 | AL43: Expansion allowed because contract was active | AM43: =ROUND(T43*(1-W43),2) -> 177634.19 | AN43: =DealsRawTable[[#This Row],[Validated_Annual_Final_Price]]*DealsRawTable[[#This Row],[Contract_Years]] -> 177634.19 | AO43: =DealsRawTable[[#This Row],[Validated_Annual_Final_Price]]-DealsRawTable[[#This Row],[Cost_to_Serve]] -> 111970.14 | AP43: =DealsRawTable[[#This Row],[Validated_Grossprofit]]/DealsRawTable[[#This Row],[Validated_Annual_Final_Price]] -> 0.63034114 | AQ43: 177634.19 | AR43: 177634.19 | AS43: 111970.14 | AT43: 0.63034114 | AU43: =IF(W43<=0.05,"0–5%", IF(W43<=0.1,"5–10%", IF(W43<=0.15,"10–15%", IF(W43<=0.2,"15–20%", IF(W43<=0.25,"20–25%", IF(W43<=0.3,"25–30%","Above 30%")))))) -> 0–5% | AV43: 55
A44: D00046 | B44: 45609 | C44: C0014 | D44: PUB-0014 | E44: CT00030 | F44: Finance | G44: Public Sector | H44: West | I44: West Commercial | J44: SMB | K44: Yes | L44: 44743 | M44: 80 | N44: Nexus Enterprise Suite | O44: Renewal | Q44: 1 | R44: 85 | S44: L. Williams | T44: 183401.78 | U44: =T44*DealsRawTable[[#This Row],[Contract_Years]] -> 183401.78 | V44: 0.103 | W44: 0.082 | X44: -0.063 | Y44: Multi-year commitment | Z44: Sales Manager | AA44: 168366.76 | AB44: =DealsRawTable[[#This Row],[Final_Price_ACV]]*DealsRawTable[[#This Row],[Contract_Years]] -> 168366.76 | AC44: 65192.742 | AD44: 103174.02 | AE44: 0.61279328 | AF44: Won | AG44: Yes | AI44: No | AJ44: 168366.76 | AK44: 103174.02 | AL44: Renewal of existing active contract | AM44: =ROUND(T44*(1-W44),2) -> 168362.84 | AN44: =DealsRawTable[[#This Row],[Validated_Annual_Final_Price]]*DealsRawTable[[#This Row],[Contract_Years]] -> 168362.84 | AO44: =DealsRawTable[[#This Row],[Validated_Annual_Final_Price]]-DealsRawTable[[#This Row],[Cost_to_Serve]] -> 103170.1 | AP44: =DealsRawTable[[#This Row],[Validated_Grossprofit]]/DealsRawTable[[#This Row],[Validated_Annual_Final_Price]] -> 0.61278426 | AQ44: 168362.84 | AR44: 168362.84 | AS44: 103170.1 | AT44: 0.61278426 | AU44: =IF(W44<=0.05,"0–5%", IF(W44<=0.1,"5–10%", IF(W44<=0.15,"10–15%", IF(W44<=0.2,"15–20%", IF(W44<=0.25,"20–25%", IF(W44<=0.3,"25–30%","Above 30%")))))) -> 5–10% | AV44: 116
A45: D00047 | B45: 45808 | C45: C0014 | D45: PUB-0014 | E45: CT00030 | F45: Finance | G45: Public Sector | H45: West | I45: West Commercial | J45: SMB | K45: Yes | L45: 44743 | M45: 80 | N45: Nexus Enterprise Suite | O45: Expansion | P45: Enterprise Upgrade | Q45: 1 | R45: 103 | S45: K. Nguyen | T45: 247456.65 | U45: =T45*DealsRawTable[[#This Row],[Contract_Years]] -> 247456.65 | V45: 0.066 | W45: 0.036 | X45: 0.061 | Y45: Expansion opportunity | Z45: Sales Manager | AA45: 238605.32 | AB45: =DealsRawTable[[#This Row],[Final_Price_ACV]]*DealsRawTable[[#This Row],[Contract_Years]] -> 238605.32 | AC45: 97136.575 | AD45: 141468.74 | AE45: 0.59289853 | AF45: Won | AH45: Yes | AI45: No | AJ45: 238605.32 | AK45: 141468.74 | AL45: Expansion allowed because contract was active | AM45: =ROUND(T45*(1-W45),2) -> 238548.21 | AN45: =DealsRawTable[[#This Row],[Validated_Annual_Final_Price]]*DealsRawTable[[#This Row],[Contract_Years]] -> 238548.21 | AO45: =DealsRawTable[[#This Row],[Validated_Annual_Final_Price]]-DealsRawTable[[#This Row],[Cost_to_Serve]] -> 141411.63 | AP45: =DealsRawTable[[#This Row],[Validated_Grossprofit]]/DealsRawTable[[#This Row],[Validated_Annual_Final_Price]] -> 0.59280107 | AQ45: 238548.21 | AR45: 238548.21 | AS45: 141411.63 | AT45: 0.59280107 | AU45: =IF(W45<=0.05,"0–5%", IF(W45<=0.1,"5–10%", IF(W45<=0.15,"10–15%", IF(W45<=0.2,"15–20%", IF(W45<=0.25,"20–25%", IF(W45<=0.3,"25–30%","Above 30%")))))) -> 0–5% | AV45: 55
A46: D00048 | B46: 45974 | C46: C0014 | D46: PUB-0014 | E46: CT00030 | F46: Finance | G46: Public Sector | H46: West | I46: West Commercial | J46: SMB | K46: Yes | L46: 44743 | M46: 80 | N46: Nexus Enterprise Suite | O46: Renewal | Q46: 1 | R46: 103 | S46: D. Chen | T46: 264737.78 | U46: =T46*DealsRawTable[[#This Row],[Contract_Years]] -> 264737.78 | V46: 0.048 | W46: 0.031 | X46: 0.031 | Y46: Verified competitor pressure | Z46: Sales Manager | AA46: 256502.02 | AB46: =DealsRawTable[[#This Row],[Final_Price_ACV]]*DealsRawTable[[#This Row],[Contract_Years]] -> 256502.02 | AC46: 84893.722 | AD46: 171608.3 | AE46: 0.66903293 | AF46: Lost | AG46: No | AI46: No | AJ46: 0 | AK46: 0 | AL46: Renewal of existing active contract | AM46: =ROUND(T46*(1-W46),2) -> 256530.91 | AN46: =DealsRawTable[[#This Row],[Validated_Annual_Final_Price]]*DealsRawTable[[#This Row],[Contract_Years]] -> 256530.91 | AO46: =DealsRawTable[[#This Row],[Validated_Annual_Final_Price]]-DealsRawTable[[#This Row],[Cost_to_Serve]] -> 171637.19 | AP46: =DealsRawTable[[#This Row],[Validated_Grossprofit]]/DealsRawTable[[#This Row],[Validated_Annual_Final_Price]] -> 0.6690702 | AQ46: 0 | AR46: 0 | AS46: 0 | AT46: 0 | AU46: =IF(W46<=0.05,"0–5%", IF(W46<=0.1,"5–10%", IF(W46<=0.15,"10–15%", IF(W46<=0.2,"15–20%", IF(W46<=0.25,"20–25%", IF(W46<=0.3,"25–30%","Above 30%")))))) -> 0–5% | AV46: 55
A47: D00049 | B47: 45596 | C47: C0014 | D47: PUB-0014 | E47: CT00031 | F47: Finance | G47: Public Sector | H47: West | I47: West Commercial | J47: SMB | K47: Yes | L47: 44743 | M47: 80 | N47: Nexus Analytics | O47: Renewal | Q47: 1 | R47: 51 | S47: S. Rivera | T47: 62550.838 | U47: =T47*DealsRawTable[[#This Row],[Contract_Years]] -> 62550.838 | V47: 0.196 | W47: 0.133 | X47: 0.039 | Y47: Strategic logo opportunity | Z47: Pricing Analyst | AA47: 54213.499 | AB47: =DealsRawTable[[#This Row],[Final_Price_ACV]]*DealsRawTable[[#This Row],[Contract_Years]] -> 54213.499 | AC47: 19711.945 | AD47: 34501.555 | AE47: 0.63640154 | AF47: Won | AG47: Yes | AI47: No | AJ47: 54213.499 | AK47: 34501.555 | AL47: Renewal of existing active contract | AM47: =ROUND(T47*(1-W47),2) -> 54231.58 | AN47: =DealsRawTable[[#This Row],[Validated_Annual_Final_Price]]*DealsRawTable[[#This Row],[Contract_Years]] -> 54231.58 | AO47: =DealsRawTable[[#This Row],[Validated_Annual_Final_Price]]-DealsRawTable[[#This Row],[Cost_to_Serve]] -> 34519.635 | AP47: =DealsRawTable[[#This Row],[Validated_Grossprofit]]/DealsRawTable[[#This Row],[Validated_Annual_Final_Price]] -> 0.63652277 | AQ47: 54231.58 | AR47: 54231.58 | AS47: 34519.635 | AT47: 0.63652277 | AU47: =IF(W47<=0.05,"0–5%", IF(W47<=0.1,"5–10%", IF(W47<=0.15,"10–15%", IF(W47<=0.2,"15–20%", IF(W47<=0.25,"20–25%", IF(W47<=0.3,"25–30%","Above 30%")))))) -> 10–15% | AV47: 113
A48: D00050 | B48: 45741 | C48: C0014 | D48: PUB-0014 | E48: CT00031 | F48: Finance | G48: Public Sector | H48: West | I48: West Commercial | J48: SMB | K48: Yes | L48: 44743 | M48: 80 | N48: Nexus Analytics | O48: Expansion | P48: Multi-year Extension | Q48: 1 | R48: 72 | S48: L. Williams | T48: 74210.126 | U48: =T48*DealsRawTable[[#This Row],[Contract_Years]] -> 74210.126 | V48: 0.142 | W48: 0.127 | X48: 0.004 | Y48: Expansion opportunity | Z48: Pricing Analyst | AA48: 64753.21 | AB48: =DealsRawTable[[#This Row],[Final_Price_ACV]]*DealsRawTable[[#This Row],[Contract_Years]] -> 64753.21 | AC48: 21484.604 | AD48: 43268.607 | AE48: 0.6682079 | AF48: Won | AH48: Yes | AI48: No | AJ48: 64753.21 | AK48: 43268.607 | AL48: Expansion allowed because contract was active | AM48: =ROUND(T48*(1-W48),2) -> 64785.44 | AN48: =DealsRawTable[[#This Row],[Validated_Annual_Final_Price]]*DealsRawTable[[#This Row],[Contract_Years]] -> 64785.44 | AO48: =DealsRawTable[[#This Row],[Validated_Annual_Final_Price]]-DealsRawTable[[#This Row],[Cost_to_Serve]] -> 43300.836 | AP48: =DealsRawTable[[#This Row],[Validated_Grossprofit]]/DealsRawTable[[#This Row],[Validated_Annual_Final_Price]] -> 0.66837296 | AQ48: 64785.44 | AR48: 64785.44 | AS48: 43300.836 | AT48: 0.66837296 | AU48: =IF(W48<=0.05,"0–5%", IF(W48<=0.1,"5–10%", IF(W48<=0.15,"10–15%", IF(W48<=0.2,"15–20%", IF(W48<=0.25,"20–25%", IF(W48<=0.3,"25–30%","Above 30%")))))) -> 10–15% | AV48: 113
A49: D00051 | B49: 45961 | C49: C0014 | D49: PUB-0014 | E49: CT00031 | F49: Finance | G49: Public Sector | H49: West | I49: West Commercial | J49: SMB | K49: Yes | L49: 44743 | M49: 80 | N49: Nexus Analytics | O49: Renewal | Q49: 1 | R49: 72 | S49: M. Johnson | T49: 77343.667 | U49: =T49*DealsRawTable[[#This Row],[Contract_Years]] -> 77343.667 | V49: 0.168 | W49: 0.158 | X49: -0.009 | Y49: Budget constraint | Z49: Pricing Analyst | AA49: 65107.557 | AB49: =DealsRawTable[[#This Row],[Final_Price_ACV]]*DealsRawTable[[#This Row],[Contract_Years]] -> 65107.557 | AC49: 26608.311 | AD49: 38499.245 | AE49: 0.59131762 | AF49: Won | AG49: Yes | AI49: No | AJ49: 65107.557 | AK49: 38499.245 | AL49: Renewal of existing active contract | AM49: =ROUND(T49*(1-W49),2) -> 65123.37 | AN49: =DealsRawTable[[#This Row],[Validated_Annual_Final_Price]]*DealsRawTable[[#This Row],[Contract_Years]] -> 65123.37 | AO49: =DealsRawTable[[#This Row],[Validated_Annual_Final_Price]]-DealsRawTable[[#This Row],[Cost_to_Serve]] -> 38515.059 | AP49: =DealsRawTable[[#This Row],[Validated_Grossprofit]]/DealsRawTable[[#This Row],[Validated_Annual_Final_Price]] -> 0.59141686 | AQ49: 65123.37 | AR49: 65123.37 | AS49: 38515.059 | AT49: 0.59141686 | AU49: =IF(W49<=0.05,"0–5%", IF(W49<=0.1,"5–10%", IF(W49<=0.15,"10–15%", IF(W49<=0.2,"15–20%", IF(W49<=0.25,"20–25%", IF(W49<=0.3,"25–30%","Above 30%")))))) -> 15–20% | AV49: 108
A50: D00052 | B50: 45739 | C50: C0014 | D50: PUB-0014 | E50: CT00032 | F50: Finance | G50: Public Sector | H50: West | I50: West Commercial | J50: SMB | K50: Yes | L50: 44743 | M50: 80 | N50: Nexus Compliance | O50: New Business | Q50: 2 | R50: 73 | S50: D. Chen | T50: 89451.616 | U50: =T50*DealsRawTable[[#This Row],[Contract_Years]] -> 178903.23 | V50: 0.255 | W50: 0.218 | X50: -0.022 | Y50: Volume purchase | Z50: Business Manager | AA50: 69942.781 | AB50: =DealsRawTable[[#This Row],[Final_Price_ACV]]*DealsRawTable[[#This Row],[Contract_Years]] -> 139885.56 | AC50: 31005.628 | AD50: 38937.153 | AE50: 0.5567001 | AF50: Lost | AI50: No | AJ50: 0 | AK50: 0 | AL50: First purchase under this contract | AM50: =ROUND(T50*(1-W50),2) -> 69951.16 | AN50: =DealsRawTable[[#This Row],[Validated_Annual_Final_Price]]*DealsRawTable[[#This Row],[Contract_Years]] -> 139902.32 | AO50: =DealsRawTable[[#This Row],[Validated_Annual_Final_Price]]-DealsRawTable[[#This Row],[Cost_to_Serve]] -> 38945.532 | AP50: =DealsRawTable[[#This Row],[Validated_Grossprofit]]/DealsRawTable[[#This Row],[Validated_Annual_Final_Price]] -> 0.5567532 | AQ50: 0 | AR50: 0 | AS50: 0 | AT50: 0 | AU50: =IF(W50<=0.05,"0–5%", IF(W50<=0.1,"5–10%", IF(W50<=0.15,"10–15%", IF(W50<=0.2,"15–20%", IF(W50<=0.25,"20–25%", IF(W50<=0.3,"25–30%","Above 30%")))))) -> 20–25% | AV50: 29
A51: D00056 | B51: 45626 | C51: C0015 | D51: FIN-0015 | E51: CT00034 | F51: Technology | G51: Financial Services | H51: Northeast | I51: Northeast Commercial | J51: SMB | K51: No | L51: 44470 | M51: 81 | N51: Nexus Compliance | O51: Renewal | Q51: 1 | R51: 74 | S51: S. Rivera | T51: 76441.028 | U51: =T51*DealsRawTable[[#This Row],[Contract_Years]] -> 76441.028 | V51: 0.189 | W51: 0.169 | X51: -0.106 | Y51: Budget constraint | Z51: Pricing Analyst | AA51: 63514.512 | AB51: =DealsRawTable[[#This Row],[Final_Price_ACV]]*DealsRawTable[[#This Row],[Contract_Years]] -> 63514.512 | AC51: 26148.54 | AD51: 37365.972 | AE51: 0.58830605 | AF51: Won | AG51: Yes | AI51: No | AJ51: 63514.512 | AK51: 37365.972 | AL51: Renewal of existing active contract | AM51: =ROUND(T51*(1-W51),2) -> 63522.49 | AN51: =DealsRawTable[[#This Row],[Validated_Annual_Final_Price]]*DealsRawTable[[#This Row],[Contract_Years]] -> 63522.49 | AO51: =DealsRawTable[[#This Row],[Validated_Annual_Final_Price]]-DealsRawTable[[#This Row],[Cost_to_Serve]] -> 37373.95 | AP51: =DealsRawTable[[#This Row],[Validated_Grossprofit]]/DealsRawTable[[#This Row],[Validated_Annual_Final_Price]] -> 0.58835776 | AQ51: 63522.49 | AR51: 63522.49 | AS51: 37373.95 | AT51: 0.58835776 | AU51: =IF(W51<=0.05,"0–5%", IF(W51<=0.1,"5–10%", IF(W51<=0.15,"10–15%", IF(W51<=0.2,"15–20%", IF(W51<=0.25,"20–25%", IF(W51<=0.3,"25–30%","Above 30%")))))) -> 15–20% | AV51: 108
A52: D00057 | B52: 45991 | C52: C0015 | D52: FIN-0015 | E52: CT00034 | F52: Technology | G52: Financial Services | H52: Northeast | I52: Northeast Commercial | J52: SMB | K52: No | L52: 44470 | M52: 81 | N52: Nexus Compliance | O52: Renewal | Q52: 1 | R52: 74 | S52: A. Patel | T52: 80922.44 | U52: =T52*DealsRawTable[[#This Row],[Contract_Years]] -> 80922.44 | V52: 0.022 | W52: 0.021 | X52: 0.015 | Y52: Budget constraint | Z52: Sales Manager | AA52: 79240.897 | AB52: =DealsRawTable[[#This Row],[Final_Price_ACV]]*DealsRawTable[[#This Row],[Contract_Years]] -> 79240.897 | AC52: 26569.301 | AD52: 52671.596 | AE52: 0.66470217 | AF52: Won | AG52: Yes | AI52: No | AJ52: 79240.897 | AK52: 52671.596 | AL52: Renewal of existing active contract | AM52: =ROUND(T52*(1-W52),2) -> 79223.07 | AN52: =DealsRawTable[[#This Row],[Validated_Annual_Final_Price]]*DealsRawTable[[#This Row],[Contract_Years]] -> 79223.07 | AO52: =DealsRawTable[[#This Row],[Validated_Annual_Final_Price]]-DealsRawTable[[#This Row],[Cost_to_Serve]] -> 52653.769 | AP52: =DealsRawTable[[#This Row],[Validated_Grossprofit]]/DealsRawTable[[#This Row],[Validated_Annual_Final_Price]] -> 0.66462672 | AQ52: 79223.07 | AR52: 79223.07 | AS52: 52653.769 | AT52: 0.66462672 | AU52: =IF(W52<=0.05,"0–5%", IF(W52<=0.1,"5–10%", IF(W52<=0.15,"10–15%", IF(W52<=0.2,"15–20%", IF(W52<=0.25,"20–25%", IF(W52<=0.3,"25–30%","Above 30%")))))) -> 0–5% | AV52: 55
A53: D00059 | B53: 45432 | C53: C0016 | D53: HEA-0016 | E53: CT00035 | F53: Legal | G53: Healthcare | H53: South | I53: South Enterprise | J53: Enterprise | K53: Yes | L53: 43221 | M53: 80 | N53: Nexus Enterprise Suite | O53: Expansion | P53: Multi-year Extension | Q53: 1 | R53: 533 | S53: R. Singh | T53: 1157457.9 | U53: =T53*DealsRawTable[[#This Row],[Contract_Years]] -> 1157457.9 | V53: 0.064 | W53: 0.05 | X53: 0.104 | Y53: Expansion opportunity | Z53: Sales Manager | AA53: 1099091.5 | AB53: =DealsRawTable[[#This Row],[Final_Price_ACV]]*DealsRawTable[[#This Row],[Contract_Years]] -> 1099091.5 | AC53: 417114.25 | AD53: 681977.29 | AE53: 0.6204918 | AF53: Won | AH53: Yes | AI53: No | AJ53: 1099091.5 | AK53: 681977.29 | AL53: Expansion allowed because contract was active | AM53: =ROUND(T53*(1-W53),2) -> 1099585.1 | AN53: =DealsRawTable[[#This Row],[Validated_Annual_Final_Price]]*DealsRawTable[[#This Row],[Contract_Years]] -> 1099585.1 | AO53: =DealsRawTable[[#This Row],[Validated_Annual_Final_Price]]-DealsRawTable[[#This Row],[Cost_to_Serve]] -> 682470.8 | AP53: =DealsRawTable[[#This Row],[Validated_Grossprofit]]/DealsRawTable[[#This Row],[Validated_Annual_Final_Price]] -> 0.62066213 | AQ53: 1099585.1 | AR53: 1099585.1 | AS53: 682470.8 | AT53: 0.62066213 | AU53: =IF(W53<=0.05,"0–5%", IF(W53<=0.1,"5–10%", IF(W53<=0.15,"10–15%", IF(W53<=0.2,"15–20%", IF(W53<=0.25,"20–25%", IF(W53<=0.3,"25–30%","Above 30%")))))) -> 0–5% | AV53: 55
A54: D00060 | B54: 45628 | C54: C0016 | D54: HEA-0016 | E54: CT00035 | F54: Legal | G54: Healthcare | H54: South | I54: South Enterprise | J54: Enterprise | K54: Yes | L54: 43221 | M54: 80 | N54: Nexus Enterprise Suite | O54: Renewal | Q54: 1 | R54: 533 | S54: M. Johnson | T54: 1184782.8 | U54: =T54*DealsRawTable[[#This Row],[Contract_Years]] -> 1184782.8 | V54: 0.059 | W54: 0.038 | X54: -0.026 | Y54: Procurement requirement | Z54: Sales Manager | AA54: 1139777.1 | AB54: =DealsRawTable[[#This Row],[Final_Price_ACV]]*DealsRawTable[[#This Row],[Contract_Years]] -> 1139777.1 | AC54: 398219.85 | AD54: 741557.29 | AE54: 0.65061604 | AF54: Won | AG54: Yes | AI54: No | AJ54: 1139777.1 | AK54: 741557.29 | AL54: Renewal of existing active contract | AM54: =ROUND(T54*(1-W54),2) -> 1139761 | AN54: =DealsRawTable[[#This Row],[Validated_Annual_Final_Price]]*DealsRawTable[[#This Row],[Contract_Years]] -> 1139761 | AO54: =DealsRawTable[[#This Row],[Validated_Annual_Final_Price]]-DealsRawTable[[#This Row],[Cost_to_Serve]] -> 741541.17 | AP54: =DealsRawTable[[#This Row],[Validated_Grossprofit]]/DealsRawTable[[#This Row],[Validated_Annual_Final_Price]] -> 0.6506111 | AQ54: 1139761 | AR54: 1139761 | AS54: 741541.17 | AT54: 0.6506111 | AU54: =IF(W54<=0.05,"0–5%", IF(W54<=0.1,"5–10%", IF(W54<=0.15,"10–15%", IF(W54<=0.2,"15–20%", IF(W54<=0.25,"20–25%", IF(W54<=0.3,"25–30%","Above 30%")))))) -> 0–5% | AV54: 55
A55: D00061 | B55: 45993 | C55: C0016 | D55: HEA-0016 | E55: CT00035 | F55: Legal | G55: Healthcare | H55: South | I55: South Enterprise | J55: Enterprise | K55: Yes | L55: 43221 | M55: 80 | N55: Nexus Enterprise Suite | O55: Renewal | Q55: 1 | R55: 533 | S55: R. Singh | T55: 1239770.4 | U55: =T55*DealsRawTable[[#This Row],[Contract_Years]] -> 1239770.4 | V55: 0.065 | W55: 0.031 | X55: 0.005 | Y55: Budget constraint | Z55: Sales Manager | AA55: 1200751.2 | AB55: =DealsRawTable[[#This Row],[Final_Price_ACV]]*DealsRawTable[[#This Row],[Contract_Years]] -> 1200751.2 | AC55: 434910.73 | AD55: 765840.47 | AE55: 0.63780113 | AF55: Won | AG55: Yes | AI55: No | AJ55: 1200751.2 | AK55: 765840.47 | AL55: Renewal of existing active contract | AM55: =ROUND(T55*(1-W55),2) -> 1201337.6 | AN55: =DealsRawTable[[#This Row],[Validated_Annual_Final_Price]]*DealsRawTable[[#This Row],[Contract_Years]] -> 1201337.6 | AO55: =DealsRawTable[[#This Row],[Validated_Annual_Final_Price]]-DealsRawTable[[#This Row],[Cost_to_Serve]] -> 766426.82 | AP55: =DealsRawTable[[#This Row],[Validated_Grossprofit]]/DealsRawTable[[#This Row],[Validated_Annual_Final_Price]] -> 0.63797791 | AQ55: 1201337.6 | AR55: 1201337.6 | AS55: 766426.82 | AT55: 0.63797791 | AU55: =IF(W55<=0.05,"0–5%", IF(W55<=0.1,"5–10%", IF(W55<=0.15,"10–15%", IF(W55<=0.2,"15–20%", IF(W55<=0.25,"20–25%", IF(W55<=0.3,"25–30%","Above 30%")))))) -> 0–5% | AV55: 55
A56: D00062 | B56: 45540 | C56: C0017 | D56: TEC-0017 | E56: CT00038 | F56: Legal | G56: Technology | H56: West | I56: West Commercial | J56: Mid-Market | K56: No | L56: 44958 | M56: 81 | N56: Nexus Enterprise Suite | O56: New Business | Q56: 1 | R56: 145 | S56: T. Brooks | T56: 336527.78 | U56: =T56*DealsRawTable[[#This Row],[Contract_Years]] -> 336527.78 | V56: 0.009 | W56: 0 | X56: 0.07 | Y56: Budget constraint | Z56: Sales Manager | AA56: 336527.78 | AB56: =DealsRawTable[[#This Row],[Final_Price_ACV]]*DealsRawTable[[#This Row],[Contract_Years]] -> 336527.78 | AC56: 139120.9 | AD56: 197406.88 | AE56: 0.58659906 | AF56: Won | AI56: No | AJ56: 336527.78 | AK56: 197406.88 | AL56: First purchase under this contract | AM56: =ROUND(T56*(1-W56),2) -> 336527.78 | AN56: =DealsRawTable[[#This Row],[Validated_Annual_Final_Price]]*DealsRawTable[[#This Row],[Contract_Years]] -> 336527.78 | AO56: =DealsRawTable[[#This Row],[Validated_Annual_Final_Price]]-DealsRawTable[[#This Row],[Cost_to_Serve]] -> 197406.88 | AP56: =DealsRawTable[[#This Row],[Validated_Grossprofit]]/DealsRawTable[[#This Row],[Validated_Annual_Final_Price]] -> 0.58659906 | AQ56: 336527.78 | AR56: 336527.78 | AS56: 197406.88 | AT56: 0.58659906 | AU56: =IF(W56<=0.05,"0–5%", IF(W56<=0.1,"5–10%", IF(W56<=0.15,"10–15%", IF(W56<=0.2,"15–20%", IF(W56<=0.25,"20–25%", IF(W56<=0.3,"25–30%","Above 30%")))))) -> 0–5% | AV56: 55
A57: D00063 | B57: 45905 | C57: C0017 | D57: TEC-0017 | E57: CT00038 | F57: Legal | G57: Technology | H57: West | I57: West Commercial | J57: Mid-Market | K57: No | L57: 44958 | M57: 81 | N57: Nexus Enterprise Suite | O57: Renewal | Q57: 1 | R57: 145 | S57: D. Chen | T57: 351058.04 | U57: =T57*DealsRawTable[[#This Row],[Contract_Years]] -> 351058.04 | V57: 0.215 | W57: 0.197 | X57: -0.062 | Y57: Verified competitor pressure | Z57: Pricing Analyst | AA57: 282013.06 | AB57: =DealsRawTable[[#This Row],[Final_Price_ACV]]*DealsRawTable[[#This Row],[Contract_Years]] -> 282013.06 | AC57: 121286.23 | AD57: 160726.83 | AE57: 0.56992689 | AF57: Lost | AG57: No | AI57: No | AJ57: 0 | AK57: 0 | AL57: Renewal of existing active contract | AM57: =ROUND(T57*(1-W57),2) -> 281899.61 | AN57: =DealsRawTable[[#This Row],[Validated_Annual_Final_Price]]*DealsRawTable[[#This Row],[Contract_Years]] -> 281899.61 | AO57: =DealsRawTable[[#This Row],[Validated_Annual_Final_Price]]-DealsRawTable[[#This Row],[Cost_to_Serve]] -> 160613.38 | AP57: =DealsRawTable[[#This Row],[Validated_Grossprofit]]/DealsRawTable[[#This Row],[Validated_Annual_Final_Price]] -> 0.56975381 | AQ57: 0 | AR57: 0 | AS57: 0 | AT57: 0 | AU57: =IF(W57<=0.05,"0–5%", IF(W57<=0.1,"5–10%", IF(W57<=0.15,"10–15%", IF(W57<=0.2,"15–20%", IF(W57<=0.25,"20–25%", IF(W57<=0.3,"25–30%","Above 30%")))))) -> 15–20% | AV57: 108
A58: D00064 | B58: 45652 | C58: C0018 | D58: PUB-0018 | E58: CT00040 | F58: Sales | G58: Public Sector | H58: South | I58: South Commercial | J58: SMB | K58: No | L58: 44136 | M58: 87 | N58: Nexus AI Assistant | O58: New Business | Q58: 2 | R58: 50 | S58: T. Brooks | T58: 49222.07 | U58: =T58*DealsRawTable[[#This Row],[Contract_Years]] -> 98444.141 | V58: 0.167 | W58: 0.134 | X58: -0.034 | Y58: Multi-year commitment | Z58: Pricing Analyst | AA58: 42645.88 | AB58: =DealsRawTable[[#This Row],[Final_Price_ACV]]*DealsRawTable[[#This Row],[Contract_Years]] -> 85291.761 | AC58: 18354.391 | AD58: 24291.489 | AE58: 0.56960929 | AF58: Won | AI58: No | AJ58: 42645.88 | AK58: 24291.489 | AL58: First purchase under this contract | AM58: =ROUND(T58*(1-W58),2) -> 42626.31 | AN58: =DealsRawTable[[#This Row],[Validated_Annual_Final_Price]]*DealsRawTable[[#This Row],[Contract_Years]] -> 85252.62 | AO58: =DealsRawTable[[#This Row],[Validated_Annual_Final_Price]]-DealsRawTable[[#This Row],[Cost_to_Serve]] -> 24271.919 | AP58: =DealsRawTable[[#This Row],[Validated_Grossprofit]]/DealsRawTable[[#This Row],[Validated_Annual_Final_Price]] -> 0.56941169 | AQ58: 42626.31 | AR58: 85252.62 | AS58: 24271.919 | AT58: 0.56941169 | AU58: =IF(W58<=0.05,"0–5%", IF(W58<=0.1,"5–10%", IF(W58<=0.15,"10–15%", IF(W58<=0.2,"15–20%", IF(W58<=0.25,"20–25%", IF(W58<=0.3,"25–30%","Above 30%")))))) -> 10–15% | AV58: 113
A59: D00065 | B59: 45508 | C59: C0019 | D59: MAN-0019 | E59: CT00041 | F59: Technology | G59: Manufacturing | H59: West | I59: West Enterprise | J59: Enterprise | K59: No | L59: 43435 | M59: 86 | N59: Nexus Analytics | O59: Expansion | P59: Enterprise Upgrade | Q59: 3 | R59: 681 | S59: L. Williams | T59: 289447.96 | U59: =T59*DealsRawTable[[#This Row],[Contract_Years]] -> 868343.88 | V59: 0.06 | W59: 0.03 | X59: 0.022 | Y59: Expansion opportunity | Z59: Sales Manager | AA59: 280672.97 | AB59: =DealsRawTable[[#This Row],[Final_Price_ACV]]*DealsRawTable[[#This Row],[Contract_Years]] -> 842018.92 | AC59: 101542.38 | AD59: 179130.6 | AE59: 0.63821819 | AF59: Lost | AH59: No | AI59: No | AJ59: 0 | AK59: 0 | AL59: Expansion allowed because contract was active | AM59: =ROUND(T59*(1-W59),2) -> 280764.52 | AN59: =DealsRawTable[[#This Row],[Validated_Annual_Final_Price]]*DealsRawTable[[#This Row],[Contract_Years]] -> 842293.56 | AO59: =DealsRawTable[[#This Row],[Validated_Annual_Final_Price]]-DealsRawTable[[#This Row],[Cost_to_Serve]] -> 179222.14 | AP59: =DealsRawTable[[#This Row],[Validated_Grossprofit]]/DealsRawTable[[#This Row],[Validated_Annual_Final_Price]] -> 0.63833616 | AQ59: 0 | AR59: 0 | AS59: 0 | AT59: 0 | AU59: =IF(W59<=0.05,"0–5%", IF(W59<=0.1,"5–10%", IF(W59<=0.15,"10–15%", IF(W59<=0.2,"15–20%", IF(W59<=0.25,"20–25%", IF(W59<=0.3,"25–30%","Above 30%")))))) -> 0–5% | AV59: 55
A60: D00066 | B60: 45676 | C60: C0019 | D60: MAN-0019 | E60: CT00041 | F60: Technology | G60: Manufacturing | H60: West | I60: West Enterprise | J60: Enterprise | K60: No | L60: 43435 | M60: 86 | N60: Nexus Analytics | O60: Renewal | Q60: 3 | R60: 596 | S60: A. Patel | T60: 273862.35 | U60: =T60*DealsRawTable[[#This Row],[Contract_Years]] -> 821587.05 | V60: 0.211 | W60: 0.177 | X60: -0.09 | Y60: Verified competitor pressure | Z60: Pricing Analyst | AA60: 225488.39 | AB60: =DealsRawTable[[#This Row],[Final_Price_ACV]]*DealsRawTable[[#This Row],[Contract_Years]] -> 676465.17 | AC60: 74877.975 | AD60: 150610.41 | AE60: 0.6679298 | AF60: Won | AG60: Yes | AI60: No | AJ60: 225488.39 | AK60: 150610.41 | AL60: Renewal of existing active contract | AM60: =ROUND(T60*(1-W60),2) -> 225388.71 | AN60: =DealsRawTable[[#This Row],[Validated_Annual_Final_Price]]*DealsRawTable[[#This Row],[Contract_Years]] -> 676166.13 | AO60: =DealsRawTable[[#This Row],[Validated_Annual_Final_Price]]-DealsRawTable[[#This Row],[Cost_to_Serve]] -> 150510.73 | AP60: =DealsRawTable[[#This Row],[Validated_Grossprofit]]/DealsRawTable[[#This Row],[Validated_Annual_Final_Price]] -> 0.66778294 | AQ60: 225388.71 | AR60: 676166.13 | AS60: 150510.73 | AT60: 0.66778294 | AU60: =IF(W60<=0.05,"0–5%", IF(W60<=0.1,"5–10%", IF(W60<=0.15,"10–15%", IF(W60<=0.2,"15–20%", IF(W60<=0.25,"20–25%", IF(W60<=0.3,"25–30%","Above 30%")))))) -> 15–20% | AV60: 108
A61: D00067 | B61: 45488 | C61: C0019 | D61: MAN-0019 | E61: CT00042 | F61: Legal | G61: Manufacturing | H61: West | I61: West Enterprise | J61: Enterprise | K61: No | L61: 43435 | M61: 86 | N61: Nexus Insights | O61: New Business | Q61: 1 | R61: 1723 | S61: K. Nguyen | T61: 137877.26 | U61: =T61*DealsRawTable[[#This Row],[Contract_Years]] -> 137877.26 | V61: 0.21 | W61: 0.166 | X61: 0.027 | Y61: Renewal retention risk | Z61: Pricing Analyst | AA61: 114993.43 | AB61: =DealsRawTable[[#This Row],[Final_Price_ACV]]*DealsRawTable[[#This Row],[Contract_Years]] -> 114993.43 | AC61: 46709.96 | AD61: 68283.471 | AE61: 0.59380323 | AF61: Lost | AI61: No | AJ61: 0 | AK61: 0 | AL61: First purchase under this contract | AM61: =ROUND(T61*(1-W61),2) -> 114989.64 | AN61: =DealsRawTable[[#This Row],[Validated_Annual_Final_Price]]*DealsRawTable[[#This Row],[Contract_Years]] -> 114989.64 | AO61: =DealsRawTable[[#This Row],[Validated_Annual_Final_Price]]-DealsRawTable[[#This Row],[Cost_to_Serve]] -> 68279.68 | AP61: =DealsRawTable[[#This Row],[Validated_Grossprofit]]/DealsRawTable[[#This Row],[Validated_Annual_Final_Price]] -> 0.59378984 | AQ61: 0 | AR61: 0 | AS61: 0 | AT61: 0 | AU61: =IF(W61<=0.05,"0–5%", IF(W61<=0.1,"5–10%", IF(W61<=0.15,"10–15%", IF(W61<=0.2,"15–20%", IF(W61<=0.25,"20–25%", IF(W61<=0.3,"25–30%","Above 30%")))))) -> 15–20% | AV61: 108
A62: D00070 | B62: 45293 | C62: C0020 | D62: LEG-0020 | E62: CT00043 | F62: Sales | G62: Legal | H62: South | I62: South Enterprise | J62: Enterprise | K62: No | L62: 43739 | M62: 78 | N62: Nexus Enterprise Suite | O62: Renewal | Q62: 1 | R62: 259 | S62: T. Brooks | T62: 620606.73 | U62: =T62*DealsRawTable[[#This Row],[Contract_Years]] -> 620606.73 | V62: 0.14 | W62: 0.121 | X62: 0.012 | Y62: Procurement requirement | Z62: Pricing Analyst | AA62: 545559.12 | AB62: =DealsRawTable[[#This Row],[Final_Price_ACV]]*DealsRawTable[[#This Row],[Contract_Years]] -> 545559.12 | AC62: 212776.07 | AD62: 332783.04 | AE62: 0.6099853 | AF62: Won | AG62: Yes | AI62: No | AJ62: 545559.12 | AK62: 332783.04 | AL62: Renewal of existing active contract | AM62: =ROUND(T62*(1-W62),2) -> 545513.32 | AN62: =DealsRawTable[[#This Row],[Validated_Annual_Final_Price]]*DealsRawTable[[#This Row],[Contract_Years]] -> 545513.32 | AO62: =DealsRawTable[[#This Row],[Validated_Annual_Final_Price]]-DealsRawTable[[#This Row],[Cost_to_Serve]] -> 332737.25 | AP62: =DealsRawTable[[#This Row],[Validated_Grossprofit]]/DealsRawTable[[#This Row],[Validated_Annual_Final_Price]] -> 0.60995256 | AQ62: 545513.32 | AR62: 545513.32 | AS62: 332737.25 | AT62: 0.60995256 | AU62: =IF(W62<=0.05,"0–5%", IF(W62<=0.1,"5–10%", IF(W62<=0.15,"10–15%", IF(W62<=0.2,"15–20%", IF(W62<=0.25,"20–25%", IF(W62<=0.3,"25–30%","Above 30%")))))) -> 10–15% | AV62: 113
A63: D00071 | B63: 45658 | C63: C0020 | D63: LEG-0020 | E63: CT00043 | F63: Sales | G63: Legal | H63: South | I63: South Enterprise | J63: Enterprise | K63: No | L63: 43739 | M63: 78 | N63: Nexus Enterprise Suite | O63: Renewal | Q63: 1 | R63: 259 | S63: K. Nguyen | T63: 639965.13 | U63: =T63*DealsRawTable[[#This Row],[Contract_Years]] -> 639965.13 | V63: 0.139 | W63: 0.102 | X63: -0.03 | Y63: Multi-year commitment | Z63: Pricing Analyst | AA63: 574726.14 | AB63: =DealsRawTable[[#This Row],[Final_Price_ACV]]*DealsRawTable[[#This Row],[Contract_Years]] -> 574726.14 | AC63: 228296.11 | AD63: 346430.03 | AE63: 0.6027741 | AF63: Won | AG63: Yes | AI63: No | AJ63: 574726.14 | AK63: 346430.03 | AL63: Renewal of existing active contract | AM63: =ROUND(T63*(1-W63),2) -> 574688.69 | AN63: =DealsRawTable[[#This Row],[Validated_Annual_Final_Price]]*DealsRawTable[[#This Row],[Contract_Years]] -> 574688.69 | AO63: =DealsRawTable[[#This Row],[Validated_Annual_Final_Price]]-DealsRawTable[[#This Row],[Cost_to_Serve]] -> 346392.58 | AP63: =DealsRawTable[[#This Row],[Validated_Grossprofit]]/DealsRawTable[[#This Row],[Validated_Annual_Final_Price]] -> 0.60274822 | AQ63: 574688.69 | AR63: 574688.69 | AS63: 346392.58 | AT63: 0.60274822 | AU63: =IF(W63<=0.05,"0–5%", IF(W63<=0.1,"5–10%", IF(W63<=0.15,"10–15%", IF(W63<=0.2,"15–20%", IF(W63<=0.25,"20–25%", IF(W63<=0.3,"25–30%","Above 30%")))))) -> 10–15% | AV63: 113
A64: D00072 | B64: 45740 | C64: C0020 | D64: LEG-0020 | E64: CT00044 | F64: Finance | G64: Legal | H64: South | I64: South Enterprise | J64: Enterprise | K64: No | L64: 43739 | M64: 78 | N64: Nexus AI Assistant | O64: New Business | Q64: 3 | R64: 526 | S64: S. Rivera | T64: 206904.51 | U64: =T64*DealsRawTable[[#This Row],[Contract_Years]] -> 620713.52 | V64: 0.135 | W64: 0.098 | X64: -0.109 | Y64: Renewal retention risk | Z64: Sales Manager | AA64: 186664.25 | AB64: =DealsRawTable[[#This Row],[Final_Price_ACV]]*DealsRawTable[[#This Row],[Contract_Years]] -> 559992.75 | AC64: 82827.288 | AD64: 103836.96 | AE64: 0.55627664 | AF64: Lost | AI64: No | AJ64: 0 | AK64: 0 | AL64: First purchase under this contract | AM64: =ROUND(T64*(1-W64),2) -> 186627.87 | AN64: =DealsRawTable[[#This Row],[Validated_Annual_Final_Price]]*DealsRawTable[[#This Row],[Contract_Years]] -> 559883.61 | AO64: =DealsRawTable[[#This Row],[Validated_Annual_Final_Price]]-DealsRawTable[[#This Row],[Cost_to_Serve]] -> 103800.58 | AP64: =DealsRawTable[[#This Row],[Validated_Grossprofit]]/DealsRawTable[[#This Row],[Validated_Annual_Final_Price]] -> 0.55619014 | AQ64: 0 | AR64: 0 | AS64: 0 | AT64: 0 | AU64: =IF(W64<=0.05,"0–5%", IF(W64<=0.1,"5–10%", IF(W64<=0.15,"10–15%", IF(W64<=0.2,"15–20%", IF(W64<=0.25,"20–25%", IF(W64<=0.3,"25–30%","Above 30%")))))) -> 5–10% | AV64: 116
A65: D00073 | B65: 45548 | C65: C0021 | D65: HEA-0021 | E65: CT00045 | F65: Legal | G65: Healthcare | H65: Midwest | I65: Midwest Commercial | J65: SMB | K65: No | L65: 44743 | M65: 81 | N65: Nexus Analytics | O65: New Business | Q65: 1 | R65: 68 | S65: D. Chen | T65: 46855.348 | U65: =T65*DealsRawTable[[#This Row],[Contract_Years]] -> 46855.348 | V65: 0.092 | W65: 0.078 | X65: 0.003 | Y65: Strategic logo opportunity | Z65: Sales Manager | AA65: 43200.502 | AB65: =DealsRawTable[[#This Row],[Final_Price_ACV]]*DealsRawTable[[#This Row],[Contract_Years]] -> 43200.502 | AC65: 14389.641 | AD65: 28810.86 | AE65: 0.66691031 | AF65: Lost | AI65: No | AJ65: 0 | AK65: 0 | AL65: First purchase under this contract | AM65: =ROUND(T65*(1-W65),2) -> 43200.63 | AN65: =DealsRawTable[[#This Row],[Validated_Annual_Final_Price]]*DealsRawTable[[#This Row],[Contract_Years]] -> 43200.63 | AO65: =DealsRawTable[[#This Row],[Validated_Annual_Final_Price]]-DealsRawTable[[#This Row],[Cost_to_Serve]] -> 28810.989 | AP65: =DealsRawTable[[#This Row],[Validated_Grossprofit]]/DealsRawTable[[#This Row],[Validated_Annual_Final_Price]] -> 0.6669113 | AQ65: 0 | AR65: 0 | AS65: 0 | AT65: 0 | AU65: =IF(W65<=0.05,"0–5%", IF(W65<=0.1,"5–10%", IF(W65<=0.15,"10–15%", IF(W65<=0.2,"15–20%", IF(W65<=0.25,"20–25%", IF(W65<=0.3,"25–30%","Above 30%")))))) -> 5–10% | AV65: 116
A66: D00074 | B66: 45870 | C66: C0021 | D66: HEA-0021 | E66: CT00045 | F66: Legal | G66: Healthcare | H66: Midwest | I66: Midwest Commercial | J66: SMB | K66: No | L66: 44743 | M66: 81 | N66: Nexus Analytics | O66: Win-back | Q66: 1 | R66: 68 | S66: L. Williams | T66: 46855.348 | U66: =T66*DealsRawTable[[#This Row],[Contract_Years]] -> 46855.348 | V66: 0.226 | W66: 0.211 | X66: -0.076 | Y66: Renewal retention risk | Z66: Business Manager | AA66: 36972.628 | AB66: =DealsRawTable[[#This Row],[Final_Price_ACV]]*DealsRawTable[[#This Row],[Contract_Years]] -> 36972.628 | AC66: 16372.349 | AD66: 20600.279 | AE66: 0.55717648 | AF66: Won | AI66: Yes | AJ66: 36972.628 | AK66: 20600.279 | AL66: Customer returned after prior lost initial opportunity | AM66: =ROUND(T66*(1-W66),2) -> 36968.87 | AN66: =DealsRawTable[[#This Row],[Validated_Annual_Final_Price]]*DealsRawTable[[#This Row],[Contract_Years]] -> 36968.87 | AO66: =DealsRawTable[[#This Row],[Validated_Annual_Final_Price]]-DealsRawTable[[#This Row],[Cost_to_Serve]] -> 20596.521 | AP66: =DealsRawTable[[#This Row],[Validated_Grossprofit]]/DealsRawTable[[#This Row],[Validated_Annual_Final_Price]] -> 0.55713147 | AQ66: 36968.87 | AR66: 36968.87 | AS66: 20596.521 | AT66: 0.55713147 | AU66: =IF(W66<=0.05,"0–5%", IF(W66<=0.1,"5–10%", IF(W66<=0.15,"10–15%", IF(W66<=0.2,"15–20%", IF(W66<=0.25,"20–25%", IF(W66<=0.3,"25–30%","Above 30%")))))) -> 20–25% | AV66: 29
A67: D00075 | B67: 45337 | C67: C0021 | D67: HEA-0021 | E67: CT00046 | F67: Finance | G67: Healthcare | H67: Midwest | I67: Midwest Commercial | J67: SMB | K67: No | L67: 44743 | M67: 81 | N67: Nexus Compliance | O67: New Business | Q67: 2 | R67: 45 | S67: A. Patel | T67: 75480.443 | U67: =T67*DealsRawTable[[#This Row],[Contract_Years]] -> 150960.89 | V67: 0.089 | W67: 0.08 | X67: 0.042 | Y67: Expansion opportunity | Z67: Sales Manager | AA67: 69441.091 | AB67: =DealsRawTable[[#This Row],[Final_Price_ACV]]*DealsRawTable[[#This Row],[Contract_Years]] -> 138882.18 | AC67: 27371.75 | AD67: 42069.341 | AE67: 0.60582776 | AF67: Won | AI67: No | AJ67: 69441.091 | AK67: 42069.341 | AL67: First purchase under this contract | AM67: =ROUND(T67*(1-W67),2) -> 69442.01 | AN67: =DealsRawTable[[#This Row],[Validated_Annual_Final_Price]]*DealsRawTable[[#This Row],[Contract_Years]] -> 138884.02 | AO67: =DealsRawTable[[#This Row],[Validated_Annual_Final_Price]]-DealsRawTable[[#This Row],[Cost_to_Serve]] -> 42070.26 | AP67: =DealsRawTable[[#This Row],[Validated_Grossprofit]]/DealsRawTable[[#This Row],[Validated_Annual_Final_Price]] -> 0.60583298 | AQ67: 69442.01 | AR67: 138884.02 | AS67: 42070.26 | AT67: 0.60583298 | AU67: =IF(W67<=0.05,"0–5%", IF(W67<=0.1,"5–10%", IF(W67<=0.15,"10–15%", IF(W67<=0.2,"15–20%", IF(W67<=0.25,"20–25%", IF(W67<=0.3,"25–30%","Above 30%")))))) -> 5–10% | AV67: 116
A68: D00076 | B68: 45744 | C68: C0021 | D68: HEA-0021 | E68: CT00047 | F68: Operations | G68: Healthcare | H68: Midwest | I68: Midwest Commercial | J68: SMB | K68: No | L68: 44743 | M68: 81 | N68: Nexus Compliance | O68: New Business | Q68: 3 | R68: 48 | S68: L. Williams | T68: 92549.228 | U68: =T68*DealsRawTable[[#This Row],[Contract_Years]] -> 277647.69 | V68: 0.204 | W68: 0.198 | X68: -0.07 | Y68: Verified competitor pressure | Z68: Pricing Analyst | AA68: 74238.653 | AB68: =DealsRawTable[[#This Row],[Final_Price_ACV]]*DealsRawTable[[#This Row],[Contract_Years]] -> 222715.96 | AC68: 35240.868 | AD68: 38997.784 | AE68: 0.52530296 | AF68: Lost | AI68: No | AJ68: 0 | AK68: 0 | AL68: First purchase under this contract | AM68: =ROUND(T68*(1-W68),2) -> 74224.48 | AN68: =DealsRawTable[[#This Row],[Validated_Annual_Final_Price]]*DealsRawTable[[#This Row],[Contract_Years]] -> 222673.44 | AO68: =DealsRawTable[[#This Row],[Validated_Annual_Final_Price]]-DealsRawTable[[#This Row],[Cost_to_Serve]] -> 38983.612 | AP68: =DealsRawTable[[#This Row],[Validated_Grossprofit]]/DealsRawTable[[#This Row],[Validated_Annual_Final_Price]] -> 0.52521232 | AQ68: 0 | AR68: 0 | AS68: 0 | AT68: 0 | AU68: =IF(W68<=0.05,"0–5%", IF(W68<=0.1,"5–10%", IF(W68<=0.15,"10–15%", IF(W68<=0.2,"15–20%", IF(W68<=0.25,"20–25%", IF(W68<=0.3,"25–30%","Above 30%")))))) -> 15–20% | AV68: 108
A69: D00077 | B69: 45520 | C69: C0022 | D69: PUB-0022 | E69: CT00048 | F69: Operations | G69: Public Sector | H69: Northeast | I69: Northeast Commercial | J69: Mid-Market | K69: No | L69: 43952 | M69: 53 | N69: Nexus Analytics | O69: Renewal | Q69: 1 | R69: 339 | S69: M. Johnson | T69: 86522.162 | U69: =T69*DealsRawTable[[#This Row],[Contract_Years]] -> 86522.162 | V69: 0.185 | W69: 0.18 | X69: -0.001 | Y69: Renewal retention risk | Z69: Pricing Analyst | AA69: 70946.785 | AB69: =DealsRawTable[[#This Row],[Final_Price_ACV]]*DealsRawTable[[#This Row],[Contract_Years]] -> 70946.785 | AC69: 26552.027 | AD69: 44394.758 | AE69: 0.62574728 | AF69: Won | AG69: Yes | AI69: No | AJ69: 70946.785 | AK69: 44394.758 | AL69: Renewal of existing active contract | AM69: =ROUND(T69*(1-W69),2) -> 70948.17 | AN69: =DealsRawTable[[#This Row],[Validated_Annual_Final_Price]]*DealsRawTable[[#This Row],[Contract_Years]] -> 70948.17 | AO69: =DealsRawTable[[#This Row],[Validated_Annual_Final_Price]]-DealsRawTable[[#This Row],[Cost_to_Serve]] -> 44396.143 | AP69: =DealsRawTable[[#This Row],[Validated_Grossprofit]]/DealsRawTable[[#This Row],[Validated_Annual_Final_Price]] -> 0.62575459 | AQ69: 70948.17 | AR69: 70948.17 | AS69: 44396.143 | AT69: 0.62575459 | AU69: =IF(W69<=0.05,"0–5%", IF(W69<=0.1,"5–10%", IF(W69<=0.15,"10–15%", IF(W69<=0.2,"15–20%", IF(W69<=0.25,"20–25%", IF(W69<=0.3,"25–30%","Above 30%")))))) -> 15–20% | AV69: 108
A70: D00078 | B70: 45885 | C70: C0022 | D70: PUB-0022 | E70: CT00048 | F70: Operations | G70: Public Sector | H70: Northeast | I70: Northeast Commercial | J70: Mid-Market | K70: No | L70: 43952 | M70: 53 | N70: Nexus Analytics | O70: Renewal | Q70: 1 | R70: 339 | S70: R. Singh | T70: 92015.976 | U70: =T70*DealsRawTable[[#This Row],[Contract_Years]] -> 92015.976 | V70: 0.133 | W70: 0.1 | X70: -0.029 | Y70: Renewal retention risk | Z70: Sales Manager | AA70: 82825.088 | AB70: =DealsRawTable[[#This Row],[Final_Price_ACV]]*DealsRawTable[[#This Row],[Contract_Years]] -> 82825.088 | AC70: 27647.365 | AD70: 55177.722 | AE70: 0.66619576 | AF70: Lost | AG70: No | AI70: No | AJ70: 0 | AK70: 0 | AL70: Renewal of existing active contract | AM70: =ROUND(T70*(1-W70),2) -> 82814.38 | AN70: =DealsRawTable[[#This Row],[Validated_Annual_Final_Price]]*DealsRawTable[[#This Row],[Contract_Years]] -> 82814.38 | AO70: =DealsRawTable[[#This Row],[Validated_Annual_Final_Price]]-DealsRawTable[[#This Row],[Cost_to_Serve]] -> 55167.015 | AP70: =DealsRawTable[[#This Row],[Validated_Grossprofit]]/DealsRawTable[[#This Row],[Validated_Annual_Final_Price]] -> 0.6661526 | AQ70: 0 | AR70: 0 | AS70: 0 | AT70: 0 | AU70: =IF(W70<=0.05,"0–5%", IF(W70<=0.1,"5–10%", IF(W70<=0.15,"10–15%", IF(W70<=0.2,"15–20%", IF(W70<=0.25,"20–25%", IF(W70<=0.3,"25–30%","Above 30%")))))) -> 5–10% | AV70: 116
A71: D00079 | B71: 45654 | C71: C0022 | D71: PUB-0022 | E71: CT00049 | F71: Operations | G71: Public Sector | H71: Northeast | I71: Northeast Commercial | J71: Mid-Market | K71: No | L71: 43952 | M71: 53 | N71: Nexus AI Assistant | O71: Expansion | P71: Module Add-on | Q71: 2 | R71: 300 | S71: L. Williams | T71: 55658.749 | U71: =T71*DealsRawTable[[#This Row],[Contract_Years]] -> 111317.5 | V71: 0.117 | W71: 0.098 | X71: -0.057 | Y71: Expansion opportunity | Z71: Sales Manager | AA71: 50202.624 | AB71: =DealsRawTable[[#This Row],[Final_Price_ACV]]*DealsRawTable[[#This Row],[Contract_Years]] -> 100405.25 | AC71: 20030.992 | AD71: 30171.632 | AE71: 0.60099711 | AF71: Won | AH71: Yes | AI71: No | AJ71: 50202.624 | AK71: 30171.632 | AL71: Expansion allowed because contract was active | AM71: =ROUND(T71*(1-W71),2) -> 50204.19 | AN71: =DealsRawTable[[#This Row],[Validated_Annual_Final_Price]]*DealsRawTable[[#This Row],[Contract_Years]] -> 100408.38 | AO71: =DealsRawTable[[#This Row],[Validated_Annual_Final_Price]]-DealsRawTable[[#This Row],[Cost_to_Serve]] -> 30173.198 | AP71: =DealsRawTable[[#This Row],[Validated_Grossprofit]]/DealsRawTable[[#This Row],[Validated_Annual_Final_Price]] -> 0.60100956 | AQ71: 50204.19 | AR71: 100408.38 | AS71: 30173.198 | AT71: 0.60100956 | AU71: =IF(W71<=0.05,"0–5%", IF(W71<=0.1,"5–10%", IF(W71<=0.15,"10–15%", IF(W71<=0.2,"15–20%", IF(W71<=0.25,"20–25%", IF(W71<=0.3,"25–30%","Above 30%")))))) -> 5–10% | AV71: 116
A72: D00080 | B72: 45795 | C72: C0022 | D72: PUB-0022 | E72: CT00049 | F72: Operations | G72: Public Sector | H72: Northeast | I72: Northeast Commercial | J72: Mid-Market | K72: No | L72: 43952 | M72: 53 | N72: Nexus AI Assistant | O72: Renewal | Q72: 2 | R72: 300 | S72: M. Johnson | T72: 57475.25 | U72: =T72*DealsRawTable[[#This Row],[Contract_Years]] -> 114950.5 | V72: 0.087 | W72: 0.07 | X72: -0.085 | Y72: Renewal retention risk | Z72: Sales Manager | AA72: 53461.192 | AB72: =DealsRawTable[[#This Row],[Final_Price_ACV]]*DealsRawTable[[#This Row],[Contract_Years]] -> 106922.38 | AC72: 21274.063 | AD72: 32187.129 | AE72: 0.60206531 | AF72: Lost | AG72: No | AI72: No | AJ72: 0 | AK72: 0 | AL72: Renewal of existing active contract | AM72: =ROUND(T72*(1-W72),2) -> 53451.98 | AN72: =DealsRawTable[[#This Row],[Validated_Annual_Final_Price]]*DealsRawTable[[#This Row],[Contract_Years]] -> 106903.96 | AO72: =DealsRawTable[[#This Row],[Validated_Annual_Final_Price]]-DealsRawTable[[#This Row],[Cost_to_Serve]] -> 32177.917 | AP72: =DealsRawTable[[#This Row],[Validated_Grossprofit]]/DealsRawTable[[#This Row],[Validated_Annual_Final_Price]] -> 0.60199673 | AQ72: 0 | AR72: 0 | AS72: 0 | AT72: 0 | AU72: =IF(W72<=0.05,"0–5%", IF(W72<=0.1,"5–10%", IF(W72<=0.15,"10–15%", IF(W72<=0.2,"15–20%", IF(W72<=0.25,"20–25%", IF(W72<=0.3,"25–30%","Above 30%")))))) -> 5–10% | AV72: 116
A73: D00081 | B73: 45320 | C73: C0022 | D73: PUB-0022 | E73: CT00050 | F73: Legal | G73: Public Sector | H73: Northeast | I73: Northeast Commercial | J73: Mid-Market | K73: No | L73: 43952 | M73: 53 | N73: Nexus Analytics | O73: New Business | Q73: 1 | R73: 125 | S73: L. Williams | T73: 124310.04 | U73: =T73*DealsRawTable[[#This Row],[Contract_Years]] -> 124310.04 | V73: 0.084 | W73: 0.068 | X73: 0 | Y73: Verified competitor pressure | Z73: Sales Manager | AA73: 115858.19 | AB73: =DealsRawTable[[#This Row],[Final_Price_ACV]]*DealsRawTable[[#This Row],[Contract_Years]] -> 115858.19 | AC73: 45971.149 | AD73: 69887.041 | AE73: 0.60321191 | AF73: Won | AI73: No | AJ73: 115858.19 | AK73: 69887.041 | AL73: First purchase under this contract | AM73: =ROUND(T73*(1-W73),2) -> 115856.96 | AN73: =DealsRawTable[[#This Row],[Validated_Annual_Final_Price]]*DealsRawTable[[#This Row],[Contract_Years]] -> 115856.96 | AO73: =DealsRawTable[[#This Row],[Validated_Annual_Final_Price]]-DealsRawTable[[#This Row],[Cost_to_Serve]] -> 69885.811 | AP73: =DealsRawTable[[#This Row],[Validated_Grossprofit]]/DealsRawTable[[#This Row],[Validated_Annual_Final_Price]] -> 0.6032077 | AQ73: 115856.96 | AR73: 115856.96 | AS73: 69885.811 | AT73: 0.6032077 | AU73: =IF(W73<=0.05,"0–5%", IF(W73<=0.1,"5–10%", IF(W73<=0.15,"10–15%", IF(W73<=0.2,"15–20%", IF(W73<=0.25,"20–25%", IF(W73<=0.3,"25–30%","Above 30%")))))) -> 5–10% | AV73: 116
A74: D00082 | B74: 45472 | C74: C0022 | D74: PUB-0022 | E74: CT00050 | F74: Legal | G74: Public Sector | H74: Northeast | I74: Northeast Commercial | J74: Mid-Market | K74: No | L74: 43952 | M74: 53 | N74: Nexus Analytics | O74: Expansion | P74: AI Add-on | Q74: 1 | R74: 140 | S74: D. Chen | T74: 135021.92 | U74: =T74*DealsRawTable[[#This Row],[Contract_Years]] -> 135021.92 | V74: 0.089 | W74: 0.087 | X74: -0.01 | Y74: Expansion opportunity | Z74: Sales Manager | AA74: 123307.69 | AB74: =DealsRawTable[[#This Row],[Final_Price_ACV]]*DealsRawTable[[#This Row],[Contract_Years]] -> 123307.69 | AC74: 48396.562 | AD74: 74911.127 | AE74: 0.60751384 | AF74: Won | AH74: Yes | AI74: No | AJ74: 123307.69 | AK74: 74911.127 | AL74: Expansion allowed because contract was active | AM74: =ROUND(T74*(1-W74),2) -> 123275.01 | AN74: =DealsRawTable[[#This Row],[Validated_Annual_Final_Price]]*DealsRawTable[[#This Row],[Contract_Years]] -> 123275.01 | AO74: =DealsRawTable[[#This Row],[Validated_Annual_Final_Price]]-DealsRawTable[[#This Row],[Cost_to_Serve]] -> 74878.448 | AP74: =DealsRawTable[[#This Row],[Validated_Grossprofit]]/DealsRawTable[[#This Row],[Validated_Annual_Final_Price]] -> 0.60740979 | AQ74: 123275.01 | AR74: 123275.01 | AS74: 74878.448 | AT74: 0.60740979 | AU74: =IF(W74<=0.05,"0–5%", IF(W74<=0.1,"5–10%", IF(W74<=0.15,"10–15%", IF(W74<=0.2,"15–20%", IF(W74<=0.25,"20–25%", IF(W74<=0.3,"25–30%","Above 30%")))))) -> 5–10% | AV74: 116
A75: D00083 | B75: 45685 | C75: C0022 | D75: PUB-0022 | E75: CT00050 | F75: Legal | G75: Public Sector | H75: Northeast | I75: Northeast Commercial | J75: Mid-Market | K75: No | L75: 43952 | M75: 53 | N75: Nexus Analytics | O75: Renewal | Q75: 1 | R75: 140 | S75: L. Williams | T75: 139959.62 | U75: =T75*DealsRawTable[[#This Row],[Contract_Years]] -> 139959.62 | V75: 0.12 | W75: 0.077 | X75: 0.028 | Y75: Renewal retention risk | Z75: Sales Manager | AA75: 129150.83 | AB75: =DealsRawTable[[#This Row],[Final_Price_ACV]]*DealsRawTable[[#This Row],[Contract_Years]] -> 129150.83 | AC75: 41549.279 | AD75: 87601.551 | AE75: 0.67828872 | AF75: Lost | AG75: No | AI75: No | AJ75: 0 | AK75: 0 | AL75: Renewal of existing active contract | AM75: =ROUND(T75*(1-W75),2) -> 129182.73 | AN75: =DealsRawTable[[#This Row],[Validated_Annual_Final_Price]]*DealsRawTable[[#This Row],[Contract_Years]] -> 129182.73 | AO75: =DealsRawTable[[#This Row],[Validated_Annual_Final_Price]]-DealsRawTable[[#This Row],[Cost_to_Serve]] -> 87633.451 | AP75: =DealsRawTable[[#This Row],[Validated_Grossprofit]]/DealsRawTable[[#This Row],[Validated_Annual_Final_Price]] -> 0.67836816 | AQ75: 0 | AR75: 0 | AS75: 0 | AT75: 0 | AU75: =IF(W75<=0.05,"0–5%", IF(W75<=0.1,"5–10%", IF(W75<=0.15,"10–15%", IF(W75<=0.2,"15–20%", IF(W75<=0.25,"20–25%", IF(W75<=0.3,"25–30%","Above 30%")))))) -> 5–10% | AV75: 116
A76: D00084 | B76: 45648 | C76: C0022 | D76: PUB-0022 | E76: CT00051 | F76: Operations | G76: Public Sector | H76: Northeast | I76: Northeast Commercial | J76: Mid-Market | K76: No | L76: 43952 | M76: 53 | N76: Nexus Compliance | O76: Renewal | Q76: 1 | R76: 331 | S76: A. Patel | T76: 116336.9 | U76: =T76*DealsRawTable[[#This Row],[Contract_Years]] -> 116336.9 | V76: 0.202 | W76: 0.179 | X76: 0.013 | Y76: Renewal retention risk | Z76: Pricing Analyst | AA76: 95492.103 | AB76: =DealsRawTable[[#This Row],[Final_Price_ACV]]*DealsRawTable[[#This Row],[Contract_Years]] -> 95492.103 | AC76: 40198.454 | AD76: 55293.649 | AE76: 0.57903897 | AF76: Won | AG76: Yes | AI76: No | AJ76: 95492.103 | AK76: 55293.649 | AL76: Renewal of existing active contract | AM76: =ROUND(T76*(1-W76),2) -> 95512.59 | AN76: =DealsRawTable[[#This Row],[Validated_Annual_Final_Price]]*DealsRawTable[[#This Row],[Contract_Years]] -> 95512.59 | AO76: =DealsRawTable[[#This Row],[Validated_Annual_Final_Price]]-DealsRawTable[[#This Row],[Cost_to_Serve]] -> 55314.136 | AP76: =DealsRawTable[[#This Row],[Validated_Grossprofit]]/DealsRawTable[[#This Row],[Validated_Annual_Final_Price]] -> 0.57912927 | AQ76: 95512.59 | AR76: 95512.59 | AS76: 55314.136 | AT76: 0.57912927 | AU76: =IF(W76<=0.05,"0–5%", IF(W76<=0.1,"5–10%", IF(W76<=0.15,"10–15%", IF(W76<=0.2,"15–20%", IF(W76<=0.25,"20–25%", IF(W76<=0.3,"25–30%","Above 30%")))))) -> 15–20% | AV76: 108
A77: D00085 | B77: 45836 | C77: C0022 | D77: PUB-0022 | E77: CT00051 | F77: Operations | G77: Public Sector | H77: Northeast | I77: Northeast Commercial | J77: Mid-Market | K77: No | L77: 43952 | M77: 53 | N77: Nexus Compliance | O77: Expansion | P77: AI Add-on | Q77: 1 | R77: 384 | S77: S. Rivera | T77: 141738.33 | U77: =T77*DealsRawTable[[#This Row],[Contract_Years]] -> 141738.33 | V77: 0.079 | W77: 0.069 | X77: -0.048 | Y77: Expansion opportunity | Z77: Sales Manager | AA77: 131923.92 | AB77: =DealsRawTable[[#This Row],[Final_Price_ACV]]*DealsRawTable[[#This Row],[Contract_Years]] -> 131923.92 | AC77: 47995.305 | AD77: 83928.619 | AE77: 0.63618953 | AF77: Lost | AH77: No | AI77: No | AJ77: 0 | AK77: 0 | AL77: Expansion allowed because contract was active | AM77: =ROUND(T77*(1-W77),2) -> 131958.38 | AN77: =DealsRawTable[[#This Row],[Validated_Annual_Final_Price]]*DealsRawTable[[#This Row],[Contract_Years]] -> 131958.38 | AO77: =DealsRawTable[[#This Row],[Validated_Annual_Final_Price]]-DealsRawTable[[#This Row],[Cost_to_Serve]] -> 83963.075 | AP77: =DealsRawTable[[#This Row],[Validated_Grossprofit]]/DealsRawTable[[#This Row],[Validated_Annual_Final_Price]] -> 0.63628452 | AQ77: 0 | AR77: 0 | AS77: 0 | AT77: 0 | AU77: =IF(W77<=0.05,"0–5%", IF(W77<=0.1,"5–10%", IF(W77<=0.15,"10–15%", IF(W77<=0.2,"15–20%", IF(W77<=0.25,"20–25%", IF(W77<=0.3,"25–30%","Above 30%")))))) -> 5–10% | AV77: 116
A78: D00086 | B78: 46013 | C78: C0022 | D78: PUB-0022 | E78: CT00051 | F78: Operations | G78: Public Sector | H78: Northeast | I78: Northeast Commercial | J78: Mid-Market | K78: No | L78: 43952 | M78: 53 | N78: Nexus Compliance | O78: Renewal | Q78: 1 | R78: 331 | S78: T. Brooks | T78: 122863.91 | U78: =T78*DealsRawTable[[#This Row],[Contract_Years]] -> 122863.91 | V78: 0.113 | W78: 0.1 | X78: 0.063 | Y78: Renewal retention risk | Z78: Pricing Analyst | AA78: 110572.03 | AB78: =DealsRawTable[[#This Row],[Final_Price_ACV]]*DealsRawTable[[#This Row],[Contract_Years]] -> 110572.03 | AC78: 38760.308 | AD78: 71811.724 | AE78: 0.64945649 | AF78: Lost | AG78: No | AI78: No | AJ78: 0 | AK78: 0 | AL78: Renewal of existing active contract | AM78: =ROUND(T78*(1-W78),2) -> 110577.52 | AN78: =DealsRawTable[[#This Row],[Validated_Annual_Final_Price]]*DealsRawTable[[#This Row],[Contract_Years]] -> 110577.52 | AO78: =DealsRawTable[[#This Row],[Validated_Annual_Final_Price]]-DealsRawTable[[#This Row],[Cost_to_Serve]] -> 71817.212 | AP78: =DealsRawTable[[#This Row],[Validated_Grossprofit]]/DealsRawTable[[#This Row],[Validated_Annual_Final_Price]] -> 0.64947389 | AQ78: 0 | AR78: 0 | AS78: 0 | AT78: 0 | AU78: =IF(W78<=0.05,"0–5%", IF(W78<=0.1,"5–10%", IF(W78<=0.15,"10–15%", IF(W78<=0.2,"15–20%", IF(W78<=0.25,"20–25%", IF(W78<=0.3,"25–30%","Above 30%")))))) -> 5–10% | AV78: 116
A79: D00087 | B79: 45590 | C79: C0023 | D79: FIN-0023 | E79: CT00052 | F79: Legal | G79: Financial Services | H79: Northeast | I79: Northeast Commercial | J79: Mid-Market | K79: No | L79: 45627 | M79: 64 | N79: Nexus AI Assistant | O79: New Business | Q79: 1 | R79: 285 | S79: R. Singh | T79: 78320.351 | U79: =T79*DealsRawTable[[#This Row],[Contract_Years]] -> 78320.351 | V79: 0.064 | W79: 0.044 | X79: -0.029 | Y79: Budget constraint | Z79: Sales Manager | AA79: 74835.986 | AB79: =DealsRawTable[[#This Row],[Final_Price_ACV]]*DealsRawTable[[#This Row],[Contract_Years]] -> 74835.986 | AC79: 33155.446 | AD79: 41680.54 | AE79: 0.55695852 | AF79: Won | AI79: No | AJ79: 74835.986 | AK79: 41680.54 | AL79: First purchase under this contract | AM79: =ROUND(T79*(1-W79),2) -> 74874.26 | AN79: =DealsRawTable[[#This Row],[Validated_Annual_Final_Price]]*DealsRawTable[[#This Row],[Contract_Years]] -> 74874.26 | AO79: =DealsRawTable[[#This Row],[Validated_Annual_Final_Price]]-DealsRawTable[[#This Row],[Cost_to_Serve]] -> 41718.814 | AP79: =DealsRawTable[[#This Row],[Validated_Grossprofit]]/DealsRawTable[[#This Row],[Validated_Annual_Final_Price]] -> 0.55718499 | AQ79: 74874.26 | AR79: 74874.26 | AS79: 41718.814 | AT79: 0.55718499 | AU79: =IF(W79<=0.05,"0–5%", IF(W79<=0.1,"5–10%", IF(W79<=0.15,"10–15%", IF(W79<=0.2,"15–20%", IF(W79<=0.25,"20–25%", IF(W79<=0.3,"25–30%","Above 30%")))))) -> 0–5% | AV79: 55
A80: D00088 | B80: 45755 | C80: C0023 | D80: FIN-0023 | E80: CT00052 | F80: Legal | G80: Financial Services | H80: Northeast | I80: Northeast Commercial | J80: Mid-Market | K80: No | L80: 45627 | M80: 64 | N80: Nexus AI Assistant | O80: Expansion | P80: Seat Expansion | Q80: 1 | R80: 352 | S80: D. Chen | T80: 93593.32 | U80: =T80*DealsRawTable[[#This Row],[Contract_Years]] -> 93593.32 | V80: 0.096 | W80: 0.082 | X80: 0.063 | Y80: Expansion opportunity | Z80: Sales Manager | AA80: 85891.795 | AB80: =DealsRawTable[[#This Row],[Final_Price_ACV]]*DealsRawTable[[#This Row],[Contract_Years]] -> 85891.795 | AC80: 36649.418 | AD80: 49242.377 | AE80: 0.57330711 | AF80: Won | AH80: Yes | AI80: No | AJ80: 85891.795 | AK80: 49242.377 | AL80: Expansion allowed because contract was active | AM80: =ROUND(T80*(1-W80),2) -> 85918.67 | AN80: =DealsRawTable[[#This Row],[Validated_Annual_Final_Price]]*DealsRawTable[[#This Row],[Contract_Years]] -> 85918.67 | AO80: =DealsRawTable[[#This Row],[Validated_Annual_Final_Price]]-DealsRawTable[[#This Row],[Cost_to_Serve]] -> 49269.252 | AP80: =DealsRawTable[[#This Row],[Validated_Grossprofit]]/DealsRawTable[[#This Row],[Validated_Annual_Final_Price]] -> 0.57344058 | AQ80: 85918.67 | AR80: 85918.67 | AS80: 49269.252 | AT80: 0.57344058 | AU80: =IF(W80<=0.05,"0–5%", IF(W80<=0.1,"5–10%", IF(W80<=0.15,"10–15%", IF(W80<=0.2,"15–20%", IF(W80<=0.25,"20–25%", IF(W80<=0.3,"25–30%","Above 30%")))))) -> 5–10% | AV80: 116
A81: D00089 | B81: 45955 | C81: C0023 | D81: FIN-0023 | E81: CT00052 | F81: Legal | G81: Financial Services | H81: Northeast | I81: Northeast Commercial | J81: Mid-Market | K81: No | L81: 45627 | M81: 64 | N81: Nexus AI Assistant | O81: Renewal | Q81: 1 | R81: 352 | S81: D. Chen | T81: 96598.603 | U81: =T81*DealsRawTable[[#This Row],[Contract_Years]] -> 96598.603 | V81: 0.138 | W81: 0.108 | X81: -0.001 | Y81: Renewal retention risk | Z81: Pricing Analyst | AA81: 86190.674 | AB81: =DealsRawTable[[#This Row],[Final_Price_ACV]]*DealsRawTable[[#This Row],[Contract_Years]] -> 86190.674 | AC81: 35774.137 | AD81: 50416.537 | AE81: 0.5849419 | AF81: Lost | AG81: No | AI81: No | AJ81: 0 | AK81: 0 | AL81: Renewal of existing active contract | AM81: =ROUND(T81*(1-W81),2) -> 86165.95 | AN81: =DealsRawTable[[#This Row],[Validated_Annual_Final_Price]]*DealsRawTable[[#This Row],[Contract_Years]] -> 86165.95 | AO81: =DealsRawTable[[#This Row],[Validated_Annual_Final_Price]]-DealsRawTable[[#This Row],[Cost_to_Serve]] -> 50391.813 | AP81: =DealsRawTable[[#This Row],[Validated_Grossprofit]]/DealsRawTable[[#This Row],[Validated_Annual_Final_Price]] -> 0.58482281 | AQ81: 0 | AR81: 0 | AS81: 0 | AT81: 0 | AU81: =IF(W81<=0.05,"0–5%", IF(W81<=0.1,"5–10%", IF(W81<=0.15,"10–15%", IF(W81<=0.2,"15–20%", IF(W81<=0.25,"20–25%", IF(W81<=0.3,"25–30%","Above 30%")))))) -> 10–15% | AV81: 113
A82: D00090 | B82: 45497 | C82: C0023 | D82: FIN-0023 | E82: CT00053 | F82: Technology | G82: Financial Services | H82: Northeast | I82: Northeast Commercial | J82: Mid-Market | K82: No | L82: 45627 | M82: 64 | N82: Nexus Insights | O82: New Business | Q82: 3 | R82: 168 | S82: L. Williams | T82: 51328.856 | U82: =T82*DealsRawTable[[#This Row],[Contract_Years]] -> 153986.57 | V82: 0.11 | W82: 0.104 | X82: 0.05 | Y82: Renewal retention risk | Z82: Pricing Analyst | AA82: 45992.19 | AB82: =DealsRawTable[[#This Row],[Final_Price_ACV]]*DealsRawTable[[#This Row],[Contract_Years]] -> 137976.57 | AC82: 16406.888 | AD82: 29585.302 | AE82: 0.64326796 | AF82: Lost | AI82: No | AJ82: 0 | AK82: 0 | AL82: First purchase under this contract | AM82: =ROUND(T82*(1-W82),2) -> 45990.65 | AN82: =DealsRawTable[[#This Row],[Validated_Annual_Final_Price]]*DealsRawTable[[#This Row],[Contract_Years]] -> 137971.95 | AO82: =DealsRawTable[[#This Row],[Validated_Annual_Final_Price]]-DealsRawTable[[#This Row],[Cost_to_Serve]] -> 29583.762 | AP82: =DealsRawTable[[#This Row],[Validated_Grossprofit]]/DealsRawTable[[#This Row],[Validated_Annual_Final_Price]] -> 0.64325601 | AQ82: 0 | AR82: 0 | AS82: 0 | AT82: 0 | AU82: =IF(W82<=0.05,"0–5%", IF(W82<=0.1,"5–10%", IF(W82<=0.15,"10–15%", IF(W82<=0.2,"15–20%", IF(W82<=0.25,"20–25%", IF(W82<=0.3,"25–30%","Above 30%")))))) -> 10–15% | AV82: 113
A83: D00091 | B83: 45872 | C83: C0023 | D83: FIN-0023 | E83: CT00053 | F83: Technology | G83: Financial Services | H83: Northeast | I83: Northeast Commercial | J83: Mid-Market | K83: No | L83: 45627 | M83: 64 | N83: Nexus Insights | O83: Win-back | Q83: 3 | R83: 168 | S83: M. Johnson | T83: 51328.856 | U83: =T83*DealsRawTable[[#This Row],[Contract_Years]] -> 153986.57 | V83: 0.183 | W83: 0.136 | X83: -0.01 | Y83: Renewal retention risk | Z83: Pricing Analyst | AA83: 44343.911 | AB83: =DealsRawTable[[#This Row],[Final_Price_ACV]]*DealsRawTable[[#This Row],[Contract_Years]] -> 133031.73 | AC83: 16111.382 | AD83: 28232.529 | AE83: 0.63667206 | AF83: Lost | AI83: Yes | AJ83: 0 | AK83: 0 | AL83: Customer returned after prior lost initial opportunity | AM83: =ROUND(T83*(1-W83),2) -> 44348.13 | AN83: =DealsRawTable[[#This Row],[Validated_Annual_Final_Price]]*DealsRawTable[[#This Row],[Contract_Years]] -> 133044.39 | AO83: =DealsRawTable[[#This Row],[Validated_Annual_Final_Price]]-DealsRawTable[[#This Row],[Cost_to_Serve]] -> 28236.748 | AP83: =DealsRawTable[[#This Row],[Validated_Grossprofit]]/DealsRawTable[[#This Row],[Validated_Annual_Final_Price]] -> 0.63670662 | AQ83: 0 | AR83: 0 | AS83: 0 | AT83: 0 | AU83: =IF(W83<=0.05,"0–5%", IF(W83<=0.1,"5–10%", IF(W83<=0.15,"10–15%", IF(W83<=0.2,"15–20%", IF(W83<=0.25,"20–25%", IF(W83<=0.3,"25–30%","Above 30%")))))) -> 10–15% | AV83: 113
A84: D00092 | B84: 45583 | C84: C0024 | D84: LEG-0024 | E84: CT00054 | F84: Corporate | G84: Legal | H84: Midwest | I84: Midwest Enterprise | J84: Enterprise | K84: Yes | L84: 44531 | M84: 62 | N84: Nexus Insights | O84: Renewal | Q84: 1 | R84: 764 | S84: T. Brooks | T84: 77819.406 | U84: =T84*DealsRawTable[[#This Row],[Contract_Years]] -> 77819.406 | V84: 0.157 | W84: 0.141 | X84: 0.032 | Y84: Renewal retention risk | Z84: Pricing Analyst | AA84: 66846.671 | AB84: =DealsRawTable[[#This Row],[Final_Price_ACV]]*DealsRawTable[[#This Row],[Contract_Years]] -> 66846.671 | AC84: 19990.464 | AD84: 46856.207 | AE84: 0.70095049 | AF84: Won | AG84: Yes | AI84: No | AJ84: 66846.671 | AK84: 46856.207 | AL84: Renewal of existing active contract | AM84: =ROUND(T84*(1-W84),2) -> 66846.87 | AN84: =DealsRawTable[[#This Row],[Validated_Annual_Final_Price]]*DealsRawTable[[#This Row],[Contract_Years]] -> 66846.87 | AO84: =DealsRawTable[[#This Row],[Validated_Annual_Final_Price]]-DealsRawTable[[#This Row],[Cost_to_Serve]] -> 46856.406 | AP84: =DealsRawTable[[#This Row],[Validated_Grossprofit]]/DealsRawTable[[#This Row],[Validated_Annual_Final_Price]] -> 0.70095138 | AQ84: 66846.87 | AR84: 66846.87 | AS84: 46856.406 | AT84: 0.70095138 | AU84: =IF(W84<=0.05,"0–5%", IF(W84<=0.1,"5–10%", IF(W84<=0.15,"10–15%", IF(W84<=0.2,"15–20%", IF(W84<=0.25,"20–25%", IF(W84<=0.3,"25–30%","Above 30%")))))) -> 10–15% | AV84: 113
A85: D00093 | B85: 45948 | C85: C0024 | D85: LEG-0024 | E85: CT00054 | F85: Corporate | G85: Legal | H85: Midwest | I85: Midwest Enterprise | J85: Enterprise | K85: Yes | L85: 44531 | M85: 62 | N85: Nexus Insights | O85: Renewal | Q85: 1 | R85: 764 | S85: K. Nguyen | T85: 82762.158 | U85: =T85*DealsRawTable[[#This Row],[Contract_Years]] -> 82762.158 | V85: 0.176 | W85: 0.173 | X85: 0.067 | Y85: Renewal retention risk | Z85: Pricing Analyst | AA85: 68455.709 | AB85: =DealsRawTable[[#This Row],[Final_Price_ACV]]*DealsRawTable[[#This Row],[Contract_Years]] -> 68455.709 | AC85: 21981.706 | AD85: 46474.003 | AE85: 0.67889156 | AF85: Won | AG85: Yes | AI85: No | AJ85: 68455.709 | AK85: 46474.003 | AL85: Renewal of existing active contract | AM85: =ROUND(T85*(1-W85),2) -> 68444.3 | AN85: =DealsRawTable[[#This Row],[Validated_Annual_Final_Price]]*DealsRawTable[[#This Row],[Contract_Years]] -> 68444.3 | AO85: =DealsRawTable[[#This Row],[Validated_Annual_Final_Price]]-DealsRawTable[[#This Row],[Cost_to_Serve]] -> 46462.594 | AP85: =DealsRawTable[[#This Row],[Validated_Grossprofit]]/DealsRawTable[[#This Row],[Validated_Annual_Final_Price]] -> 0.67883804 | AQ85: 68444.3 | AR85: 68444.3 | AS85: 46462.594 | AT85: 0.67883804 | AU85: =IF(W85<=0.05,"0–5%", IF(W85<=0.1,"5–10%", IF(W85<=0.15,"10–15%", IF(W85<=0.2,"15–20%", IF(W85<=0.25,"20–25%", IF(W85<=0.3,"25–30%","Above 30%")))))) -> 15–20% | AV85: 108
A86: D00094 | B86: 45522 | C86: C0024 | D86: LEG-0024 | E86: CT00055 | F86: Legal | G86: Legal | H86: Midwest | I86: Midwest Enterprise | J86: Enterprise | K86: Yes | L86: 44531 | M86: 62 | N86: Nexus Analytics | O86: New Business | Q86: 1 | R86: 1409 | S86: S. Rivera | T86: 329442.78 | U86: =T86*DealsRawTable[[#This Row],[Contract_Years]] -> 329442.78 | V86: 0.19 | W86: 0.162 | X86: -0.124 | Y86: Multi-year commitment | Z86: Pricing Analyst | AA86: 276207.03 | AB86: =DealsRawTable[[#This Row],[Final_Price_ACV]]*DealsRawTable[[#This Row],[Contract_Years]] -> 276207.03 | AC86: 118383.42 | AD86: 157823.61 | AE86: 0.57139608 | AF86: Won | AI86: No | AJ86: 276207.03 | AK86: 157823.61 | AL86: First purchase under this contract | AM86: =ROUND(T86*(1-W86),2) -> 276073.05 | AN86: =DealsRawTable[[#This Row],[Validated_Annual_Final_Price]]*DealsRawTable[[#This Row],[Contract_Years]] -> 276073.05 | AO86: =DealsRawTable[[#This Row],[Validated_Annual_Final_Price]]-DealsRawTable[[#This Row],[Cost_to_Serve]] -> 157689.63 | AP86: =DealsRawTable[[#This Row],[Validated_Grossprofit]]/DealsRawTable[[#This Row],[Validated_Annual_Final_Price]] -> 0.57118808 | AQ86: 276073.05 | AR86: 276073.05 | AS86: 157689.63 | AT86: 0.57118808 | AU86: =IF(W86<=0.05,"0–5%", IF(W86<=0.1,"5–10%", IF(W86<=0.15,"10–15%", IF(W86<=0.2,"15–20%", IF(W86<=0.25,"20–25%", IF(W86<=0.3,"25–30%","Above 30%")))))) -> 15–20% | AV86: 108
A87: D00095 | B87: 45887 | C87: C0024 | D87: LEG-0024 | E87: CT00055 | F87: Legal | G87: Legal | H87: Midwest | I87: Midwest Enterprise | J87: Enterprise | K87: Yes | L87: 44531 | M87: 62 | N87: Nexus Analytics | O87: Renewal | Q87: 1 | R87: 1409 | S87: T. Brooks | T87: 347991.84 | U87: =T87*DealsRawTable[[#This Row],[Contract_Years]] -> 347991.84 | V87: 0.188 | W87: 0.177 | X87: -0.069 | Y87: Renewal retention risk | Z87: Pricing Analyst | AA87: 286525.35 | AB87: =DealsRawTable[[#This Row],[Final_Price_ACV]]*DealsRawTable[[#This Row],[Contract_Years]] -> 286525.35 | AC87: 109065.75 | AD87: 177459.61 | AE87: 0.61935045 | AF87: Won | AG87: Yes | AI87: No | AJ87: 286525.35 | AK87: 177459.61 | AL87: Renewal of existing active contract | AM87: =ROUND(T87*(1-W87),2) -> 286397.28 | AN87: =DealsRawTable[[#This Row],[Validated_Annual_Final_Price]]*DealsRawTable[[#This Row],[Contract_Years]] -> 286397.28 | AO87: =DealsRawTable[[#This Row],[Validated_Annual_Final_Price]]-DealsRawTable[[#This Row],[Cost_to_Serve]] -> 177331.53 | AP87: =DealsRawTable[[#This Row],[Validated_Grossprofit]]/DealsRawTable[[#This Row],[Validated_Annual_Final_Price]] -> 0.61918023 | AQ87: 286397.28 | AR87: 286397.28 | AS87: 177331.53 | AT87: 0.61918023 | AU87: =IF(W87<=0.05,"0–5%", IF(W87<=0.1,"5–10%", IF(W87<=0.15,"10–15%", IF(W87<=0.2,"15–20%", IF(W87<=0.25,"20–25%", IF(W87<=0.3,"25–30%","Above 30%")))))) -> 15–20% | AV87: 108
A88: D00096 | B88: 45624 | C88: C0025 | D88: TEC-0025 | E88: CT00056 | F88: Sales | G88: Technology | H88: Northeast | I88: Northeast Commercial | J88: SMB | K88: No | L88: 43132 | M88: 75 | N88: Nexus Analytics | O88: New Business | Q88: 1 | R88: 66 | S88: S. Rivera | T88: 47271.301 | U88: =T88*DealsRawTable[[#This Row],[Contract_Years]] -> 47271.301 | V88: 0.105 | W88: 0.094 | X88: -0.134 | Y88: Renewal retention risk | Z88: Sales Manager | AA88: 42825.234 | AB88: =DealsRawTable[[#This Row],[Final_Price_ACV]]*DealsRawTable[[#This Row],[Contract_Years]] -> 42825.234 | AC88: 16223.059 | AD88: 26602.175 | AE88: 0.62117991 | AF88: Lost | AI88: No | AJ88: 0 | AK88: 0 | AL88: First purchase under this contract | AM88: =ROUND(T88*(1-W88),2) -> 42827.8 | AN88: =DealsRawTable[[#This Row],[Validated_Annual_Final_Price]]*DealsRawTable[[#This Row],[Contract_Years]] -> 42827.8 | AO88: =DealsRawTable[[#This Row],[Validated_Annual_Final_Price]]-DealsRawTable[[#This Row],[Cost_to_Serve]] -> 26604.741 | AP88: =DealsRawTable[[#This Row],[Validated_Grossprofit]]/DealsRawTable[[#This Row],[Validated_Annual_Final_Price]] -> 0.62120261 | AQ88: 0 | AR88: 0 | AS88: 0 | AT88: 0 | AU88: =IF(W88<=0.05,"0–5%", IF(W88<=0.1,"5–10%", IF(W88<=0.15,"10–15%", IF(W88<=0.2,"15–20%", IF(W88<=0.25,"20–25%", IF(W88<=0.3,"25–30%","Above 30%")))))) -> 5–10% | AV88: 116
A89: D00097 | B89: 45774 | C89: C0025 | D89: TEC-0025 | E89: CT00057 | F89: Sales | G89: Technology | H89: Northeast | I89: Northeast Commercial | J89: SMB | K89: No | L89: 43132 | M89: 75 | N89: Nexus Compliance | O89: New Business | Q89: 1 | R89: 50 | S89: A. Patel | T89: 57208.563 | U89: =T89*DealsRawTable[[#This Row],[Contract_Years]] -> 57208.563 | V89: 0.075 | W89: 0.059 | X89: -0.096 | Y89: Budget constraint | Z89: Sales Manager | AA89: 53823.129 | AB89: =DealsRawTable[[#This Row],[Final_Price_ACV]]*DealsRawTable[[#This Row],[Contract_Years]] -> 53823.129 | AC89: 20791.988 | AD89: 33031.141 | AE89: 0.61369789 | AF89: Lost | AI89: No | AJ89: 0 | AK89: 0 | AL89: First purchase under this contract | AM89: =ROUND(T89*(1-W89),2) -> 53833.26 | AN89: =DealsRawTable[[#This Row],[Validated_Annual_Final_Price]]*DealsRawTable[[#This Row],[Contract_Years]] -> 53833.26 | AO89: =DealsRawTable[[#This Row],[Validated_Annual_Final_Price]]-DealsRawTable[[#This Row],[Cost_to_Serve]] -> 33041.272 | AP89: =DealsRawTable[[#This Row],[Validated_Grossprofit]]/DealsRawTable[[#This Row],[Validated_Annual_Final_Price]] -> 0.61377059 | AQ89: 0 | AR89: 0 | AS89: 0 | AT89: 0 | AU89: =IF(W89<=0.05,"0–5%", IF(W89<=0.1,"5–10%", IF(W89<=0.15,"10–15%", IF(W89<=0.2,"15–20%", IF(W89<=0.25,"20–25%", IF(W89<=0.3,"25–30%","Above 30%")))))) -> 5–10% | AV89: 116
A90: D00098 | B90: 45320 | C90: C0026 | D90: FIN-0026 | E90: CT00058 | F90: Technology | G90: Financial Services | H90: West | I90: West Commercial | J90: Mid-Market | K90: No | L90: 45108 | M90: 40 | N90: Nexus Analytics | O90: New Business | Q90: 1 | R90: 255 | S90: K. Nguyen | T90: 128064.61 | U90: =T90*DealsRawTable[[#This Row],[Contract_Years]] -> 128064.61 | V90: 0.129 | W90: 0.091 | X90: 0.009 | Y90: Strategic logo opportunity | Z90: Sales Manager | AA90: 116407.16 | AB90: =DealsRawTable[[#This Row],[Final_Price_ACV]]*DealsRawTable[[#This Row],[Contract_Years]] -> 116407.16 | AC90: 46750.646 | AD90: 69656.51 | AE90: 0.59838684 | AF90: Lost | AI90: No | AJ90: 0 | AK90: 0 | AL90: First purchase under this contract | AM90: =ROUND(T90*(1-W90),2) -> 116410.73 | AN90: =DealsRawTable[[#This Row],[Validated_Annual_Final_Price]]*DealsRawTable[[#This Row],[Contract_Years]] -> 116410.73 | AO90: =DealsRawTable[[#This Row],[Validated_Annual_Final_Price]]-DealsRawTable[[#This Row],[Cost_to_Serve]] -> 69660.084 | AP90: =DealsRawTable[[#This Row],[Validated_Grossprofit]]/DealsRawTable[[#This Row],[Validated_Annual_Final_Price]] -> 0.59839916 | AQ90: 0 | AR90: 0 | AS90: 0 | AT90: 0 | AU90: =IF(W90<=0.05,"0–5%", IF(W90<=0.1,"5–10%", IF(W90<=0.15,"10–15%", IF(W90<=0.2,"15–20%", IF(W90<=0.25,"20–25%", IF(W90<=0.3,"25–30%","Above 30%")))))) -> 5–10% | AV90: 116
A91: D00099 | B91: 45556 | C91: C0026 | D91: FIN-0026 | E91: CT00058 | F91: Technology | G91: Financial Services | H91: West | I91: West Commercial | J91: Mid-Market | K91: No | L91: 45108 | M91: 40 | N91: Nexus Analytics | O91: Win-back | Q91: 1 | R91: 255 | S91: K. Nguyen | T91: 128064.61 | U91: =T91*DealsRawTable[[#This Row],[Contract_Years]] -> 128064.61 | V91: 0.137 | W91: 0.132 | X91: -0.065 | Y91: Renewal retention risk | Z91: Pricing Analyst | AA91: 111213.8 | AB91: =DealsRawTable[[#This Row],[Final_Price_ACV]]*DealsRawTable[[#This Row],[Contract_Years]] -> 111213.8 | AC91: 46962.879 | AD91: 64250.925 | AE91: 0.57772437 | AF91: Lost | AI91: Yes | AJ91: 0 | AK91: 0 | AL91: Customer returned after prior lost initial opportunity | AM91: =ROUND(T91*(1-W91),2) -> 111160.08 | AN91: =DealsRawTable[[#This Row],[Validated_Annual_Final_Price]]*DealsRawTable[[#This Row],[Contract_Years]] -> 111160.08 | AO91: =DealsRawTable[[#This Row],[Validated_Annual_Final_Price]]-DealsRawTable[[#This Row],[Cost_to_Serve]] -> 64197.201 | AP91: =DealsRawTable[[#This Row],[Validated_Grossprofit]]/DealsRawTable[[#This Row],[Validated_Annual_Final_Price]] -> 0.57752029 | AQ91: 0 | AR91: 0 | AS91: 0 | AT91: 0 | AU91: =IF(W91<=0.05,"0–5%", IF(W91<=0.1,"5–10%", IF(W91<=0.15,"10–15%", IF(W91<=0.2,"15–20%", IF(W91<=0.25,"20–25%", IF(W91<=0.3,"25–30%","Above 30%")))))) -> 10–15% | AV91: 113
A92: D00101 | B92: 45402 | C92: C0027 | D92: LEG-0027 | E92: CT00060 | F92: Sales | G92: Legal | H92: Northeast | I92: Northeast Commercial | J92: SMB | K92: No | L92: 44287 | M92: 72 | N92: Nexus Compliance | O92: Renewal | Q92: 1 | R92: 55 | S92: K. Nguyen | T92: 74635.04 | U92: =T92*DealsRawTable[[#This Row],[Contract_Years]] -> 74635.04 | V92: 0.142 | W92: 0.141 | X92: -0.11 | Y92: Procurement requirement | Z92: Pricing Analyst | AA92: 64107.953 | AB92: =DealsRawTable[[#This Row],[Final_Price_ACV]]*DealsRawTable[[#This Row],[Contract_Years]] -> 64107.953 | AC92: 24002.114 | AD92: 40105.839 | AE92: 0.62559849 | AF92: Won | AG92: Yes | AI92: No | AJ92: 64107.953 | AK92: 40105.839 | AL92: Renewal of existing active contract | AM92: =ROUND(T92*(1-W92),2) -> 64111.5 | AN92: =DealsRawTable[[#This Row],[Validated_Annual_Final_Price]]*DealsRawTable[[#This Row],[Contract_Years]] -> 64111.5 | AO92: =DealsRawTable[[#This Row],[Validated_Annual_Final_Price]]-DealsRawTable[[#This Row],[Cost_to_Serve]] -> 40109.386 | AP92: =DealsRawTable[[#This Row],[Validated_Grossprofit]]/DealsRawTable[[#This Row],[Validated_Annual_Final_Price]] -> 0.62561921 | AQ92: 64111.5 | AR92: 64111.5 | AS92: 40109.386 | AT92: 0.62561921 | AU92: =IF(W92<=0.05,"0–5%", IF(W92<=0.1,"5–10%", IF(W92<=0.15,"10–15%", IF(W92<=0.2,"15–20%", IF(W92<=0.25,"20–25%", IF(W92<=0.3,"25–30%","Above 30%")))))) -> 10–15% | AV92: 113
A93: D00102 | B93: 45767 | C93: C0027 | D93: LEG-0027 | E93: CT00060 | F93: Sales | G93: Legal | H93: Northeast | I93: Northeast Commercial | J93: SMB | K93: No | L93: 44287 | M93: 72 | N93: Nexus Compliance | O93: Renewal | Q93: 1 | R93: 55 | S93: K. Nguyen | T93: 77849.189 | U93: =T93*DealsRawTable[[#This Row],[Contract_Years]] -> 77849.189 | V93: 0.103 | W93: 0.071 | X93: -0.009 | Y93: Verified competitor pressure | Z93: Sales Manager | AA93: 72314.757 | AB93: =DealsRawTable[[#This Row],[Final_Price_ACV]]*DealsRawTable[[#This Row],[Contract_Years]] -> 72314.757 | AC93: 26187.224 | AD93: 46127.533 | AE93: 0.63787164 | AF93: Lost | AG93: No | AI93: No | AJ93: 0 | AK93: 0 | AL93: Renewal of existing active contract | AM93: =ROUND(T93*(1-W93),2) -> 72321.9 | AN93: =DealsRawTable[[#This Row],[Validated_Annual_Final_Price]]*DealsRawTable[[#This Row],[Contract_Years]] -> 72321.9 | AO93: =DealsRawTable[[#This Row],[Validated_Annual_Final_Price]]-DealsRawTable[[#This Row],[Cost_to_Serve]] -> 46134.676 | AP93: =DealsRawTable[[#This Row],[Validated_Grossprofit]]/DealsRawTable[[#This Row],[Validated_Annual_Final_Price]] -> 0.63790741 | AQ93: 0 | AR93: 0 | AS93: 0 | AT93: 0 | AU93: =IF(W93<=0.05,"0–5%", IF(W93<=0.1,"5–10%", IF(W93<=0.15,"10–15%", IF(W93<=0.2,"15–20%", IF(W93<=0.25,"20–25%", IF(W93<=0.3,"25–30%","Above 30%")))))) -> 5–10% | AV93: 116
A94: D00103 | B94: 45892 | C94: C0027 | D94: LEG-0027 | E94: CT00060 | F94: Sales | G94: Legal | H94: Northeast | I94: Northeast Commercial | J94: SMB | K94: No | L94: 44287 | M94: 72 | N94: Nexus Compliance | O94: Win-back | Q94: 1 | R94: 55 | S94: K. Nguyen | T94: 77849.189 | U94: =T94*DealsRawTable[[#This Row],[Contract_Years]] -> 77849.189 | V94: 0.217 | W94: 0.199 | X94: -0.093 | Y94: Renewal retention risk | Z94: Pricing Analyst | AA94: 62385.968 | AB94: =DealsRawTable[[#This Row],[Final_Price_ACV]]*DealsRawTable[[#This Row],[Contract_Years]] -> 62385.968 | AC94: 24114.843 | AD94: 38271.124 | AE94: 0.61345725 | AF94: Won | AI94: Yes | AJ94: 62385.968 | AK94: 38271.124 | AL94: Customer returned after lost renewal | AM94: =ROUND(T94*(1-W94),2) -> 62357.2 | AN94: =DealsRawTable[[#This Row],[Validated_Annual_Final_Price]]*DealsRawTable[[#This Row],[Contract_Years]] -> 62357.2 | AO94: =DealsRawTable[[#This Row],[Validated_Annual_Final_Price]]-DealsRawTable[[#This Row],[Cost_to_Serve]] -> 38242.357 | AP94: =DealsRawTable[[#This Row],[Validated_Grossprofit]]/DealsRawTable[[#This Row],[Validated_Annual_Final_Price]] -> 0.61327892 | AQ94: 62357.2 | AR94: 62357.2 | AS94: 38242.357 | AT94: 0.61327892 | AU94: =IF(W94<=0.05,"0–5%", IF(W94<=0.1,"5–10%", IF(W94<=0.15,"10–15%", IF(W94<=0.2,"15–20%", IF(W94<=0.25,"20–25%", IF(W94<=0.3,"25–30%","Above 30%")))))) -> 15–20% | AV94: 108
A95: D00104 | B95: 45332 | C95: C0028 | D95: HEA-0028 | E95: CT00061 | F95: Technology | G95: Healthcare | H95: West | I95: West Commercial | J95: SMB | K95: No | L95: 43344 | M95: 53 | N95: Nexus Enterprise Suite | O95: Renewal | Q95: 3 | R95: 66 | S95: M. Johnson | T95: 158972.83 | U95: =T95*DealsRawTable[[#This Row],[Contract_Years]] -> 476918.5 | V95: 0.247 | W95: 0.187 | X95: -0.044 | Y95: Renewal retention risk | Z95: Pricing Analyst | AA95: 129300.7 | AB95: =DealsRawTable[[#This Row],[Final_Price_ACV]]*DealsRawTable[[#This Row],[Contract_Years]] -> 387902.1 | AC95: 56384.814 | AD95: 72915.886 | AE95: 0.56392491 | AF95: Won | AG95: Yes | AI95: No | AJ95: 129300.7 | AK95: 72915.886 | AL95: Renewal of existing active contract | AM95: =ROUND(T95*(1-W95),2) -> 129244.91 | AN95: =DealsRawTable[[#This Row],[Validated_Annual_Final_Price]]*DealsRawTable[[#This Row],[Contract_Years]] -> 387734.73 | AO95: =DealsRawTable[[#This Row],[Validated_Annual_Final_Price]]-DealsRawTable[[#This Row],[Cost_to_Serve]] -> 72860.096 | AP95: =DealsRawTable[[#This Row],[Validated_Grossprofit]]/DealsRawTable[[#This Row],[Validated_Annual_Final_Price]] -> 0.56373668 | AQ95: 129244.91 | AR95: 387734.73 | AS95: 72860.096 | AT95: 0.56373668 | AU95: =IF(W95<=0.05,"0–5%", IF(W95<=0.1,"5–10%", IF(W95<=0.15,"10–15%", IF(W95<=0.2,"15–20%", IF(W95<=0.25,"20–25%", IF(W95<=0.3,"25–30%","Above 30%")))))) -> 15–20% | AV95: 108
A96: D00105 | B96: 45548 | C96: C0028 | D96: HEA-0028 | E96: CT00062 | F96: Finance | G96: Healthcare | H96: West | I96: West Commercial | J96: SMB | K96: No | L96: 43344 | M96: 53 | N96: Nexus Enterprise Suite | O96: New Business | Q96: 1 | R96: 50 | S96: D. Chen | T96: 128386.83 | U96: =T96*DealsRawTable[[#This Row],[Contract_Years]] -> 128386.83 | V96: 0.178 | W96: 0.149 | X96: -0.111 | Y96: Expansion opportunity | Z96: Pricing Analyst | AA96: 109234.03 | AB96: =DealsRawTable[[#This Row],[Final_Price_ACV]]*DealsRawTable[[#This Row],[Contract_Years]] -> 109234.03 | AC96: 46387.804 | AD96: 62846.223 | AE96: 0.57533559 | AF96: Lost | AI96: No | AJ96: 0 | AK96: 0 | AL96: First purchase under this contract | AM96: =ROUND(T96*(1-W96),2) -> 109257.2 | AN96: =DealsRawTable[[#This Row],[Validated_Annual_Final_Price]]*DealsRawTable[[#This Row],[Contract_Years]] -> 109257.2 | AO96: =DealsRawTable[[#This Row],[Validated_Annual_Final_Price]]-DealsRawTable[[#This Row],[Cost_to_Serve]] -> 62869.396 | AP96: =DealsRawTable[[#This Row],[Validated_Grossprofit]]/DealsRawTable[[#This Row],[Validated_Annual_Final_Price]] -> 0.57542566 | AQ96: 0 | AR96: 0 | AS96: 0 | AT96: 0 | AU96: =IF(W96<=0.05,"0–5%", IF(W96<=0.1,"5–10%", IF(W96<=0.15,"10–15%", IF(W96<=0.2,"15–20%", IF(W96<=0.25,"20–25%", IF(W96<=0.3,"25–30%","Above 30%")))))) -> 10–15% | AV96: 113
A97: D00106 | B97: 45842 | C97: C0028 | D97: HEA-0028 | E97: CT00063 | F97: Operations | G97: Healthcare | H97: West | I97: West Commercial | J97: SMB | K97: No | L97: 43344 | M97: 53 | N97: Nexus Enterprise Suite | O97: New Business | Q97: 1 | R97: 77 | S97: K. Nguyen | T97: 129088.72 | U97: =T97*DealsRawTable[[#This Row],[Contract_Years]] -> 129088.72 | V97: 0.184 | W97: 0.168 | X97: -0.101 | Y97: Multi-year commitment | Z97: Pricing Analyst | AA97: 107440.63 | AB97: =DealsRawTable[[#This Row],[Final_Price_ACV]]*DealsRawTable[[#This Row],[Contract_Years]] -> 107440.63 | AC97: 51082.765 | AD97: 56357.867 | AE97: 0.52454892 | AF97: Lost | AI97: No | AJ97: 0 | AK97: 0 | AL97: First purchase under this contract | AM97: =ROUND(T97*(1-W97),2) -> 107401.81 | AN97: =DealsRawTable[[#This Row],[Validated_Annual_Final_Price]]*DealsRawTable[[#This Row],[Contract_Years]] -> 107401.81 | AO97: =DealsRawTable[[#This Row],[Validated_Annual_Final_Price]]-DealsRawTable[[#This Row],[Cost_to_Serve]] -> 56319.045 | AP97: =DealsRawTable[[#This Row],[Validated_Grossprofit]]/DealsRawTable[[#This Row],[Validated_Annual_Final_Price]] -> 0.52437706 | AQ97: 0 | AR97: 0 | AS97: 0 | AT97: 0 | AU97: =IF(W97<=0.05,"0–5%", IF(W97<=0.1,"5–10%", IF(W97<=0.15,"10–15%", IF(W97<=0.2,"15–20%", IF(W97<=0.25,"20–25%", IF(W97<=0.3,"25–30%","Above 30%")))))) -> 15–20% | AV97: 108
A98: D00107 | B98: 45696 | C98: C0029 | D98: LEG-0029 | E98: CT00064 | F98: Corporate | G98: Legal | H98: Northeast | I98: Northeast Enterprise | J98: Enterprise | K98: No | L98: 43617 | M98: 92 | N98: Nexus Insights | O98: New Business | Q98: 1 | R98: 1345 | S98: S. Rivera | T98: 178580.66 | U98: =T98*DealsRawTable[[#This Row],[Contract_Years]] -> 178580.66 | V98: 0.132 | W98: 0.099 | X98: 0.059 | Y98: Multi-year commitment | Z98: Sales Manager | AA98: 160972.32 | AB98: =DealsRawTable[[#This Row],[Final_Price_ACV]]*DealsRawTable[[#This Row],[Contract_Years]] -> 160972.32 | AC98: 56576.113 | AD98: 104396.2 | AE98: 0.64853514 | AF98: Won | AI98: No | AJ98: 160972.32 | AK98: 104396.2 | AL98: First purchase under this contract | AM98: =ROUND(T98*(1-W98),2) -> 160901.17 | AN98: =DealsRawTable[[#This Row],[Validated_Annual_Final_Price]]*DealsRawTable[[#This Row],[Contract_Years]] -> 160901.17 | AO98: =DealsRawTable[[#This Row],[Validated_Annual_Final_Price]]-DealsRawTable[[#This Row],[Cost_to_Serve]] -> 104325.06 | AP98: =DealsRawTable[[#This Row],[Validated_Grossprofit]]/DealsRawTable[[#This Row],[Validated_Annual_Final_Price]] -> 0.64837973 | AQ98: 160901.17 | AR98: 160901.17 | AS98: 104325.06 | AT98: 0.64837973 | AU98: =IF(W98<=0.05,"0–5%", IF(W98<=0.1,"5–10%", IF(W98<=0.15,"10–15%", IF(W98<=0.2,"15–20%", IF(W98<=0.25,"20–25%", IF(W98<=0.3,"25–30%","Above 30%")))))) -> 5–10% | AV98: 116
A99: D00108 | B99: 45363 | C99: C0029 | D99: LEG-0029 | E99: CT00065 | F99: Finance | G99: Legal | H99: Northeast | I99: Northeast Enterprise | J99: Enterprise | K99: No | L99: 43617 | M99: 92 | N99: Nexus AI Assistant | O99: Renewal | Q99: 2 | R99: 1816 | S99: R. Singh | T99: 329201.78 | U99: =T99*DealsRawTable[[#This Row],[Contract_Years]] -> 658403.56 | V99: 0.164 | W99: 0.144 | X99: -0.005 | Y99: Strategic logo opportunity | Z99: Pricing Analyst | AA99: 281710.27 | AB99: =DealsRawTable[[#This Row],[Final_Price_ACV]]*DealsRawTable[[#This Row],[Contract_Years]] -> 563420.54 | AC99: 117322.31 | AD99: 164387.96 | AE99: 0.58353555 | AF99: Won | AG99: Yes | AI99: No | AJ99: 281710.27 | AK99: 164387.96 | AL99: Renewal of existing active contract | AM99: =ROUND(T99*(1-W99),2) -> 281796.72 | AN99: =DealsRawTable[[#This Row],[Validated_Annual_Final_Price]]*DealsRawTable[[#This Row],[Contract_Years]] -> 563593.44 | AO99: =DealsRawTable[[#This Row],[Validated_Annual_Final_Price]]-DealsRawTable[[#This Row],[Cost_to_Serve]] -> 164474.41 | AP99: =DealsRawTable[[#This Row],[Validated_Grossprofit]]/DealsRawTable[[#This Row],[Validated_Annual_Final_Price]] -> 0.58366332 | AQ99: 281796.72 | AR99: 563593.44 | AS99: 164474.41 | AT99: 0.58366332 | AU99: =IF(W99<=0.05,"0–5%", IF(W99<=0.1,"5–10%", IF(W99<=0.15,"10–15%", IF(W99<=0.2,"15–20%", IF(W99<=0.25,"20–25%", IF(W99<=0.3,"25–30%","Above 30%")))))) -> 10–15% | AV99: 113
A100: D00109 | B100: 45977 | C100: C0030 | D100: HEA-0030 | E100: CT00066 | F100: Operations | G100: Healthcare | H100: South | I100: South Commercial | J100: SMB | K100: No | L100: 44075 | M100: 82 | N100: Nexus Analytics | O100: Renewal | Q100: 3 | R100: 64 | S100: T. Brooks | T100: 55750.816 | U100: =T100*DealsRawTable[[#This Row],[Contract_Years]] -> 167252.45 | V100: 0.166 | W100: 0.158 | X100: -0.023 | Y100: Expansion opportunity | Z100: Pricing Analyst | AA100: 46959.859 | AB100: =DealsRawTable[[#This Row],[Final_Price_ACV]]*DealsRawTable[[#This Row],[Contract_Years]] -> 140879.58 | AC100: 17438.327 | AD100: 29521.532 | AE100: 0.62865462 | AF100: Won | AG100: Yes | AI100: No | AJ100: 46959.859 | AK100: 29521.532 | AL100: Renewal of existing active contract | AM100: =ROUND(T100*(1-W100),2) -> 46942.19 | AN100: =DealsRawTable[[#This Row],[Validated_Annual_Final_Price]]*DealsRawTable[[#This Row],[Contract_Years]] -> 140826.57 | AO100: =DealsRawTable[[#This Row],[Validated_Annual_Final_Price]]-DealsRawTable[[#This Row],[Cost_to_Serve]] -> 29503.863 | AP100: =DealsRawTable[[#This Row],[Validated_Grossprofit]]/DealsRawTable[[#This Row],[Validated_Annual_Final_Price]] -> 0.62851484 | AQ100: 46942.19 | AR100: 140826.57 | AS100: 29503.863 | AT100: 0.62851484 | AU100: =IF(W100<=0.05,"0–5%", IF(W100<=0.1,"5–10%", IF(W100<=0.15,"10–15%", IF(W100<=0.2,"15–20%", IF(W100<=0.25,"20–25%", IF(W100<=0.3,"25–30%","Above 30%")))))) -> 15–20% | AV100: 108
A101: D00112 | B101: 45591 | C101: C0031 | D101: MAN-0031 | E101: CT00067 | F101: Corporate | G101: Manufacturing | H101: West | I101: West Commercial | J101: Mid-Market | K101: No | L101: 43466 | M101: 54 | N101: Nexus Insights | O101: Renewal | Q101: 1 | R101: 206 | S101: S. Rivera | T101: 34843.352 | U101: =T101*DealsRawTable[[#This Row],[Contract_Years]] -> 34843.352 | V101: 0.219 | W101: 0.209 | X101: -0.086 | Y101: Renewal retention risk | Z101: Business Manager | AA101: 27577.373 | AB101: =DealsRawTable[[#This Row],[Final_Price_ACV]]*DealsRawTable[[#This Row],[Contract_Years]] -> 27577.373 | AC101: 9106.811 | AD101: 18470.562 | AE101: 0.66977236 | AF101: Won | AG101: Yes | AI101: No | AJ101: 27577.373 | AK101: 18470.562 | AL101: Renewal of existing active contract | AM101: =ROUND(T101*(1-W101),2) -> 27561.09 | AN101: =DealsRawTable[[#This Row],[Validated_Annual_Final_Price]]*DealsRawTable[[#This Row],[Contract_Years]] -> 27561.09 | AO101: =DealsRawTable[[#This Row],[Validated_Annual_Final_Price]]-DealsRawTable[[#This Row],[Cost_to_Serve]] -> 18454.279 | AP101: =DealsRawTable[[#This Row],[Validated_Grossprofit]]/DealsRawTable[[#This Row],[Validated_Annual_Final_Price]] -> 0.66957726 | AQ101: 27561.09 | AR101: 27561.09 | AS101: 18454.279 | AT101: 0.66957726 | AU101: =IF(W101<=0.05,"0–5%", IF(W101<=0.1,"5–10%", IF(W101<=0.15,"10–15%", IF(W101<=0.2,"15–20%", IF(W101<=0.25,"20–25%", IF(W101<=0.3,"25–30%","Above 30%")))))) -> 20–25% | AV101: 29
A102: D00113 | B102: 45956 | C102: C0031 | D102: MAN-0031 | E102: CT00067 | F102: Corporate | G102: Manufacturing | H102: West | I102: West Commercial | J102: Mid-Market | K102: No | L102: 43466 | M102: 54 | N102: Nexus Insights | O102: Renewal | Q102: 1 | R102: 206 | S102: R. Singh | T102: 37348.168 | U102: =T102*DealsRawTable[[#This Row],[Contract_Years]] -> 37348.168 | V102: 0.185 | W102: 0.176 | X102: 0.033 | Y102: Renewal retention risk | Z102: Pricing Analyst | AA102: 30768.282 | AB102: =DealsRawTable[[#This Row],[Final_Price_ACV]]*DealsRawTable[[#This Row],[Contract_Years]] -> 30768.282 | AC102: 10680.367 | AD102: 20087.915 | AE102: 0.65287737 | AF102: Won | AG102: Yes | AI102: No | AJ102: 30768.282 | AK102: 20087.915 | AL102: Renewal of existing active contract | AM102: =ROUND(T102*(1-W102),2) -> 30774.89 | AN102: =DealsRawTable[[#This Row],[Validated_Annual_Final_Price]]*DealsRawTable[[#This Row],[Contract_Years]] -> 30774.89 | AO102: =DealsRawTable[[#This Row],[Validated_Annual_Final_Price]]-DealsRawTable[[#This Row],[Cost_to_Serve]] -> 20094.523 | AP102: =DealsRawTable[[#This Row],[Validated_Grossprofit]]/DealsRawTable[[#This Row],[Validated_Annual_Final_Price]] -> 0.6529519 | AQ102: 30774.89 | AR102: 30774.89 | AS102: 20094.523 | AT102: 0.6529519 | AU102: =IF(W102<=0.05,"0–5%", IF(W102<=0.1,"5–10%", IF(W102<=0.15,"10–15%", IF(W102<=0.2,"15–20%", IF(W102<=0.25,"20–25%", IF(W102<=0.3,"25–30%","Above 30%")))))) -> 15–20% | AV102: 108
...

Sheet StraCustomer segm pricing perf 
A1: Industry | B1: Company Size | C1: Industry X Company | D1: Strategic Account | E1: industry X Company size X Strategy | F1: Total Deals | G1: Won Deals | H1: Win Rate | I1: Avg Approved Discount | J1: Avg Annual Final Price | K1: Total Revenue | L1: Avg Gross Margin | M1: Total Gross Profit | N1: Revenue Share
A2: Financial Services | B2: SMB | C2: =COUNTIFS(Deals_Raw!$G2:$G642, A2, Deals_Raw!$J2:$J642, B2) -> 14 | D2: Yes | E2: =COUNTIFS(Deals_Raw!$G2:$G642, A2, Deals_Raw!$J2:$J642, B2, Deals_Raw!$K2:K642, D2) -> 0 | F2: =COUNTIFS(Deals_Raw!$G$5:$G$643,$A2, Deals_Raw!$J$5:$J$643,$B2, Deals_Raw!$K$5:$K$643,$D2) -> 0 | G2: =COUNTIFS( Deals_Raw!$AF$5:$AF$643,"Won", Deals_Raw!$G$5:$G$643,$A2, Deals_Raw!$J$5:$J$643,$B2, Deals_Raw!$K$5:$K$643,$D2) -> 0 | H2: 0 | I2: 0 | J2: =IFERROR( AVERAGEIFS( Deals_Raw!$AQ$5:$AQ$643, Deals_Raw!$AF$5:$AF$643,"Won", Deals_Raw!$G$5:$G$643,$A2, Deals_Raw!$J$5:$J$643,$B2, Deals_Raw!$K$5:$K$643,$D2 ),0) -> 0 | K2: =SUMIFS(Deals_Raw!$AQ$5:$AQ$643, Deals_Raw!$AF$5:$AF$643,"Won", Deals_Raw!$G$5:$G$643,$A2, Deals_Raw!$J$5:$J$643,$B2, Deals_Raw!$K$5:$K$643,$D2) -> 0 | L2: 0 | M2: =SUMIFS(Deals_Raw!$AS$5:$AS$643, Deals_Raw!$AF$5:$AF$643,"Won", Deals_Raw!$G$5:$G$643,$A2, Deals_Raw!$J$5:$J$643,$B2, Deals_Raw!$K$5:$K$643,$D2) -> 0 | N2: =K2/$O$2 -> 0 | O2: 79196734
A3: Financial Services | B3: Mid-Market | C3: =COUNTIFS(Deals_Raw!$G3:$G643, A3, Deals_Raw!$J3:$J643, B3) -> 45 | D3: Yes | E3: =COUNTIFS(Deals_Raw!$G3:$G643, A3, Deals_Raw!$J3:$J643, B3, Deals_Raw!$K3:K643, D3) -> 0 | F3: =COUNTIFS( Deals_Raw!$G$5:$G$643,$A3, Deals_Raw!$J$5:$J$643,$B3, Deals_Raw!$K$5:$K$643,$D3 ) -> 0 | G3: =COUNTIFS( Deals_Raw!$AF$5:$AF$643,"Won", Deals_Raw!$G$5:$G$643,$A3, Deals_Raw!$J$5:$J$643,$B3, Deals_Raw!$K$5:$K$643,$D3 ) -> 0 | H3: 0 | I3: 0 | J3: =IFERROR( AVERAGEIFS( Deals_Raw!$AQ$5:$AQ$643, Deals_Raw!$AF$5:$AF$643,"Won", Deals_Raw!$G$5:$G$643,$A3, Deals_Raw!$J$5:$J$643,$B3, Deals_Raw!$K$5:$K$643,$D3 ),0) -> 0 | K3: =SUMIFS(Deals_Raw!$AQ$5:$AQ$643, Deals_Raw!$AF$5:$AF$643,"Won", Deals_Raw!$G$5:$G$643,$A3, Deals_Raw!$J$5:$J$643,$B3, Deals_Raw!$K$5:$K$643,$D3) -> 0 | L3: 0 | M3: =SUMIFS(Deals_Raw!$AS$5:$AS$643, Deals_Raw!$AF$5:$AF$643,"Won", Deals_Raw!$G$5:$G$643,$A3, Deals_Raw!$J$5:$J$643,$B3, Deals_Raw!$K$5:$K$643,$D3) -> 0 | N3: =K3/$O$2 -> 0
A4: Financial Services | B4: Enterprise | C4: =COUNTIFS(Deals_Raw!$G4:$G644, A4, Deals_Raw!$J4:$J644, B4) -> 16 | D4: Yes | E4: =COUNTIFS(Deals_Raw!$G4:$G644, A4, Deals_Raw!$J4:$J644, B4, Deals_Raw!$K4:K644, D4) -> 12 | F4: =COUNTIFS( Deals_Raw!$G$5:$G$643,$A4, Deals_Raw!$J$5:$J$643,$B4, Deals_Raw!$K$5:$K$643,$D4 ) -> 12 | G4: =COUNTIFS( Deals_Raw!$AF$5:$AF$643,"Won", Deals_Raw!$G$5:$G$643,$A4, Deals_Raw!$J$5:$J$643,$B4, Deals_Raw!$K$5:$K$643,$D4 ) -> 9 | H4: =G4/F4 -> 0.75 | I4: =AVERAGEIFS(Deals_Raw!$W$5:$W$643, Deals_Raw!$AF$5:$AF$643,"Won", Deals_Raw!$G$5:$G$643,$A4, Deals_Raw!$J$5:$J$643,$B4, Deals_Raw!$K$5:$K$643,$D4) -> 0.11 | J4: =IFERROR( AVERAGEIFS( Deals_Raw!$AQ$5:$AQ$643, Deals_Raw!$AF$5:$AF$643,"Won", Deals_Raw!$G$5:$G$643,$A4, Deals_Raw!$J$5:$J$643,$B4, Deals_Raw!$K$5:$K$643,$D4 ),0) -> 351516.49 | K4: =SUMIFS(Deals_Raw!$AQ$5:$AQ$643, Deals_Raw!$AF$5:$AF$643,"Won", Deals_Raw!$G$5:$G$643,$A4, Deals_Raw!$J$5:$J$643,$B4, Deals_Raw!$K$5:$K$643,$D4) -> 3163648.4 | L4: =AVERAGEIFS(Deals_Raw!$AT$5:$AT$643, Deals_Raw!$AF$5:$AF$643,"Won", Deals_Raw!$G$5:$G$643,$A4, Deals_Raw!$J$5:$J$643,$B4, Deals_Raw!$K$5:$K$643,$D4) -> 0.61969387 | M4: =SUMIFS(Deals_Raw!$AS$5:$AS$643, Deals_Raw!$AF$5:$AF$643,"Won", Deals_Raw!$G$5:$G$643,$A4, Deals_Raw!$J$5:$J$643,$B4, Deals_Raw!$K$5:$K$643,$D4) -> 1965728 | N4: =K4/$O$2 -> 0.039946703
A5: Legal | B5: SMB | C5: =COUNTIFS(Deals_Raw!$G5:$G645, A5, Deals_Raw!$J5:$J645, B5) -> 32 | D5: Yes | E5: =COUNTIFS(Deals_Raw!$G5:$G645, A5, Deals_Raw!$J5:$J645, B5, Deals_Raw!$K5:K645, D5) -> 0 | F5: =COUNTIFS( Deals_Raw!$G$5:$G$643,$A5, Deals_Raw!$J$5:$J$643,$B5, Deals_Raw!$K$5:$K$643,$D5 ) -> 0 | G5: =COUNTIFS( Deals_Raw!$AF$5:$AF$643,"Won", Deals_Raw!$G$5:$G$643,$A5, Deals_Raw!$J$5:$J$643,$B5, Deals_Raw!$K$5:$K$643,$D5 ) -> 0 | H5: 0 | I5: 0 | J5: =IFERROR( AVERAGEIFS( Deals_Raw!$AQ$5:$AQ$643, Deals_Raw!$AF$5:$AF$643,"Won", Deals_Raw!$G$5:$G$643,$A5, Deals_Raw!$J$5:$J$643,$B5, Deals_Raw!$K$5:$K$643,$D5 ),0) -> 0 | K5: =SUMIFS(Deals_Raw!$AQ$5:$AQ$643, Deals_Raw!$AF$5:$AF$643,"Won", Deals_Raw!$G$5:$G$643,$A5, Deals_Raw!$J$5:$J$643,$B5, Deals_Raw!$K$5:$K$643,$D5) -> 0 | L5: 0 | M5: =SUMIFS(Deals_Raw!$AS$5:$AS$643, Deals_Raw!$AF$5:$AF$643,"Won", Deals_Raw!$G$5:$G$643,$A5, Deals_Raw!$J$5:$J$643,$B5, Deals_Raw!$K$5:$K$643,$D5) -> 0 | N5: =K5/$O$2 -> 0
A6: Legal | B6: Mid-Market | C6: =COUNTIFS(Deals_Raw!$G6:$G646, A6, Deals_Raw!$J6:$J646, B6) -> 40 | D6: Yes | E6: =COUNTIFS(Deals_Raw!$G6:$G646, A6, Deals_Raw!$J6:$J646, B6, Deals_Raw!$K6:K646, D6) -> 2 | F6: =COUNTIFS( Deals_Raw!$G$5:$G$643,$A6, Deals_Raw!$J$5:$J$643,$B6, Deals_Raw!$K$5:$K$643,$D6 ) -> 2 | G6: =COUNTIFS( Deals_Raw!$AF$5:$AF$643,"Won", Deals_Raw!$G$5:$G$643,$A6, Deals_Raw!$J$5:$J$643,$B6, Deals_Raw!$K$5:$K$643,$D6) -> 1 | H6: =G6/F6 -> 0.5 | I6: =AVERAGEIFS( Deals_Raw!$W$5:$W$643, Deals_Raw!$AF$5:$AF$643,"Won", Deals_Raw!$G$5:$G$643,$A6, Deals_Raw!$J$5:$J$643,$B6, Deals_Raw!$K$5:$K$643,$D6 ) -> 0.071 | J6: =IFERROR( AVERAGEIFS( Deals_Raw!$AQ$5:$AQ$643, Deals_Raw!$AF$5:$AF$643,"Won", Deals_Raw!$G$5:$G$643,$A6, Deals_Raw!$J$5:$J$643,$B6, Deals_Raw!$K$5:$K$643,$D6 ),0) -> 289327.58 | K6: =SUMIFS(Deals_Raw!$AQ$5:$AQ$643, Deals_Raw!$AF$5:$AF$643,"Won", Deals_Raw!$G$5:$G$643,$A6, Deals_Raw!$J$5:$J$643,$B6, Deals_Raw!$K$5:$K$643,$D6) -> 289327.58 | L6: =AVERAGEIFS(Deals_Raw!$AT$5:$AT$643, Deals_Raw!$AF$5:$AF$643,"Won", Deals_Raw!$G$5:$G$643,$A6, Deals_Raw!$J$5:$J$643,$B6, Deals_Raw!$K$5:$K$643,$D6) -> 0.59915164 | M6: =SUMIFS(Deals_Raw!$AS$5:$AS$643, Deals_Raw!$AF$5:$AF$643,"Won", Deals_Raw!$G$5:$G$643,$A6, Deals_Raw!$J$5:$J$643,$B6, Deals_Raw!$K$5:$K$643,$D6) -> 173351.09 | N6: =K6/$O$2 -> 0.0036532766
A7: Legal | B7: Enterprise | C7: =COUNTIFS(Deals_Raw!$G7:$G647, A7, Deals_Raw!$J7:$J647, B7) -> 46 | D7: Yes | E7: =COUNTIFS(Deals_Raw!$G7:$G647, A7, Deals_Raw!$J7:$J647, B7, Deals_Raw!$K7:K647, D7) -> 27 | F7: =COUNTIFS( Deals_Raw!$G$5:$G$643,$A7, Deals_Raw!$J$5:$J$643,$B7, Deals_Raw!$K$5:$K$643,$D7 ) -> 27 | G7: =COUNTIFS( Deals_Raw!$AF$5:$AF$643,"Won", Deals_Raw!$G$5:$G$643,$A7, Deals_Raw!$J$5:$J$643,$B7, Deals_Raw!$K$5:$K$643,$D7 ) -> 19 | H7: =G7/F7 -> 0.7037037 | I7: =AVERAGEIFS( Deals_Raw!$W$5:$W$643, Deals_Raw!$AF$5:$AF$643,"Won", Deals_Raw!$G$5:$G$643,$A7, Deals_Raw!$J$5:$J$643,$B7, Deals_Raw!$K$5:$K$643,$D7 ) -> 0.11494737 | J7: =IFERROR( AVERAGEIFS( Deals_Raw!$AQ$5:$AQ$643, Deals_Raw!$AF$5:$AF$643,"Won", Deals_Raw!$G$5:$G$643,$A7, Deals_Raw!$J$5:$J$643,$B7, Deals_Raw!$K$5:$K$643,$D7 ),0) -> 507193 | K7: =SUMIFS(Deals_Raw!$AQ$5:$AQ$643, Deals_Raw!$AF$5:$AF$643,"Won", Deals_Raw!$G$5:$G$643,$A7, Deals_Raw!$J$5:$J$643,$B7, Deals_Raw!$K$5:$K$643,$D7) -> 9636666.9 | L7: =AVERAGEIFS(Deals_Raw!$AT$5:$AT$643, Deals_Raw!$AF$5:$AF$643,"Won", Deals_Raw!$G$5:$G$643,$A7, Deals_Raw!$J$5:$J$643,$B7, Deals_Raw!$K$5:$K$643,$D7) -> 0.62066097 | M7: =SUMIFS(Deals_Raw!$AS$5:$AS$643, Deals_Raw!$AF$5:$AF$643,"Won", Deals_Raw!$G$5:$G$643,$A7, Deals_Raw!$J$5:$J$643,$B7, Deals_Raw!$K$5:$K$643,$D7) -> 5797155.7 | N7: =K7/$O$2 -> 0.1216801
A8: Healthcare | B8: SMB | C8: =COUNTIFS(Deals_Raw!$G8:$G648, A8, Deals_Raw!$J8:$J648, B8) -> 35 | D8: Yes | E8: =COUNTIFS(Deals_Raw!$G8:$G648, A8, Deals_Raw!$J8:$J648, B8, Deals_Raw!$K8:K648, D8) -> 0 | F8: =COUNTIFS( Deals_Raw!$G$5:$G$643,$A8, Deals_Raw!$J$5:$J$643,$B8, Deals_Raw!$K$5:$K$643,$D8 ) -> 0 | G8: =COUNTIFS( Deals_Raw!$AF$5:$AF$643,"Won", Deals_Raw!$G$5:$G$643,$A8, Deals_Raw!$J$5:$J$643,$B8, Deals_Raw!$K$5:$K$643,$D8 ) -> 0 | H8: 0 | I8: 0 | J8: =IFERROR( AVERAGEIFS( Deals_Raw!$AQ$5:$AQ$643, Deals_Raw!$AF$5:$AF$643,"Won", Deals_Raw!$G$5:$G$643,$A8, Deals_Raw!$J$5:$J$643,$B8, Deals_Raw!$K$5:$K$643,$D8 ),0) -> 0 | K8: =SUMIFS(Deals_Raw!$AQ$5:$AQ$643, Deals_Raw!$AF$5:$AF$643,"Won", Deals_Raw!$G$5:$G$643,$A8, Deals_Raw!$J$5:$J$643,$B8, Deals_Raw!$K$5:$K$643,$D8) -> 0 | L8: 0 | M8: =SUMIFS(Deals_Raw!$AS$5:$AS$643, Deals_Raw!$AF$5:$AF$643,"Won", Deals_Raw!$G$5:$G$643,$A8, Deals_Raw!$J$5:$J$643,$B8, Deals_Raw!$K$5:$K$643,$D8) -> 0 | N8: =K8/$O$2 -> 0
A9: Healthcare | B9: Mid-Market | C9: =COUNTIFS(Deals_Raw!$G9:$G649, A9, Deals_Raw!$J9:$J649, B9) -> 26 | D9: Yes | E9: =COUNTIFS(Deals_Raw!$G9:$G649, A9, Deals_Raw!$J9:$J649, B9, Deals_Raw!$K9:K649, D9) -> 0 | F9: =COUNTIFS( Deals_Raw!$G$5:$G$643,$A9, Deals_Raw!$J$5:$J$643,$B9, Deals_Raw!$K$5:$K$643,$D9 ) -> 0 | G9: =COUNTIFS( Deals_Raw!$AF$5:$AF$643,"Won", Deals_Raw!$G$5:$G$643,$A9, Deals_Raw!$J$5:$J$643,$B9, Deals_Raw!$K$5:$K$643,$D9 ) -> 0 | H9: 0 | I9: 0 | J9: =IFERROR( AVERAGEIFS( Deals_Raw!$AQ$5:$AQ$643, Deals_Raw!$AF$5:$AF$643,"Won", Deals_Raw!$G$5:$G$643,$A9, Deals_Raw!$J$5:$J$643,$B9, Deals_Raw!$K$5:$K$643,$D9 ),0) -> 0 | K9: =SUMIFS(Deals_Raw!$AQ$5:$AQ$643, Deals_Raw!$AF$5:$AF$643,"Won", Deals_Raw!$G$5:$G$643,$A9, Deals_Raw!$J$5:$J$643,$B9, Deals_Raw!$K$5:$K$643,$D9) -> 0 | L9: 0 | M9: =SUMIFS(Deals_Raw!$AS$5:$AS$643, Deals_Raw!$AF$5:$AF$643,"Won", Deals_Raw!$G$5:$G$643,$A9, Deals_Raw!$J$5:$J$643,$B9, Deals_Raw!$K$5:$K$643,$D9) -> 0 | N9: =K9/$O$2 -> 0
A10: Healthcare | B10: Enterprise | C10: =COUNTIFS(Deals_Raw!$G10:$G650, A10, Deals_Raw!$J10:$J650, B10) -> 36 | D10: Yes | E10: =COUNTIFS(Deals_Raw!$G10:$G650, A10, Deals_Raw!$J10:$J650, B10, Deals_Raw!$K10:K650, D10) -> 17 | F10: =COUNTIFS( Deals_Raw!$G$5:$G$643,$A10, Deals_Raw!$J$5:$J$643,$B10, Deals_Raw!$K$5:$K$643,$D10 ) -> 17 | G10: =COUNTIFS( Deals_Raw!$AF$5:$AF$643,"Won", Deals_Raw!$G$5:$G$643,$A10, Deals_Raw!$J$5:$J$643,$B10, Deals_Raw!$K$5:$K$643,$D10) -> 12 | H10: =G10/F10 -> 0.70588235 | I10: =AVERAGEIFS( Deals_Raw!$W$5:$W$643, Deals_Raw!$AF$5:$AF$643,"Won", Deals_Raw!$G$5:$G$643,$A10, Deals_Raw!$J$5:$J$643,$B10, Deals_Raw!$K$5:$K$643,$D10 ) -> 0.11541667 | J10: =IFERROR( AVERAGEIFS( Deals_Raw!$AQ$5:$AQ$643, Deals_Raw!$AF$5:$AF$643,"Won", Deals_Raw!$G$5:$G$643,$A10, Deals_Raw!$J$5:$J$643,$B10, Deals_Raw!$K$5:$K$643,$D10 ),0) -> 445968.86 | K10: =SUMIFS(Deals_Raw!$AQ$5:$AQ$643, Deals_Raw!$AF$5:$AF$643,"Won", Deals_Raw!$G$5:$G$643,$A10, Deals_Raw!$J$5:$J$643,$B10, Deals_Raw!$K$5:$K$643,$D10) -> 5351626.4 | L10: =AVERAGEIFS(Deals_Raw!$AT$5:$AT$643, Deals_Raw!$AF$5:$AF$643,"Won", Deals_Raw!$G$5:$G$643,$A10, Deals_Raw!$J$5:$J$643,$B10, Deals_Raw!$K$5:$K$643,$D10) -> 0.62022112 | M10: =SUMIFS(Deals_Raw!$AS$5:$AS$643, Deals_Raw!$AF$5:$AF$643,"Won", Deals_Raw!$G$5:$G$643,$A10, Deals_Raw!$J$5:$J$643,$B10, Deals_Raw!$K$5:$K$643,$D10) -> 3359894.4 | N10: =K10/$O$2 -> 0.067573826
A11: Manufacturing | B11: SMB | C11: =COUNTIFS(Deals_Raw!$G11:$G651, A11, Deals_Raw!$J11:$J651, B11) -> 24 | D11: Yes | E11: =COUNTIFS(Deals_Raw!$G11:$G651, A11, Deals_Raw!$J11:$J651, B11, Deals_Raw!$K11:K651, D11) -> 6 | F11: =COUNTIFS( Deals_Raw!$G$5:$G$643,$A11, Deals_Raw!$J$5:$J$643,$B11, Deals_Raw!$K$5:$K$643,$D11 ) -> 6 | G11: =COUNTIFS( Deals_Raw!$AF$5:$AF$643,"Won", Deals_Raw!$G$5:$G$643,$A11, Deals_Raw!$J$5:$J$643,$B11, Deals_Raw!$K$5:$K$643,$D11 ) -> 5 | H11: =G11/F11 -> 0.83333333 | I11: =AVERAGEIFS( Deals_Raw!$W$5:$W$643, Deals_Raw!$AF$5:$AF$643,"Won", Deals_Raw!$G$5:$G$643,$A11, Deals_Raw!$J$5:$J$643,$B11, Deals_Raw!$K$5:$K$643,$D11 ) -> 0.1098 | J11: =IFERROR( AVERAGEIFS( Deals_Raw!$AQ$5:$AQ$643, Deals_Raw!$AF$5:$AF$643,"Won", Deals_Raw!$G$5:$G$643,$A11, Deals_Raw!$J$5:$J$643,$B11, Deals_Raw!$K$5:$K$643,$D11 ),0) -> 131560.07 | K11: =SUMIFS(Deals_Raw!$AQ$5:$AQ$643, Deals_Raw!$AF$5:$AF$643,"Won", Deals_Raw!$G$5:$G$643,$A11, Deals_Raw!$J$5:$J$643,$B11, Deals_Raw!$K$5:$K$643,$D11) -> 657800.35 | L11: =AVERAGEIFS(Deals_Raw!$AT$5:$AT$643, Deals_Raw!$AF$5:$AF$643,"Won", Deals_Raw!$G$5:$G$643,$A11, Deals_Raw!$J$5:$J$643,$B11, Deals_Raw!$K$5:$K$643,$D11) -> 0.60644682 | M11: =SUMIFS(Deals_Raw!$AS$5:$AS$643, Deals_Raw!$AF$5:$AF$643,"Won", Deals_Raw!$G$5:$G$643,$A11, Deals_Raw!$J$5:$J$643,$B11, Deals_Raw!$K$5:$K$643,$D11) -> 400151.68 | N11: =K11/$O$2 -> 0.0083059025
A12: Manufacturing | B12: Mid-Market | C12: =COUNTIFS(Deals_Raw!$G12:$G652, A12, Deals_Raw!$J12:$J652, B12) -> 41 | D12: Yes | E12: =COUNTIFS(Deals_Raw!$G12:$G652, A12, Deals_Raw!$J12:$J652, B12, Deals_Raw!$K12:K652, D12) -> 4 | F12: =COUNTIFS( Deals_Raw!$G$5:$G$643,$A12, Deals_Raw!$J$5:$J$643,$B12, Deals_Raw!$K$5:$K$643,$D12 ) -> 4 | G12: =COUNTIFS( Deals_Raw!$AF$5:$AF$643,"Won", Deals_Raw!$G$5:$G$643,$A12, Deals_Raw!$J$5:$J$643,$B12, Deals_Raw!$K$5:$K$643,$D12 ) -> 4 | H12: =G12/F12 -> 1 | I12: =AVERAGEIFS( Deals_Raw!$W$5:$W$643, Deals_Raw!$AF$5:$AF$643,"Won", Deals_Raw!$G$5:$G$643,$A12, Deals_Raw!$J$5:$J$643,$B12, Deals_Raw!$K$5:$K$643,$D12 ) -> 0.179 | J12: =IFERROR( AVERAGEIFS( Deals_Raw!$AQ$5:$AQ$643, Deals_Raw!$AF$5:$AF$643,"Won", Deals_Raw!$G$5:$G$643,$A12, Deals_Raw!$J$5:$J$643,$B12, Deals_Raw!$K$5:$K$643,$D12 ),0) -> 159086.74 | K12: =SUMIFS(Deals_Raw!$AQ$5:$AQ$643, Deals_Raw!$AF$5:$AF$643,"Won", Deals_Raw!$G$5:$G$643,$A12, Deals_Raw!$J$5:$J$643,$B12, Deals_Raw!$K$5:$K$643,$D12) -> 636346.97 | L12: =AVERAGEIFS(Deals_Raw!$AT$5:$AT$643, Deals_Raw!$AF$5:$AF$643,"Won", Deals_Raw!$G$5:$G$643,$A12, Deals_Raw!$J$5:$J$643,$B12, Deals_Raw!$K$5:$K$643,$D12) -> 0.60791132 | M12: =SUMIFS(Deals_Raw!$AS$5:$AS$643, Deals_Raw!$AF$5:$AF$643,"Won", Deals_Raw!$G$5:$G$643,$A12, Deals_Raw!$J$5:$J$643,$B12, Deals_Raw!$K$5:$K$643,$D12) -> 373292.62 | N12: =K12/$O$2 -> 0.0080350153
A13: Manufacturing | B13: Enterprise | C13: =COUNTIFS(Deals_Raw!$G13:$G653, A13, Deals_Raw!$J13:$J653, B13) -> 24 | D13: Yes | E13: =COUNTIFS(Deals_Raw!$G13:$G653, A13, Deals_Raw!$J13:$J653, B13, Deals_Raw!$K13:K653, D13) -> 5 | F13: =COUNTIFS( Deals_Raw!$G$5:$G$643,$A13, Deals_Raw!$J$5:$J$643,$B13, Deals_Raw!$K$5:$K$643,$D13 ) -> 5 | G13: =COUNTIFS( Deals_Raw!$AF$5:$AF$643,"Won", Deals_Raw!$G$5:$G$643,$A13, Deals_Raw!$J$5:$J$643,$B13, Deals_Raw!$K$5:$K$643,$D13 ) -> 4 | H13: =G13/F13 -> 0.8 | I13: =AVERAGEIFS( Deals_Raw!$W$5:$W$643, Deals_Raw!$AF$5:$AF$643,"Won", Deals_Raw!$G$5:$G$643,$A13, Deals_Raw!$J$5:$J$643,$B13, Deals_Raw!$K$5:$K$643,$D13 ) -> 0.16275 | J13: =IFERROR( AVERAGEIFS( Deals_Raw!$AQ$5:$AQ$643, Deals_Raw!$AF$5:$AF$643,"Won", Deals_Raw!$G$5:$G$643,$A13, Deals_Raw!$J$5:$J$643,$B13, Deals_Raw!$K$5:$K$643,$D13 ),0) -> 290999.28 | K13: =SUMIFS(Deals_Raw!$AQ$5:$AQ$643, Deals_Raw!$AF$5:$AF$643,"Won", Deals_Raw!$G$5:$G$643,$A13, Deals_Raw!$J$5:$J$643,$B13, Deals_Raw!$K$5:$K$643,$D13) -> 1163997.1 | L13: =AVERAGEIFS(Deals_Raw!$AT$5:$AT$643, Deals_Raw!$AF$5:$AF$643,"Won", Deals_Raw!$G$5:$G$643,$A13, Deals_Raw!$J$5:$J$643,$B13, Deals_Raw!$K$5:$K$643,$D13) -> 0.56428092 | M13: =SUMIFS(Deals_Raw!$AS$5:$AS$643, Deals_Raw!$AF$5:$AF$643,"Won", Deals_Raw!$G$5:$G$643,$A13, Deals_Raw!$J$5:$J$643,$B13, Deals_Raw!$K$5:$K$643,$D13) -> 665769.32 | N13: =K13/$O$2 -> 0.014697539
A14: Public Sector | B14: SMB | C14: =COUNTIFS(Deals_Raw!$G14:$G654, A14, Deals_Raw!$J14:$J654, B14) -> 37 | D14: Yes | E14: =COUNTIFS(Deals_Raw!$G14:$G654, A14, Deals_Raw!$J14:$J654, B14, Deals_Raw!$K14:K654, D14) -> 8 | F14: =COUNTIFS( Deals_Raw!$G$5:$G$643,$A14, Deals_Raw!$J$5:$J$643,$B14, Deals_Raw!$K$5:$K$643,$D14 ) -> 8 | G14: =COUNTIFS( Deals_Raw!$AF$5:$AF$643,"Won", Deals_Raw!$G$5:$G$643,$A14, Deals_Raw!$J$5:$J$643,$B14, Deals_Raw!$K$5:$K$643,$D14) -> 6 | H14: =G14/F14 -> 0.75 | I14: =AVERAGEIFS( Deals_Raw!$W$5:$W$643, Deals_Raw!$AF$5:$AF$643,"Won", Deals_Raw!$G$5:$G$643,$A14, Deals_Raw!$J$5:$J$643,$B14, Deals_Raw!$K$5:$K$643,$D14 ) -> 0.0905 | J14: =IFERROR( AVERAGEIFS( Deals_Raw!$AQ$5:$AQ$643, Deals_Raw!$AF$5:$AF$643,"Won", Deals_Raw!$G$5:$G$643,$A14, Deals_Raw!$J$5:$J$643,$B14, Deals_Raw!$K$5:$K$643,$D14 ),0) -> 128114.27 | K14: =SUMIFS(Deals_Raw!$AQ$5:$AQ$643, Deals_Raw!$AF$5:$AF$643,"Won", Deals_Raw!$G$5:$G$643,$A14, Deals_Raw!$J$5:$J$643,$B14, Deals_Raw!$K$5:$K$643,$D14) -> 768685.63 | L14: =AVERAGEIFS(Deals_Raw!$AT$5:$AT$643, Deals_Raw!$AF$5:$AF$643,"Won", Deals_Raw!$G$5:$G$643,$A14, Deals_Raw!$J$5:$J$643,$B14, Deals_Raw!$K$5:$K$643,$D14) -> 0.62203984 | M14: =SUMIFS(Deals_Raw!$AS$5:$AS$643, Deals_Raw!$AF$5:$AF$643,"Won", Deals_Raw!$G$5:$G$643,$A14, Deals_Raw!$J$5:$J$643,$B14, Deals_Raw!$K$5:$K$643,$D14) -> 472887.4 | N14: =K14/$O$2 -> 0.0097060269
A15: Public Sector | B15: Mid-Market | C15: =COUNTIFS(Deals_Raw!$G15:$G655, A15, Deals_Raw!$J15:$J655, B15) -> 54 | D15: Yes | E15: =COUNTIFS(Deals_Raw!$G15:$G655, A15, Deals_Raw!$J15:$J655, B15, Deals_Raw!$K15:K655, D15) -> 8 | F15: =COUNTIFS( Deals_Raw!$G$5:$G$643,$A15, Deals_Raw!$J$5:$J$643,$B15, Deals_Raw!$K$5:$K$643,$D15 ) -> 8 | G15: =COUNTIFS( Deals_Raw!$AF$5:$AF$643,"Won", Deals_Raw!$G$5:$G$643,$A15, Deals_Raw!$J$5:$J$643,$B15, Deals_Raw!$K$5:$K$643,$D15 ) -> 6 | H15: =G15/F15 -> 0.75 | I15: =AVERAGEIFS( Deals_Raw!$W$5:$W$643, Deals_Raw!$AF$5:$AF$643,"Won", Deals_Raw!$G$5:$G$643,$A15, Deals_Raw!$J$5:$J$643,$B15, Deals_Raw!$K$5:$K$643,$D15 ) -> 0.098333333 | J15: =IFERROR( AVERAGEIFS( Deals_Raw!$AQ$5:$AQ$643, Deals_Raw!$AF$5:$AF$643,"Won", Deals_Raw!$G$5:$G$643,$A15, Deals_Raw!$J$5:$J$643,$B15, Deals_Raw!$K$5:$K$643,$D15 ),0) -> 165469.44 | K15: =SUMIFS(Deals_Raw!$AQ$5:$AQ$643, Deals_Raw!$AF$5:$AF$643,"Won", Deals_Raw!$G$5:$G$643,$A15, Deals_Raw!$J$5:$J$643,$B15, Deals_Raw!$K$5:$K$643,$D15) -> 992816.63 | L15: =AVERAGEIFS(Deals_Raw!$AT$5:$AT$643, Deals_Raw!$AF$5:$AF$643,"Won", Deals_Raw!$G$5:$G$643,$A15, Deals_Raw!$J$5:$J$643,$B15, Deals_Raw!$K$5:$K$643,$D15) -> 0.62112928 | M15: =SUMIFS(Deals_Raw!$AS$5:$AS$643, Deals_Raw!$AF$5:$AF$643,"Won", Deals_Raw!$G$5:$G$643,$A15, Deals_Raw!$J$5:$J$643,$B15, Deals_Raw!$K$5:$K$643,$D15) -> 607641.31 | N15: =K15/$O$2 -> 0.01253608
A16: Public Sector | B16: Enterprise | C16: =COUNTIFS(Deals_Raw!$G16:$G656, A16, Deals_Raw!$J16:$J656, B16) -> 19 | D16: Yes | E16: =COUNTIFS(Deals_Raw!$G16:$G656, A16, Deals_Raw!$J16:$J656, B16, Deals_Raw!$K16:K656, D16) -> 7 | F16: =COUNTIFS( Deals_Raw!$G$5:$G$643,$A16, Deals_Raw!$J$5:$J$643,$B16, Deals_Raw!$K$5:$K$643,$D16 ) -> 7 | G16: =COUNTIFS( Deals_Raw!$AF$5:$AF$643,"Won", Deals_Raw!$G$5:$G$643,$A16, Deals_Raw!$J$5:$J$643,$B16, Deals_Raw!$K$5:$K$643,$D16 ) -> 3 | H16: =G16/F16 -> 0.42857143 | I16: =AVERAGEIFS( Deals_Raw!$W$5:$W$643, Deals_Raw!$AF$5:$AF$643,"Won", Deals_Raw!$G$5:$G$643,$A16, Deals_Raw!$J$5:$J$643,$B16, Deals_Raw!$K$5:$K$643,$D16 ) -> 0.086666667 | J16: =IFERROR( AVERAGEIFS( Deals_Raw!$AQ$5:$AQ$643, Deals_Raw!$AF$5:$AF$643,"Won", Deals_Raw!$G$5:$G$643,$A16, Deals_Raw!$J$5:$J$643,$B16, Deals_Raw!$K$5:$K$643,$D16 ),0) -> 291514.49 | K16: =SUMIFS(Deals_Raw!$AQ$5:$AQ$643, Deals_Raw!$AF$5:$AF$643,"Won", Deals_Raw!$G$5:$G$643,$A16, Deals_Raw!$J$5:$J$643,$B16, Deals_Raw!$K$5:$K$643,$D16) -> 874543.48 | L16: =AVERAGEIFS(Deals_Raw!$AT$5:$AT$643, Deals_Raw!$AF$5:$AF$643,"Won", Deals_Raw!$G$5:$G$643,$A16, Deals_Raw!$J$5:$J$643,$B16, Deals_Raw!$K$5:$K$643,$D16) -> 0.55185258 | M16: =SUMIFS(Deals_Raw!$AS$5:$AS$643, Deals_Raw!$AF$5:$AF$643,"Won", Deals_Raw!$G$5:$G$643,$A16, Deals_Raw!$J$5:$J$643,$B16, Deals_Raw!$K$5:$K$643,$D16) -> 492688.66 | N16: =K16/$O$2 -> 0.011042671
A17: Technology | B17: SMB | C17: =COUNTIFS(Deals_Raw!$G17:$G657, A17, Deals_Raw!$J17:$J657, B17) -> 26 | D17: Yes | E17: =COUNTIFS(Deals_Raw!$G17:$G657, A17, Deals_Raw!$J17:$J657, B17, Deals_Raw!$K17:K657, D17) -> 0 | F17: =COUNTIFS( Deals_Raw!$G$5:$G$643,$A17, Deals_Raw!$J$5:$J$643,$B17, Deals_Raw!$K$5:$K$643,$D17 ) -> 0 | G17: =COUNTIFS( Deals_Raw!$AF$5:$AF$643,"Won", Deals_Raw!$G$5:$G$643,$A17, Deals_Raw!$J$5:$J$643,$B17, Deals_Raw!$K$5:$K$643,$D17 ) -> 0 | H17: 0 | I17: 0 | J17: =IFERROR( AVERAGEIFS( Deals_Raw!$AQ$5:$AQ$643, Deals_Raw!$AF$5:$AF$643,"Won", Deals_Raw!$G$5:$G$643,$A17, Deals_Raw!$J$5:$J$643,$B17, Deals_Raw!$K$5:$K$643,$D17 ),0) -> 0 | K17: =SUMIFS(Deals_Raw!$AQ$5:$AQ$643, Deals_Raw!$AF$5:$AF$643,"Won", Deals_Raw!$G$5:$G$643,$A17, Deals_Raw!$J$5:$J$643,$B17, Deals_Raw!$K$5:$K$643,$D17) -> 0 | L17: 0 | M17: =SUMIFS(Deals_Raw!$AS$5:$AS$643, Deals_Raw!$AF$5:$AF$643,"Won", Deals_Raw!$G$5:$G$643,$A17, Deals_Raw!$J$5:$J$643,$B17, Deals_Raw!$K$5:$K$643,$D17) -> 0 | N17: =K17/$O$2 -> 0
A18: Technology | B18: Mid-Market | C18: =COUNTIFS(Deals_Raw!$G18:$G658, A18, Deals_Raw!$J18:$J658, B18) -> 77 | D18: Yes | E18: =COUNTIFS(Deals_Raw!$G18:$G658, A18, Deals_Raw!$J18:$J658, B18, Deals_Raw!$K18:K658, D18) -> 11 | F18: =COUNTIFS( Deals_Raw!$G$5:$G$643,$A18, Deals_Raw!$J$5:$J$643,$B18, Deals_Raw!$K$5:$K$643,$D18 ) -> 11 | G18: =COUNTIFS( Deals_Raw!$AF$5:$AF$643,"Won", Deals_Raw!$G$5:$G$643,$A18, Deals_Raw!$J$5:$J$643,$B18, Deals_Raw!$K$5:$K$643,$D18) -> 8 | H18: =G18/F18 -> 0.72727273 | I18: =AVERAGEIFS( Deals_Raw!$W$5:$W$643, Deals_Raw!$AF$5:$AF$643,"Won", Deals_Raw!$G$5:$G$643,$A18, Deals_Raw!$J$5:$J$643,$B18, Deals_Raw!$K$5:$K$643,$D18 ) -> 0.131 | J18: =IFERROR( AVERAGEIFS( Deals_Raw!$AQ$5:$AQ$643, Deals_Raw!$AF$5:$AF$643,"Won", Deals_Raw!$G$5:$G$643,$A18, Deals_Raw!$J$5:$J$643,$B18, Deals_Raw!$K$5:$K$643,$D18 ),0) -> 261881.19 | K18: =SUMIFS(Deals_Raw!$AQ$5:$AQ$643, Deals_Raw!$AF$5:$AF$643,"Won", Deals_Raw!$G$5:$G$643,$A18, Deals_Raw!$J$5:$J$643,$B18, Deals_Raw!$K$5:$K$643,$D18) -> 2095049.6 | L18: =AVERAGEIFS(Deals_Raw!$AT$5:$AT$643, Deals_Raw!$AF$5:$AF$643,"Won", Deals_Raw!$G$5:$G$643,$A18, Deals_Raw!$J$5:$J$643,$B18, Deals_Raw!$K$5:$K$643,$D18) -> 0.61045895 | M18: =SUMIFS(Deals_Raw!$AS$5:$AS$643, Deals_Raw!$AF$5:$AF$643,"Won", Deals_Raw!$G$5:$G$643,$A18, Deals_Raw!$J$5:$J$643,$B18, Deals_Raw!$K$5:$K$643,$D18) -> 1232770.7 | N18: =K18/$O$2 -> 0.026453737
A19: Technology | B19: Enterprise | C19: =COUNTIFS(Deals_Raw!$G19:$G659, A19, Deals_Raw!$J19:$J659, B19) -> 44 | D19: Yes | E19: =COUNTIFS(Deals_Raw!$G19:$G659, A19, Deals_Raw!$J19:$J659, B19, Deals_Raw!$K19:K659, D19) -> 31 | F19: =COUNTIFS( Deals_Raw!$G$5:$G$643,$A19, Deals_Raw!$J$5:$J$643,$B19, Deals_Raw!$K$5:$K$643,$D19 ) -> 31 | G19: =COUNTIFS( Deals_Raw!$AF$5:$AF$643,"Won", Deals_Raw!$G$5:$G$643,$A19, Deals_Raw!$J$5:$J$643,$B19, Deals_Raw!$K$5:$K$643,$D19 ) -> 20 | H19: =G19/F19 -> 0.64516129 | I19: =AVERAGEIFS( Deals_Raw!$W$5:$W$643, Deals_Raw!$AF$5:$AF$643,"Won", Deals_Raw!$G$5:$G$643,$A19, Deals_Raw!$J$5:$J$643,$B19, Deals_Raw!$K$5:$K$643,$D19 ) -> 0.1271 | J19: =IFERROR( AVERAGEIFS( Deals_Raw!$AQ$5:$AQ$643, Deals_Raw!$AF$5:$AF$643,"Won", Deals_Raw!$G$5:$G$643,$A19, Deals_Raw!$J$5:$J$643,$B19, Deals_Raw!$K$5:$K$643,$D19 ),0) -> 392232.04 | K19: =SUMIFS(Deals_Raw!$AQ$5:$AQ$643, Deals_Raw!$AF$5:$AF$643,"Won", Deals_Raw!$G$5:$G$643,$A19, Deals_Raw!$J$5:$J$643,$B19, Deals_Raw!$K$5:$K$643,$D19) -> 7844640.9 | L19: =AVERAGEIFS(Deals_Raw!$AT$5:$AT$643, Deals_Raw!$AF$5:$AF$643,"Won", Deals_Raw!$G$5:$G$643,$A19, Deals_Raw!$J$5:$J$643,$B19, Deals_Raw!$K$5:$K$643,$D19) -> 0.60265919 | M19: =SUMIFS(Deals_Raw!$AS$5:$AS$643, Deals_Raw!$AF$5:$AF$643,"Won", Deals_Raw!$G$5:$G$643,$A19, Deals_Raw!$J$5:$J$643,$B19, Deals_Raw!$K$5:$K$643,$D19) -> 4718963.5 | N19: =K19/$O$2 -> 0.09905258

Sheet Pricing_Analysis
D1: Discount_Approved | E1: Discount Band | F1: Total Deals | G1: Won Deals | H1: Win Rate | I1: Average Gross Margin
A2: Gross Annual Revenue | B2: 79196734 | D2: 0.06 | E2: =Deals_Raw!AU5 -> 5–10% | F2: =COUNTIF($E:$E,E2) -> 171 | G2: =COUNTIFS($E:$E,E2, Deals_Raw!AF:AF, "Won") -> 116 | H2: =G2/F2 -> 0.67836257 | I2: =AVERAGEIFS(Deals_Raw!$AT:$AT, $E:$E, E2, Deals_Raw!$AF:$AF, "Won") -> 0.60778781
A3: Total Gross Profit | B3: 47724181 | D3: 0.012 | E3: =Deals_Raw!AU6 -> 0–5% | F3: =COUNTIF($E:$E,E3) -> 79 | G3: =COUNTIFS($E:$E,E3, Deals_Raw!AF:AF, "Won") -> 55 | H3: =G3/F3 -> 0.69620253 | I3: =AVERAGEIFS(Deals_Raw!$AT:$AT, $E:$E, E3, Deals_Raw!$AF:$AF, "Won") -> 0.61352612
D4: 0.148 | E4: =Deals_Raw!AU7 -> 10–15% | F4: =COUNTIF($E:$E,E4) -> 189 | G4: =COUNTIFS($E:$E,E4, Deals_Raw!AF:AF, "Won") -> 113 | H4: =G4/F4 -> 0.5978836 | I4: =AVERAGEIFS(Deals_Raw!$AT:$AT, $E:$E, E4, Deals_Raw!$AF:$AF, "Won") -> 0.60366151
D5: 0.2 | E5: =Deals_Raw!AU8 -> 15–20% | F5: =COUNTIF($E:$E,E5) -> 149 | G5: =COUNTIFS($E:$E,E5, Deals_Raw!AF:AF, "Won") -> 108 | H5: =G5/F5 -> 0.72483221 | I5: =AVERAGEIFS(Deals_Raw!$AT:$AT, $E:$E, E5, Deals_Raw!$AF:$AF, "Won") -> 0.61267443
D6: 0.089 | E6: =Deals_Raw!AU9 -> 5–10% | F6: =COUNTIF($E:$E,E6) -> 171 | G6: =COUNTIFS($E:$E,E6, Deals_Raw!AF:AF, "Won") -> 116 | H6: =G6/F6 -> 0.67836257 | I6: =AVERAGEIFS(Deals_Raw!$AT:$AT, $E:$E, E6, Deals_Raw!$AF:$AF, "Won") -> 0.60778781
D7: 0.137 | E7: =Deals_Raw!AU10 -> 10–15% | F7: =COUNTIF($E:$E,E7) -> 189 | G7: =COUNTIFS($E:$E,E7, Deals_Raw!AF:AF, "Won") -> 113 | H7: =G7/F7 -> 0.5978836 | I7: =AVERAGEIFS(Deals_Raw!$AT:$AT, $E:$E, E7, Deals_Raw!$AF:$AF, "Won") -> 0.60366151
D8: 0.12 | E8: =Deals_Raw!AU11 -> 10–15% | F8: =COUNTIF($E:$E,E8) -> 189 | G8: =COUNTIFS($E:$E,E8, Deals_Raw!AF:AF, "Won") -> 113 | H8: =G8/F8 -> 0.5978836 | I8: =AVERAGEIFS(Deals_Raw!$AT:$AT, $E:$E, E8, Deals_Raw!$AF:$AF, "Won") -> 0.60366151
D9: 0.188 | E9: =Deals_Raw!AU12 -> 15–20% | F9: =COUNTIF($E:$E,E9) -> 149 | G9: =COUNTIFS($E:$E,E9, Deals_Raw!AF:AF, "Won") -> 108 | H9: =G9/F9 -> 0.72483221 | I9: =AVERAGEIFS(Deals_Raw!$AT:$AT, $E:$E, E9, Deals_Raw!$AF:$AF, "Won") -> 0.61267443
D10: 0.119 | E10: =Deals_Raw!AU13 -> 10–15% | F10: =COUNTIF($E:$E,E10) -> 189 | G10: =COUNTIFS($E:$E,E10, Deals_Raw!AF:AF, "Won") -> 113 | H10: =G10/F10 -> 0.5978836 | I10: =AVERAGEIFS(Deals_Raw!$AT:$AT, $E:$E, E10, Deals_Raw!$AF:$AF, "Won") -> 0.60366151
D11: 0.13 | E11: =Deals_Raw!AU14 -> 10–15% | F11: =COUNTIF($E:$E,E11) -> 189 | G11: =COUNTIFS($E:$E,E11, Deals_Raw!AF:AF, "Won") -> 113 | H11: =G11/F11 -> 0.5978836 | I11: =AVERAGEIFS(Deals_Raw!$AT:$AT, $E:$E, E11, Deals_Raw!$AF:$AF, "Won") -> 0.60366151
D12: 0.188 | E12: =Deals_Raw!AU15 -> 15–20% | F12: =COUNTIF($E:$E,E12) -> 149 | G12: =COUNTIFS($E:$E,E12, Deals_Raw!AF:AF, "Won") -> 108 | H12: =G12/F12 -> 0.72483221 | I12: =AVERAGEIFS(Deals_Raw!$AT:$AT, $E:$E, E12, Deals_Raw!$AF:$AF, "Won") -> 0.61267443
D13: 0.168 | E13: =Deals_Raw!AU16 -> 15–20% | F13: =COUNTIF($E:$E,E13) -> 149 | G13: =COUNTIFS($E:$E,E13, Deals_Raw!AF:AF, "Won") -> 108 | H13: =G13/F13 -> 0.72483221 | I13: =AVERAGEIFS(Deals_Raw!$AT:$AT, $E:$E, E13, Deals_Raw!$AF:$AF, "Won") -> 0.61267443
D14: 0.115 | E14: =Deals_Raw!AU17 -> 10–15% | F14: =COUNTIF($E:$E,E14) -> 189 | G14: =COUNTIFS($E:$E,E14, Deals_Raw!AF:AF, "Won") -> 113 | H14: =G14/F14 -> 0.5978836 | I14: =AVERAGEIFS(Deals_Raw!$AT:$AT, $E:$E, E14, Deals_Raw!$AF:$AF, "Won") -> 0.60366151
D15: 0.212 | E15: =Deals_Raw!AU18 -> 20–25% | F15: =COUNTIF($E:$E,E15) -> 41 | G15: =COUNTIFS($E:$E,E15, Deals_Raw!AF:AF, "Won") -> 29 | H15: =G15/F15 -> 0.70731707 | I15: =AVERAGEIFS(Deals_Raw!$AT:$AT, $E:$E, E15, Deals_Raw!$AF:$AF, "Won") -> 0.6163731
... D639: 0.129 | E639: =Deals_Raw!AU642 -> 10–15% | F639: =COUNTIF($E:$E,E639) -> 189 | G639: =COUNTIFS($E:$E,E639, Deals_Raw!AF:AF, "Won") -> 113 | H639: =G639/F639 -> 0.5978836 | I639: =AVERAGEIFS(Deals_Raw!$AT:$AT, $E:$E, E639, Deals_Raw!$AF:$AF, "Won") -> 0.60366151

Sheet Notes on dataset
A1: 1 | B1: The dataset excludes one-time implementation and onboarding fees. Therefore, List ACV represents the annual recurring list value of the software subscription only.

Sheet Pricing_Policy
A1: Pricing Policy
A4: Policy_Area | B4: Rule | C4: Threshold | D4: Unit | E4: Rationale | F4: Status
A5: Discount authority | B5: Sales Manager maximum | C5: 0.1 | D5: % | E5: Routine flexibility | F5: Active
A6: Discount authority | B6: Pricing Analyst maximum | C6: 0.2 | D6: % | E6: Moderate exceptions | F6: Active
A7: Discount authority | B7: Business Manager maximum | C7: 0.28 | D7: % | E7: High-value exceptions | F7: Active
A8: Discount authority | B8: VP Pricing required above | C8: 0.28 | D8: % | E8: Extreme concessions | F8: Active
A9: Margin | B9: Target gross margin | C9: 0.6 | D9: % | E9: Normal profitability target | F9: Active
A10: Margin | B10: Hard gross margin floor | C10: 0.45 | D10: % | E10: Below this requires executive exception | F10: Active
A11: Lifecycle | B11: Expansion requires active contract | C11: 1 | D11: Boolean | E11: Prevents invalid expansion records | F11: Active
A12: Lifecycle | B12: Win-back requires prior lost/churn event | C12: 1 | D12: Boolean | E12: Separates returning customers from new business | F12: Active

Sheet Analyst_Model
A1: Analyst Model — Formula-Driven Fields
A4: Deal_ID | B4: Deal_Date | C4: Customer_ID | D4: Customer | E4: Contract_ID | F4: Business_Unit | G4: Industry | H4: Region | I4: Sales_Territory | J4: Company_Size | K4: Strategic_Account | L4: Customer_Since | M4: Health_Score | N4: Product | O4: Deal_Type | P4: Expansion_Type | Q4: Contract_Years | R4: Seats | S4: Sales_Rep | T4: List_ACV | U4: Discount_Requested | V4: Discount_Approved | W4: Competitor_Gap_vs_Us | X4: Discount_Reason | Y4: Approval_Level | Z4: Final_Price | AA4: Cost_to_Serve | AB4: Proposed_Gross_Profit | AC4: Proposed_Gross_Margin | AD4: Deal_Status | AE4: Renewed | AF4: Expanded | AG4: Winback_Flag | AH4: Realized_Revenue | AI4: Realized_Gross_Profit | AJ4: Lifecycle_Notes | AK4: Customer_Tenure_Years | AL4: Price_Realization | AM4: Discount_Gap | AN4: Margin_Floor_Flag | AO4: Discount_Exception_Flag | AP4: Policy_Compliance_Flag | AQ4: AOV_Eligible | AR4: Realized_Margin | AS4: Customer_Product_Count
A5: =Deals_Raw!A5 -> D00003 | B5: =Deals_Raw!B5 -> 45646 | C5: =Deals_Raw!C5 -> C0001 | D5: =Deals_Raw!D5 -> LEG-0001 | E5: =Deals_Raw!E5 -> CT00001 | F5: =Deals_Raw!F5 -> Sales | G5: =Deals_Raw!G5 -> Legal | H5: =Deals_Raw!H5 -> South | ... T5: =Deals_Raw!T5 -> 157663.13 | U5: =Deals_Raw!V5 -> 0.066 | V5: =Deals_Raw!W5 -> 0.06 | W5: =Deals_Raw!X5 -> -0.119 | X5: =Deals_Raw!Y5 -> Renewal retention risk | Y5: =Deals_Raw!Z5 -> Sales Manager | Z5: =Deals_Raw!AA5 -> 148139.39 | AA5: =Deals_Raw!AC5 -> 61223.551 | AB5: =Deals_Raw!AD5 -> 86915.841 | AC5: =Deals_Raw!AE5 -> 0.5867166 | AD5: =Deals_Raw!AF5 -> Won | AE5: =Deals_Raw!AG5 -> Yes | AF5: =Deals_Raw!AH5 -> 0 | AG5: =Deals_Raw!AI5 -> No | AH5: =Deals_Raw!AJ5 -> 148139.39 | ... AJ5: =Deals_Raw!AL5 -> Renewal of existing active contract | AK5: =YEARFRAC(L5,B5) -> 4.8027778 | AL5: =IFERROR(Z5/T5,0) -> 0.9395944 | AM5: =U5-V5 -> 0.006 | AN5: =IF(AC5<Pricing_Policy!$C$10,"Below Floor","Pass") -> Pass | AO5: =IF(V5>Pricing_Policy!$C$7,"Exception","Standard") -> Standard | AP5: =IF(OR(AND(V5<=0.1,Y5<>"Sales Manager"),AND(V5>0.1,V5<=0.2,Y5<>"Pricing Analyst"),AND(V5>0.2,V5<=0.28,Y5<>"Business Manager"),AND(V5>0.28,Y5<>"VP Pricing")),"Review","Pass") -> Pass | AQ5: =IF(AD5="Won",1,0) -> 1 | AR5: =IFERROR(AI5/AH5,0) -> 0.5867166 | AS5: =COUNTIFS($C:$C,C5,$N:$N,N5) -> 3
A6: =Deals_Raw!A6 -> D00004 | B6: =Deals_Raw!B6 -> 45863 | C6: =Deals_Raw!C6 -> C0001 | D6: =Deals_Raw!D6 -> LEG-0001 | E6: =Deals_Raw!E6 -> CT00001 | F6: =Deals_Raw!F6 -> Sales | G6: =Deals_Raw!G6 -> Legal | H6: =Deals_Raw!H6 -> South | ... T6: =Deals_Raw!T6 -> 171556.91 | U6: =Deals_Raw!V6 -> 0.012 | V6: =Deals_Raw!W6 -> 0.012 | W6: =Deals_Raw!X6 -> 0.079 | X6: =Deals_Raw!Y6 -> Expansion opportunity | Y6: =Deals_Raw!Z6 -> Sales Manager | Z6: =Deals_Raw!AA6 -> 169511.06 | AA6: =Deals_Raw!AC6 -> 59147.753 | AB6: =Deals_Raw!AD6 -> 110363.3 | AC6: =Deals_Raw!AE6 -> 0.65106847 | AD6: =Deals_Raw!AF6 -> Won | AE6: =Deals_Raw!AG6 -> 0 | AF6: =Deals_Raw!AH6 -> Yes | AG6: =Deals_Raw!AI6 -> No | AH6: =Deals_Raw!AJ6 -> 169511.06 | ... AJ6: =Deals_Raw!AL6 -> Expansion allowed because contract was active | AK6: =YEARFRAC(L6,B6) -> 5.4 | AL6: =IFERROR(Z6/T6,0) -> 0.98807479 | AM6: =U6-V6 -> 0 | AN6: =IF(AC6<Pricing_Policy!$C$10,"Below Floor","Pass") -> Pass | AO6: =IF(V6>Pricing_Policy!$C$7,"Exception","Standard") -> Standard | AP6: =IF(OR(AND(V6<=0.1,Y6<>"Sales Manager"),AND(V6>0.1,V6<=0.2,Y6<>"Pricing Analyst"),AND(V6>0.2,V6<=0.28,Y6<>"Business Manager"),AND(V6>0.28,Y6<>"VP Pricing")),"Review","Pass") -> Pass | AQ6: =IF(AD6="Won",1,0) -> 1 | AR6: =IFERROR(AI6/AH6,0) -> 0.65106847 | AS6: =COUNTIFS($C:$C,C6,$N:$N,N6) -> 3
A7: =Deals_Raw!A7 -> D00005 | B7: =Deals_Raw!B7 -> 46011 | C7: =Deals_Raw!C7 -> C0001 | D7: =Deals_Raw!D7 -> LEG-0001 | E7: =Deals_Raw!E7 -> CT00001 | F7: =Deals_Raw!F7 -> Sales | G7: =Deals_Raw!G7 -> Legal | H7: =Deals_Raw!H7 -> South | ... T7: =Deals_Raw!T7 -> 183149.11 | U7: =Deals_Raw!V7 -> 0.167 | V7: =Deals_Raw!W7 -> 0.148 | W7: =Deals_Raw!X7 -> -0.02 | X7: =Deals_Raw!Y7 -> Renewal retention risk | Y7: =Deals_Raw!Z7 -> Pricing Analyst | Z7: =Deals_Raw!AA7 -> 155982.63 | AA7: =Deals_Raw!AC7 -> 64410.549 | AB7: =Deals_Raw!AD7 -> 91572.082 | AC7: =Deals_Raw!AE7 -> 0.58706589 | AD7: =Deals_Raw!AF7 -> Won | AE7: =Deals_Raw!AG7 -> Yes | AF7: =Deals_Raw!AH7 -> 0 | AG7: =Deals_Raw!AI7 -> No | AH7: =Deals_Raw!AJ7 -> 155982.63 | ... AJ7: =Deals_Raw!AL7 -> Renewal of existing active contract | AK7: =YEARFRAC(L7,B7) -> 5.8027778 | AL7: =IFERROR(Z7/T7,0) -> 0.85167015 | AM7: =U7-V7 -> 0.019 | AN7: =IF(AC7<Pricing_Policy!$C$10,"Below Floor","Pass") -> Pass | AO7: =IF(V7>Pricing_Policy!$C$7,"Exception","Standard") -> Standard | AP7: =IF(OR(AND(V7<=0.1,Y7<>"Sales Manager"),AND(V7>0.1,V7<=0.2,Y7<>"Pricing Analyst"),AND(V7>0.2,V7<=0.28,Y7<>"Business Manager"),AND(V7>0.28,Y7<>"VP Pricing")),"Review","Pass") -> Pass | AQ7: =IF(AD7="Won",1,0) -> 1 | AR7: =IFERROR(AI7/AH7,0) -> 0.58706589 | AS7: =COUNTIFS($C:$C,C7,$N:$N,N7) -> 3
A8: =Deals_Raw!A8 -> D00006 | B8: =Deals_Raw!B8 -> 45578 | C8: =Deals_Raw!C8 -> C0002 | D8: =Deals_Raw!D8 -> LEG-0002 | E8: =Deals_Raw!E8 -> CT00002 | F8: =Deals_Raw!F8 -> Finance | G8: =Deals_Raw!G8 -> Legal | H8: =Deals_Raw!H8 -> South | ... T8: =Deals_Raw!T8 -> 448091.47 | U8: =Deals_Raw!V8 -> 0.211 | V8: =Deals_Raw!W8 -> 0.2 | W8: =Deals_Raw!X8 -> 0.104 | X8: =Deals_Raw!Y8 -> Renewal retention risk | Y8: =Deals_Raw!Z8 -> Business Manager | Z8: =Deals_Raw!AA8 -> 358284.32 | AA8: =Deals_Raw!AC8 -> 180745.64 | AB8: =Deals_Raw!AD8 -> 177538.68 | AC8: =Deals_Raw!AE8 -> 0.49552456 | AD8: =Deals_Raw!AF8 -> Won | AE8: =Deals_Raw!AG8 -> 0 | AF8: =Deals_Raw!AH8 -> 0 | AG8: =Deals_Raw!AI8 -> No | AH8: =Deals_Raw!AJ8 -> 358284.32 | ... AJ8: =Deals_Raw!AL8 -> First purchase under this contract | AK8: =YEARFRAC(L8,B8) -> 1.7 | AL8: =IFERROR(Z8/T8,0) -> 0.79957854 | AM8: =U8-V8 -> 0.011 | AN8: =IF(AC8<Pricing_Policy!$C$10,"Below Floor","Pass") -> Pass | AO8: =IF(V8>Pricing_Policy!$C$7,"Exception","Standard") -> Standard | AP8: =IF(OR(AND(V8<=0.1,Y8<>"Sales Manager"),AND(V8>0.1,V8<=0.2,Y8<>"Pricing Analyst"),AND(V8>0.2,V8<=0.28,Y8<>"Business Manager"),AND(V8>0.28,Y8<>"VP Pricing")),"Review","Pass") -> Review | AQ8: =IF(AD8="Won",1,0) -> 1 | AR8: =IFERROR(AI8/AH8,0) -> 0.49552456 | AS8: =COUNTIFS($C:$C,C8,$N:$N,N8) -> 2
A9: =Deals_Raw!A9 -> D00007 | B9: =Deals_Raw!B9 -> 45943 | C9: =Deals_Raw!C9 -> C0002 | D9: =Deals_Raw!D9 -> LEG-0002 | E9: =Deals_Raw!E9 -> CT00002 | F9: =Deals_Raw!F9 -> Finance | G9: =Deals_Raw!G9 -> Legal | H9: =Deals_Raw!H9 -> South | ... T9: =Deals_Raw!T9 -> 470220.96 | U9: =Deals_Raw!V9 -> 0.147 | V9: =Deals_Raw!W9 -> 0.089 | W9: =Deals_Raw!X9 -> -0.086 | X9: =Deals_Raw!Y9 -> Multi-year commitment | Y9: =Deals_Raw!Z9 -> Sales Manager | Z9: =Deals_Raw!AA9 -> 428472.21 | AA9: =Deals_Raw!AC9 -> 163165.18 | AB9: =Deals_Raw!AD9 -> 265307.03 | AC9: =Deals_Raw!AE9 -> 0.61919309 | AD9: =Deals_Raw!AF9 -> Won | AE9: =Deals_Raw!AG9 -> Yes | AF9: =Deals_Raw!AH9 -> 0 | AG9: =Deals_Raw!AI9 -> No | AH9: =Deals_Raw!AJ9 -> 428472.21 | ... AJ9: =Deals_Raw!AL9 -> Renewal of existing active contract | AK9: =YEARFRAC(L9,B9) -> 2.7 | AL9: =IFERROR(Z9/T9,0) -> 0.91121462 | AM9: =U9-V9 -> 0.058 | AN9: =IF(AC9<Pricing_Policy!$C$10,"Below Floor","Pass") -> Pass | AO9: =IF(V9>Pricing_Policy!$C$7,"Exception","Standard") -> Standard | AP9: =IF(OR(AND(V9<=0.1,Y9<>"Sales Manager"),AND(V9>0.1,V9<=0.2,Y9<>"Pricing Analyst"),AND(V9>0.2,V9<=0.28,Y9<>"Business Manager"),AND(V9>0.28,Y9<>"VP Pricing")),"Review","Pass") -> Pass | AQ9: =IF(AD9="Won",1,0) -> 1 | AR9: =IFERROR(AI9/AH9,0) -> 0.61919309 | AS9: =COUNTIFS($C:$C,C9,$N:$N,N9) -> 2
A10: =Deals_Raw!A10 -> D00008 | B10: =Deals_Raw!B10 -> 45872 | C10: =Deals_Raw!C10 -> C0003 | D10: =Deals_Raw!D10 -> TEC-0003 | E10: =Deals_Raw!E10 -> CT00004 | F10: =Deals_Raw!F10 -> Legal | G10: =Deals_Raw!G10 -> Technology | H10: =Deals_Raw!H10 -> Northeast | ... T10: =Deals_Raw!T10 -> 30632.964 | U10: =Deals_Raw!V10 -> 0.148 | V10: =Deals_Raw!W10 -> 0.137 | W10: =Deals_Raw!X10 -> 0.054 | X10: =Deals_Raw!Y10 -> Expansion opportunity | Y10: =Deals_Raw!Z10 -> Pricing Analyst | Z10: =Deals_Raw!AA10 -> 26446.113 | AA10: =Deals_Raw!AC10 -> 8043.5155 | AB10: =Deals_Raw!AD10 -> 18402.598 | AC10: =Deals_Raw!AE10 -> 0.69585264 | AD10: =Deals_Raw!AF10 -> Won | AE10: =Deals_Raw!AG10 -> 0 | AF10: =Deals_Raw!AH10 -> Yes | AG10: =Deals_Raw!AI10 -> No | AH10: =Deals_Raw!AJ10 -> 26446.113 | ... AJ10: =Deals_Raw!AL10 -> Expansion allowed because contract was active | AK10: =YEARFRAC(L10,B10) -> 4.4222222 | AL10: =IFERROR(Z10/T10,0) -> 0.86332204 | AM10: =U10-V10 -> 0.011 | AN10: =IF(AC10<Pricing_Policy!$C$10,"Below Floor","Pass") -> Pass | AO10: =IF(V10>Pricing_Policy!$C$7,"Exception","Standard") -> Standard | AP10: =IF(OR(AND(V10<=0.1,Y10<>"Sales Manager"),AND(V10>0.1,V10<=0.2,Y10<>"Pricing Analyst"),AND(V10>0.2,V10<=0.28,Y10<>"Business Manager"),AND(V10>0.28,Y10<>"VP Pricing")),"Review","Pass") -> Pass | AQ10: =IF(AD10="Won",1,0) -> 1 | AR10: =IFERROR(AI10/AH10,0) -> 0.69585264 | AS10: =COUNTIFS($C:$C,C10,$N:$N,N10) -> 2
A11: =Deals_Raw!A11 -> D00009 | B11: =Deals_Raw!B11 -> 46012 | C11: =Deals_Raw!C11 -> C0003 | D11: =Deals_Raw!D11 -> TEC-0003 | E11: =Deals_Raw!E11 -> CT00004 | F11: =Deals_Raw!F11 -> Legal | G11: =Deals_Raw!G11 -> Technology | H11: =Deals_Raw!H11 -> Northeast | ... T11: =Deals_Raw!T11 -> 33055.576 | U11: =Deals_Raw!V11 -> 0.154 | V11: =Deals_Raw!W11 -> 0.12 | W11: =Deals_Raw!X11 -> -0.081 | X11: =Deals_Raw!Y11 -> Verified competitor pressure | Y11: =Deals_Raw!Z11 -> Pricing Analyst | Z11: =Deals_Raw!AA11 -> 29083.19 | AA11: =Deals_Raw!AC11 -> 8527.9708 | AB11: =Deals_Raw!AD11 -> 20555.219 | AC11: =Deals_Raw!AE11 -> 0.7067732 | AD11: =Deals_Raw!AF11 -> Won | AE11: =Deals_Raw!AG11 -> Yes | AF11: =Deals_Raw!AH11 -> 0 | AG11: =Deals_Raw!AI11 -> No | AH11: =Deals_Raw!AJ11 -> 29083.19 | ... AJ11: =Deals_Raw!AL11 -> Renewal of existing active contract | AK11: =YEARFRAC(L11,B11) -> 4.8055556 | AL11: =IFERROR(Z11/T11,0) -> 0.87982705 | AM11: =U11-V11 -> 0.034 | AN11: =IF(AC11<Pricing_Policy!$C$10,"Below Floor","Pass") -> Pass | AO11: =IF(V11>Pricing_Policy!$C$7,"Exception","Standard") -> Standard | AP11: =IF(OR(AND(V11<=0.1,Y11<>"Sales Manager"),AND(V11>0.1,V11<=0.2,Y11<>"Pricing Analyst"),AND(V11>0.2,V11<=0.28,Y11<>"Business Manager"),AND(V11>0.28,Y11<>"VP Pricing")),"Review","Pass") -> Pass | AQ11: =IF(AD11="Won",1,0) -> 1 | AR11: =IFERROR(AI11/AH11,0) -> 0.7067732 | AS11: =COUNTIFS($C:$C,C11,$N:$N,N11) -> 2
A12: =Deals_Raw!A12 -> D00010 | B12: =Deals_Raw!B12 -> 45567 | C12: =Deals_Raw!C12 -> C0004 | D12: =Deals_Raw!D12 -> FIN-0004 | E12: =Deals_Raw!E12 -> CT00005 | F12: =Deals_Raw!F12 -> Finance | G12: =Deals_Raw!G12 -> Financial Services | H12: =Deals_Raw!H12 -> West | ... T12: =Deals_Raw!T12 -> 64148.04 | U12: =Deals_Raw!V12 -> 0.189 | V12: =Deals_Raw!W12 -> 0.188 | W12: =Deals_Raw!X12 -> -0.013 | X12: =Deals_Raw!Y12 -> Verified competitor pressure | Y12: =Deals_Raw!Z12 -> Pricing Analyst | Z12: =Deals_Raw!AA12 -> 52095.758 | AA12: =Deals_Raw!AC12 -> 27124.236 | AB12: =Deals_Raw!AD12 -> 24971.522 | AC12: =Deals_Raw!AE12 -> 0.47933887 | AD12: =Deals_Raw!AF12 -> Won | AE12: =Deals_Raw!AG12 -> 0 | AF12: =Deals_Raw!AH12 -> 0 | AG12: =Deals_Raw!AI12 -> No | AH12: =Deals_Raw!AJ12 -> 52095.758 | ... AJ12: =Deals_Raw!AL12 -> First purchase under this contract | AK12: =YEARFRAC(L12,B12) -> 0.50277778 | AL12: =IFERROR(Z12/T12,0) -> 0.81211769 | AM12: =U12-V12 -> 0.001 | AN12: =IF(AC12<Pricing_Policy!$C$10,"Below Floor","Pass") -> Pass | AO12: =IF(V12>Pricing_Policy!$C$7,"Exception","Standard") -> Standard | AP12: =IF(OR(AND(V12<=0.1,Y12<>"Sales Manager"),AND(V12>0.1,V12<=0.2,Y12<>"Pricing Analyst"),AND(V12>0.2,V12<=0.28,Y12<>"Business Manager"),AND(V12>0.28,Y12<>"VP Pricing")),"Review","Pass") -> Pass | AQ12: =IF(AD12="Won",1,0) -> 1 | AR12: =IFERROR(AI12/AH12,0) -> 0.47933887 | AS12: =COUNTIFS($C:$C,C12,$N:$N,N12) -> 1
A13: =Deals_Raw!A13 -> D00011 | B13: =Deals_Raw!B13 -> 45821 | C13: =Deals_Raw!C13 -> C0004 | D13: =Deals_Raw!D13 -> FIN-0004 | E13: =Deals_Raw!E13 -> CT00006 | F13: =Deals_Raw!F13 -> Legal | G13: =Deals_Raw!G13 -> Financial Services | H13: =Deals_Raw!H13 -> West | ... T13: =Deals_Raw!T13 -> 223858.23 | U13: =Deals_Raw!V13 -> 0.167 | V13: =Deals_Raw!W13 -> 0.119 | W13: =Deals_Raw!X13 -> -0.049 | X13: =Deals_Raw!Y13 -> Strategic logo opportunity | Y13: =Deals_Raw!Z13 -> Pricing Analyst | Z13: =Deals_Raw!AA13 -> 197151.93 | AA13: =Deals_Raw!AC13 -> 94186.983 | AB13: =Deals_Raw!AD13 -> 102964.94 | AC13: =Deals_Raw!AE13 -> 0.52226192 | AD13: =Deals_Raw!AF13 -> Won | AE13: =Deals_Raw!AG13 -> 0 | AF13: =Deals_Raw!AH13 -> 0 | AG13: =Deals_Raw!AI13 -> No | AH13: =Deals_Raw!AJ13 -> 197151.93 | ... AJ13: =Deals_Raw!AL13 -> First purchase under this contract | AK13: =YEARFRAC(L13,B13) -> 1.2 | AL13: =IFERROR(Z13/T13,0) -> 0.88069993 | AM13: =U13-V13 -> 0.048 | AN13: =IF(AC13<Pricing_Policy!$C$10,"Below Floor","Pass") -> Pass | AO13: =IF(V13>Pricing_Policy!$C$7,"Exception","Standard") -> Standard | AP13: =IF(OR(AND(V13<=0.1,Y13<>"Sales Manager"),AND(V13>0.1,V13<=0.2,Y13<>"Pricing Analyst"),AND(V13>0.2,V13<=0.28,Y13<>"Business Manager"),AND(V13>0.28,Y13<>"VP Pricing")),"Review","Pass") -> Pass | AQ13: =IF(AD13="Won",1,0) -> 1 | AR13: =IFERROR(AI13/AH13,0) -> 0.52226192 | AS13: =COUNTIFS($C:$C,C13,$N:$N,N13) -> 1
A14: =Deals_Raw!A14 -> D00012 | B14: =Deals_Raw!B14 -> 45663 | C14: =Deals_Raw!C14 -> C0005 | D14: =Deals_Raw!D14 -> HEA-0005 | E14: =Deals_Raw!E14 -> CT00007 | F14: =Deals_Raw!F14 -> Technology | G14: =Deals_Raw!G14 -> Healthcare | H14: =Deals_Raw!H14 -> South | ... T14: =Deals_Raw!T14 -> 340477.39 | U14: =Deals_Raw!V14 -> 0.159 | V14: =Deals_Raw!W14 -> 0.13 | W14: =Deals_Raw!X14 -> -0.081 | X14: =Deals_Raw!Y14 -> Verified competitor pressure | Y14: =Deals_Raw!Z14 -> Pricing Analyst | Z14: =Deals_Raw!AA14 -> 296123.33 | AA14: =Deals_Raw!AC14 -> 134110.72 | AB14: =Deals_Raw!AD14 -> 162012.61 | AC14: =Deals_Raw!AE14 -> 0.54711193 | AD14: =Deals_Raw!AF14 -> Lost | AE14: =Deals_Raw!AG14 -> No | AF14: =Deals_Raw!AH14 -> 0 | AG14: =Deals_Raw!AI14 -> No | AH14: =Deals_Raw!AJ14 -> 0 | ... AJ14: =Deals_Raw!AL14 -> Renewal of existing active contract | AK14: =YEARFRAC(L14,B14) -> 4.6805556 | AL14: =IFERROR(Z14/T14,0) -> 0.86972978 | AM14: =U14-V14 -> 0.029 | AN14: =IF(AC14<Pricing_Policy!$C$10,"Below Floor","Pass") -> Pass | AO14: =IF(V14>Pricing_Policy!$C$7,"Exception","Standard") -> Standard | AP14: =IF(OR(AND(V14<=0.1,Y14<>"Sales Manager"),AND(V14>0.1,V14<=0.2,Y14<>"Pricing Analyst"),AND(V14>0.2,V14<=0.28,Y14<>"Business Manager"),AND(V14>0.28,Y14<>"VP Pricing")),"Review","Pass") -> Pass | AQ14: =IF(AD14="Won",1,0) -> 0 | AR14: =IFERROR(AI14/AH14,0) -> 0 | AS14: =COUNTIFS($C:$C,C14,$N:$N,N14) -> 2
A15: =Deals_Raw!A15 -> D00013 | B15: =Deals_Raw!B15 -> 45804 | C15: =Deals_Raw!C15 -> C0005 | D15: =Deals_Raw!D15 -> HEA-0005 | E15: =Deals_Raw!E15 -> CT00008 | F15: =Deals_Raw!F15 -> Legal | G15: =Deals_Raw!G15 -> Healthcare | H15: =Deals_Raw!H15 -> South | ... T15: =Deals_Raw!T15 -> 320597.41 | U15: =Deals_Raw!V15 -> 0.191 | V15: =Deals_Raw!W15 -> 0.188 | W15: =Deals_Raw!X15 -> -0.007 | X15: =Deals_Raw!Y15 -> Procurement requirement | Y15: =Deals_Raw!Z15 -> Pricing Analyst | Z15: =Deals_Raw!AA15 -> 260342.6 | AA15: =Deals_Raw!AC15 -> 126422.67 | AB15: =Deals_Raw!AD15 -> 133919.93 | AC15: =Deals_Raw!AE15 -> 0.51439882 | AD15: =Deals_Raw!AF15 -> Lost | AE15: =Deals_Raw!AG15 -> 0 | AF15: =Deals_Raw!AH15 -> 0 | AG15: =Deals_Raw!AI15 -> No | AH15: =Deals_Raw!AJ15 -> 0 | ... AJ15: =Deals_Raw!AL15 -> First purchase under this contract | AK15: =YEARFRAC(L15,B15) -> 5.0722222 | AL15: =IFERROR(Z15/T15,0) -> 0.8120546 | AM15: =U15-V15 -> 0.003 | AN15: =IF(AC15<Pricing_Policy!$C$10,"Below Floor","Pass") -> Pass | AO15: =IF(V15>Pricing_Policy!$C$7,"Exception","Standard") -> Standard | AP15: =IF(OR(AND(V15<=0.1,Y15<>"Sales Manager"),AND(V15>0.1,V15<=0.2,Y15<>"Pricing Analyst"),AND(V15>0.2,V15<=0.28,Y15<>"Business Manager"),AND(V15>0.28,Y15<>"VP Pricing")),"Review","Pass") -> Pass | AQ15: =IF(AD15="Won",1,0) -> 0 | AR15: =IFERROR(AI15/AH15,0) -> 0 | AS15: =COUNTIFS($C:$C,C15,$N:$N,N15) -> 2
A16: =Deals_Raw!A16 -> D00014 | B16: =Deals_Raw!B16 -> 45340 | C16: =Deals_Raw!C16 -> C0005 | D16: =Deals_Raw!D16 -> HEA-0005 | E16: =Deals_Raw!E16 -> CT00009 | F16: =Deals_Raw!F16 -> Finance | G16: =Deals_Raw!G16 -> Healthcare | H16: =Deals_Raw!H16 -> South | ... T16: =Deals_Raw!T16 -> 110842.81 | U16: =Deals_Raw!V16 -> 0.185 | V16: =Deals_Raw!W16 -> 0.168 | W16: =Deals_Raw!X16 -> -0.131 | X16: =Deals_Raw!Y16 -> Budget constraint | Y16: =Deals_Raw!Z16 -> Pricing Analyst | Z16: =Deals_Raw!AA16 -> 92186.507 | AA16: =Deals_Raw!AC16 -> 40259.459 | AB16: =Deals_Raw!AD16 -> 51927.049 | AC16: =Deals_Raw!AE16 -> 0.56328253 | AD16: =Deals_Raw!AF16 -> Lost | AE16: =Deals_Raw!AG16 -> No | AF16: =Deals_Raw!AH16 -> 0 | AG16: =Deals_Raw!AI16 -> No | AH16: =Deals_Raw!AJ16 -> 0 | ... AJ16: =Deals_Raw!AL16 -> Renewal of existing active contract | AK16: =YEARFRAC(L16,B16) -> 3.7972222 | AL16: =IFERROR(Z16/T16,0) -> 0.83168683 | AM16: =U16-V16 -> 0.017 | AN16: =IF(AC16<Pricing_Policy!$C$10,"Below Floor","Pass") -> Pass | AO16: =IF(V16>Pricing_Policy!$C$7,"Exception","Standard") -> Standard | AP16: =IF(OR(AND(V16<=0.1,Y16<>"Sales Manager"),AND(V16>0.1,V16<=0.2,Y16<>"Pricing Analyst"),AND(V16>0.2,V16<=0.28,Y16<>"Business Manager"),AND(V16>0.28,Y16<>"VP Pricing")),"Review","Pass") -> Pass | AQ16: =IF(AD16="Won",1,0) -> 0 | AR16: =IFERROR(AI16/AH16,0) -> 0 | AS16: =COUNTIFS($C:$C,C16,$N:$N,N16) -> 1
... A642: =Deals_Raw!A642 -> D00724 | B642: =Deals_Raw!B642 -> 45831 | C642: =Deals_Raw!C642 -> C0180 | D642: =Deals_Raw!D642 -> TEC-0180 | E642: =Deals_Raw!E642 -> CT00398 | F642: =Deals_Raw!F642 -> Legal | G642: =Deals_Raw!G642 -> Technology | H642: =Deals_Raw!H642 -> West | ... T642: =Deals_Raw!T642 -> 56101.806 | U642: =Deals_Raw!V642 -> 0.162 | V642: =Deals_Raw!W642 -> 0.129 | W642: =Deals_Raw!X642 -> -0.086 | X642: =Deals_Raw!Y642 -> Verified competitor pressure | Y642: =Deals_Raw!Z642 -> Pricing Analyst | Z642: =Deals_Raw!AA642 -> 48886.279 | AA642: =Deals_Raw!AC642 -> 18811.987 | AB642: =Deals_Raw!AD642 -> 30074.292 | AC642: =Deals_Raw!AE642 -> 0.61518882 | AD642: =Deals_Raw!AF642 -> Lost | AE642: =Deals_Raw!AG642 -> 0 | AF642: =Deals_Raw!AH642 -> 0 | AG642: =Deals_Raw!AI642 -> No | AH642: =Deals_Raw!AJ642 -> 0 | ... AJ642: =Deals_Raw!AL642 -> First purchase under this contract | AK642: =YEARFRAC(L642,B642) -> 6.8111111 | AL642: =IFERROR(Z642/T642,0) -> 0.87138513 | AM642: =U642-V642 -> 0.033 | AN642: =IF(AC642<Pricing_Policy!$C$10,"Below Floor","Pass") -> Pass | AO642: =IF(V642>Pricing_Policy!$C$7,"Exception","Standard") -> Standard | AP642: =IF(OR(AND(V642<=0.1,Y642<>"Sales Manager"),AND(V642>0.1,V642<=0.2,Y642<>"Pricing Analyst"),AND(V642>0.2,V642<=0.28,Y642<>"Business Manager"),AND(V642>0.28,Y642<>"VP Pricing")),"Review","Pass") -> Pass | AQ642: =IF(AD642="Won",1,0) -> 0 | AR642: =IFERROR(AI642/AH642,0) -> 0 | AS642: =COUNTIFS($C:$C,C642,$N:$N,N642) -> 1

Sheet Data_Dictionary
A1: Data Dictionary
A4: Field | B4: Level | C4: Definition | D4: Example | E4: Why It Matters | F4: Raw or Derived
A5: Customer_ID | B5: Customer | C5: Unique customer/company identifier | D5: C0001 | E5: Links all contracts and opportunities | F5: Raw
A6: Contract_ID | B6: Contract | C6: Unique agreement identifier | D6: CT00001 | E6: Separates multiple same-product contracts | F6: Raw
A7: Deal_ID | B7: Opportunity | C7: Unique commercial negotiation | D7: D00001 | E7: Primary key for opportunities | F7: Raw
A8: Customer_Since | B8: Customer | C8: First relationship date with NexusAI | D8: 05/01/2019 | E8: Used to calculate tenure | F8: Raw
A9: Customer_Tenure_Years | B9: Deal | C9: Years from Customer_Since to Deal_Date | D9: 5.2 | E9: Relationship age at each deal | F9: Derived
A10: Contract_Years | B10: Deal/Contract | C10: Length of this specific agreement | D10: 2 | E10: Different renewals can have different terms | F10: Raw
A11: Deal_Type | B11: Opportunity | C11: New Business, Renewal, Expansion, or Win-back | D11: Expansion | E11: Defines lifecycle stage | F11: Raw
A12: Expansion_Type | B12: Opportunity | C12: What grew within an active contract | D12: Seat Expansion | E12: Explains expansion economics | F12: Raw
A13: Price_Realization | B13: Deal | C13: Final Price divided by List ACV | D13: 82% | E13: Share of list value captured | F13: Derived
A14: Customer_Product_Count | B14: Deal | C14: Count of same customer-product opportunities | D14: 3 | E14: Helps identify repeat product activity | F14: Derived
A15: Winback_Flag | B15: Opportunity | C15: Yes when returning after churn/lost renewal | D15: Yes | E15: Prevents win-backs being counted as new business | F15: Raw

Sheet Lifecycle_Rules
A1: Lifecycle Rules
A4: Previous State | B4: Current Deal Type | C4: Allowed? | D4: Meaning | E4: Required Condition | F4: Example
A5: No contract | B5: New Business | C5: Yes | D5: First purchase | E5: No prior active contract for that Contract_ID | F5: First Analytics purchase
A6: Active contract | B6: Renewal | C6: Yes | D6: Continuation | E6: Contract is active and term is ending | F6: Annual renewal
A7: Active contract | B7: Expansion | C7: Yes | D7: Growth | E7: Contract is active | F7: More seats or module
A8: Churned/lost renewal | B8: Win-back | C8: Yes | D8: Customer returns | E8: Prior lost/churn event exists | F8: Returns six months later
A9: Active contract | B9: New Business | C9: No for same Contract_ID | D9: Would misclassify existing relationship | E9: Use Expansion or separate Contract_ID | F9: Second division needs own contract
A10: No active contract | B10: Expansion | C10: No | D10: Cannot expand absent active base | E10: Must first win New Business or Win-back | F10: Invalid sequence

Sheet Dashboard
A1: Dataset Overview
A4: KPI | B4: Value | D4: Deal Type | E4: Opportunities | F4: Won | G4: Win Rate | H4: Avg Discount | I4: Avg GM
A5: Customers | B5: =COUNTA(Customer_Master!A5:A184) -> 180 | D5: New Business | E5: =COUNTIF(Deals_Raw!O5:O642,D5) -> 202 | F5: =COUNTIFS(Deals_Raw!O5:O642,D5,Deals_Raw!AF5:AF642,"Won") -> 103 | G5: =IFERROR(F5/E5,0) -> 0.50990099 | H5: =IFERROR(SUMIFS(Deals_Raw!W5:W642,Deals_Raw!O5:O642,D5)/E5,0) -> 0.11766832 | I5: =IFERROR(SUMIFS(Deals_Raw!AE5:AE642,Deals_Raw!O5:O642,D5)/E5,0) -> 0.58033474
A6: Contracts | B6: =COUNTA(Contract_Master!A5:A402) -> 398 | D6: Renewal | E6: =COUNTIF(Deals_Raw!O5:O642,D6) -> 303 | F6: =COUNTIFS(Deals_Raw!O5:O642,D6,Deals_Raw!AF5:AF642,"Won") -> 223 | G6: =IFERROR(F6/E6,0) -> 0.7359736 | H6: =IFERROR(SUMIFS(Deals_Raw!W5:W642,Deals_Raw!O5:O642,D6)/E6,0) -> 0.11780198 | I6: =IFERROR(SUMIFS(Deals_Raw!AE5:AE642,Deals_Raw!O5:O642,D6)/E6,0) -> 0.62205756
A7: Opportunities | B7: =COUNTA(Deals_Raw!A5:A642) -> 638 | D7: Expansion | E7: =COUNTIF(Deals_Raw!O5:O642,D7) -> 89 | F7: =COUNTIFS(Deals_Raw!O5:O642,D7,Deals_Raw!AF5:AF642,"Won") -> 71 | G7: =IFERROR(F7/E7,0) -> 0.79775281 | H7: =IFERROR(SUMIFS(Deals_Raw!W5:W642,Deals_Raw!O5:O642,D7)/E7,0) -> 0.087494382 | I7: =IFERROR(SUMIFS(Deals_Raw!AE5:AE642,Deals_Raw!O5:O642,D7)/E7,0) -> 0.63031903
A8: Won Deals | B8: =COUNTIF(Deals_Raw!AF5:AF642,"Won") -> 427 | D8: Win-back | E8: =COUNTIF(Deals_Raw!O5:O642,D8) -> 44 | F8: =COUNTIFS(Deals_Raw!O5:O642,D8,Deals_Raw!AF5:AF642,"Won") -> 30 | G8: =IFERROR(F8/E8,0) -> 0.68181818 | H8: =IFERROR(SUMIFS(Deals_Raw!W5:W642,Deals_Raw!O5:O642,D8)/E8,0) -> 0.19236364 | I8: =IFERROR(SUMIFS(Deals_Raw!AE5:AE642,Deals_Raw!O5:O642,D8)/E8,0) -> 0.55946561
A9: Win Rate | B9: =B8/B7 -> 0.669279
A10: Realized Revenue | B10: =SUM(Deals_Raw!AJ5:AJ642) -> 79197172
A11: Average Order Value | B11: =B10/B8 -> 185473.47
A12: Realized Gross Margin | B12: =SUM(Deals_Raw!AK5:AK642)/SUM(Deals_Raw!AJ5:AJ642) -> 0.60260509

Sheet Report_Data_validation checks
A1: Check_ID | B1: Validation Check | C1: Business Rule | D1: Formula/Method | E1: Records Flagged | F1: Outcome | G1: Action
A2: 1 | B2: Deal Id Duplication | C2: Every opportunity must have a unique Deal_ID | D2: COUNTIF across Deals_Raw!A5:A643 | E2: 0 | F2: Pass | G2: None
A3: 2 | B3: Contract_ID | C3: Every opportunity must map to a valid contract | D3: Visual inspection of referenced Contract_ID column | E3: 0 | F3: Pass | G3: None
A4: 3 | B4: Annual Final Price | C4: Annual Final Price should equal List ACV × (1 − Approved Discount) | D4: Recalculated Final Price using Excel formula and compared against stored Final Price. | E4: 638 | G4: Identified a systematic reconciliation error. The stored Final Price values do not consistently match the published List ACV and Approved Discount. The discrepancy was attributed to internal dataset calculations rather than a pricing policy issue. Documented the finding and preserved the source data without overwriting it.Created a new AM and AN columns with validated annual final price and validated total final price
A5: 4 | B5: Discount Threshold & Approval Authority Compliance | C5: Approved discounts must fall within the organization's pricing approval thresholds and be authorized by the appropriate approval level. | D5: Compared Discount_Approved against the defined approval matrix (Sales Manager ≤10%, Pricing Analyst >10–20%, Business Manager >20–28%, VP Pricing >28%). | E5: 0 policy violations (2 VP-approved high-discount deals identified: 33.9% and 34.1%) | G5: All discounts complied with the approval policy. Two executive-approved high-discount deals were identified and flagged for downstream pricing analysis to evaluate whether the additional concessions were commercially justified or if pricing leverage remained on the table.
A6: 5 | B6: Gross Profit and Margin Reconciliation | C6: Gross Profit must equal Validated Annual Final Price − Cost to Serve. | D6: Recalculated Gross Profit using validated selling price and compared against stored Gross Profit. | E6: --- | F6: ------ | G6: -----
A7: 6 | B7: Gross Margin Floor Compliance | C7: Proposed Gross Margin should not fall below the company's minimum pricing floor of 45%. | D7: Compared Proposed_Gross_Margin against the 45% policy threshold using an IF statement to identify deals below the margin floor. | E7: 1 deal (AP568) | F7: Review (Commercial policy exception) | G7: One deal (AP568) with a gross margin of 44.7% was identified below the pricing policy floor. The deal has been flagged for commercial review to determine whether the reduced margin was strategically justified (e.g., competitive pressure, strategic account, renewal retention, or executive approval). The remaining deals complied with the company's minimum margin policy.
A8: 7

Sheet Pricing Analysis Log
A1: Check_ID | B1: Analysis | C1: Objective | D1: Method | E1: Finding | F1: Business Insight | G1: Notes
